Workbook

Sheet Facturación
A1: 7
B2: DATOS DE FACTURACIÓN
B3: Centro de costo principal | C3: Centro de costo específico
B4: RESERVAS
B6: CLIENTE - USUARIO
B7: Nombre | C7: Apellido | D7: Tipo | E7: ID | F7: Teléfono | G7: Dirección | H7: Ciudad | I7: Correo electrónico
B10: Forma de pago | C10: Estado de la factura | D10: Concepto | E10: Fecha | F10: Valor Usd | G10: Valor Pesos | H10: Recibo de caja
B15: Ingresos para terceros | C15: Ingresos propios MEDICAL TRIP | D15: Retención en la fuente _____ %
A18: Fecha SS | B18: Tercero | C18: Nit | D18: Fecha de factura | E18: Factura electrónica O documento soporte | F18: Montante total de la factura | G18: Servicio | H18: Ingresos para terceros de esta RVA
H35: =SUM(H19:H34) -> 0

Sheet Pasaporte - HC
G3: HILLARY
G4: MARY
G5: GORETTE
G6: KWIDAMA
G7: VALENTIJN
G8: Pasaporte
G9: NN93PD299
G10: 35252

Sheet COSTEO
V2: Libro diario contable | AD2: Factura electrónica
C3: PAGOS | S3: ESTADO DE CUENTA | V3: PAGOS | AD3: FACTURA
B4: ACV documentos | C4: Contabilidad | D4: Operativo | E4: Concepto | F4: Proveedor | G4: Valor | H4: Días | I4: HIllary | K4: Comisionable | L4: Usd | M4: Hillary | O4: Hillary | P4: Retención en la fuente | Q4: Valor pagado | S4: Valor Neto cobrado al cliente | T4: DIFERENCIA | V4: PROVEEDOR - NOMBRE COMERCIAL | W4: ID | X4: Fecha del pago | Y4: Valor del pago | Z4: Forma de pago de donde salió el dinero | AA4: Tipo de movimiento | AB4: Comentarios | AD4: Fecha de la factura | AE4: FACTURA O CUENTA COBRO | AF4: VALOR REAL DE LA FACTURA | AG4: CONCEPTO
C5: Facturado | D5: Confirmado | E5: DROSPERINONA (SLINDA) 4 mg caja x 28 tabletas x 7 cajas | F5: Cruz Verde | G5: 37440 | H5: 7 | I5: =G5*H5 -> 262080 | K5: =I5/0.8 -> 327600 | L5: =K5/$H$14 -> 86.210526 | M5: 50 | O5: =37440*4 -> 149760 | V5: CRUZ VERDE | X5: 45636 | Y5: 152260 | Z5: JENNY CUENTA PERSONAL BANCOLOMBIA
C6: Incluído | D6: Confirmado | E6: Domicilio casa en Medellin | F6: Cruz Verde | G6: 35000 | H6: 1 | I6: =G6*H6 -> 35000 | K6: =I6/0.8 -> 43750 | L6: =K6/$H$14 -> 11.513158 | M6: 10 | O6: =152260-O5 -> 2500
E7: Domicilio casa Medellin hotel del pasajero que lo lleve a Curazao | F7: Medical Trip Colombia | G7: 20000 | H7: 1 | I7: =G7*H7 -> 20000 | K7: 22000 | L7: =K7/$H$14 -> 5.7894737 | M7: 6
E8: Servicio de Medical Trip Colombia | F8: Medical Trip Colombia | G8: 35000 | H8: 1 | I8: =G8*H8 -> 35000 | K8: =I8/0.9 -> 38888.889 | L8: =K8/$H$14 -> 10.233918 | M8: 10 | O8: =2750*8 -> 22000 | P8: 0 | Q8: 22000
I9: =SUM(I5:I8) -> 352080 | K9: =SUM(K5:K8) -> 432238.89 | M9: =SUM(M5:M8) -> 76
H10: 0.18 | I10: =I9/0.82 -> 429365.85
G11: Gastos bancarios | H11: 4 * 1000 | I11: =I9*4/1000 -> 1408.32 | M11: =I11/$H$14 -> 0.37061053
G12: Gastos bancarios | H12: Transferencia nacional
G13: Gastos bancarios | H13: Transferencia internacional
G14: Tasa del dólar | H14: 3800 | I14: =SUM(I10:I13) -> 430774.17
I15: =I14/H14 -> 113.36162 | M15: =SUM(M9:M13) -> 76.370611

Sheet Detalle de los servicios
B4: DETALLE DE SERVICIOS | C4: Hillary
B5: =COSTEO!E5 -> DROSPERINONA (SLINDA) 4 mg caja x 28 tabletas x 7 cajas | C5: =COSTEO!K5 -> 327600
B6: =COSTEO!E6 -> Domicilio casa en Medellin | C6: =COSTEO!K6 -> 43750
B7: =COSTEO!E7 -> Domicilio casa Medellin hotel del pasajero que lo lleve a Curazao | C7: =COSTEO!K7 -> 22000
B8: =COSTEO!E8 -> Servicio de Medical Trip Colombia | C8: =COSTEO!K8 -> 38888.889
B9: Tarjeta de crédito 6% | C9: =432238*6% -> 25934.28
B10: VALOR TOTAL A PAGAR | C10: =SUM(C5:C9) -> 458173.17
