Workbook

Sheet Facturación
B2: DATOS DE FACTURACIÓN
B3: Centro de costo principal | C3: Centro de costo específico
B4: RESERVAS
B6: CLIENTE - USUARIO
B7: Nombre | C7: Apellido | D7: Tipo | E7: ID | F7: Teléfono | G7: Dirección | H7: Ciudad | I7: Correo electrónico
B10: Forma de pago | C10: Estado de la factura | D10: Concepto | E10: Fecha | F10: Valor Usd | G10: Valor Pesos | H10: Recibo de caja
B15: Ingresos para terceros | C15: Ingresos propios MEDICAL TRIP | D15: Retención en la fuente _____ %
A18: Fecha SS | B18: Tercero | C18: Nit | D18: Fecha de factura | E18: Factura electrónica O documento soporte | F18: Montante total de la factura | G18: Servicio | H18: Ingresos para terceros de esta RVA
H35: =SUM(H19:H34) -> 0

Sheet Pasaporte - HC
C16: Ruthmilda | D16: Pietersz
B19: Ruthmilda | C19: Cresencia | D19: Pietersz | E19: NY1FDD0K1
B20: Nombre | C20: Ruthmilda | D20: Pasaporte | E20: NY1FDD0K1
B21: Nombre | C21: Cresencia | D21: Fecha de nacimiento | E21: 18 de abril de 1955. | I21: Cedric | J21: Guzman | K21: Pietersz | L21: NT662PRR7
B22: Apellido | C22: Pietersz | D22: Edad | E22: 69 | H22: Nombre | I22: Cedric
H23: Nombre | I23: Guzman
B24: Padre | C24: Donato Pietersz | D24: Ruthmilda | E24: Pietersz | H24: Apellido | I24: Pietersz | K24: 27980
B25: Madre | C25: Argenpina Clarinda. | H25: Pasaporte | I25: NT662PRR7
B26: Estado civil
B27: Dirección | C27: Bacoenaweg25, Charo. | I27: cgpietersz@gmail.com
B28: País | C28: Curazao
B29: Email: | C29: cgpietersz@gmail.com
B30: Profesión | C30: pensionista.
B31: Teléfono | C31: =59995158448 -> 59995158448
B32: RH | C32: O+
B33: Seguro | C33: SVB
B34: Peso | C34: 71 kilos
B35: Altura | C35: 1.71 mts
B36: Idioma | C36: Idiomas: Inglés, Papiamento, Español.
B38: Salud
B45: IVS
B46: Usuario | C46: NY1FDD0K1
B47: Contraseña | C47: nY1FDD0K1*

Sheet COSTEO
F1: 910000
R2: Libro diario contable | Z2: Factura electrónica
B3: DOCUMENTOS | D3: PAGOS | E3: RESERVAS | M3: COMISIONABLE | O3: PRECIO VENTA | R3: PAGOS | W3: ESTADO DE CUENTA | Z3: PAGOS | AH3: FACTURA
B4: Ruthmilda | C4: Cedric | D4: Contabilidad | E4: Operativo | F4: Concepto | G4: Proveedor | H4: Valor | I4: Días | J4: Ruthmilda | K4: Cedric | M4: Ruthmilda | N4: Cedric | O4: Ruthmilda | P4: Cedric | R4: Ruthmilda | S4: Cedric | T4: Retención en la fuente | W4: Valor Neto cobrado al cliente | X4: DIFERENCIA | Z4: PROVEEDOR - NOMBRE COMERCIAL | AA4: ID | AB4: Fecha del pago | AC4: Valor del pago | AD4: Forma de pago de donde salió el dinero | AE4: Tipo de movimiento | AF4: Comentarios | AH4: Fecha de la factura | AI4: FACTURA O CUENTA COBRO | AJ4: VALOR REAL DE LA FACTURA | AK4: CONCEPTO
D5: Facturado | E5: Confirmado | F5: Domicilio | G5: Echavarria | H5: 35000 | I5: 1 | J5: =H5*I5 -> 35000 | M5: =J5 -> 35000 | O5: =M5/$I$58 -> 9.0909091 | R5: 21600 | T5: 0 | U5: =R5+S5-T5 -> 21600 | W5: =J5 -> 35000 | X5: =W5-U5 -> 13400 | Z5: Laboratorio Echavarría | AB5: 45763 | AC5: 641000 | AD5: Bancolombia Jurídica | AE5: Transferencia | AF5: Por cajero automático
B6: Archivado | D6: Facturado | E6: Confirmado | F6: Ferritina | G6: Echavarria | H6: 40000 | I6: 1 | J6: =H6*I6 -> 40000 | M6: =J6/0.6 -> 66666.667 | O6: =M6/$I$58 -> 17.316017 | R6: 27300 | T6: 0 | U6: =R6+S6-T6 -> 27300 | W6: =J6 -> 40000 | X6: =W6-U6 -> 12700
B7: Archivado | D7: Facturado | E7: Confirmado | F7: Hemograma completo | G7: Echavarria | H7: 30000 | I7: 1 | J7: =H7*I7 -> 30000 | M7: =J7/0.6 -> 50000 | O7: =M7/$I$58 -> 12.987013 | R7: 11550 | T7: 0 | U7: =R7+S7-T7 -> 11550 | W7: =J7 -> 30000 | X7: =W7-U7 -> 18450
B8: Archivado | D8: Facturado | E8: Confirmado | F8: T3 libre | G8: Echavarria | H8: 25000 | I8: 1 | J8: =H8*I8 -> 25000 | M8: =J8/0.6 -> 41666.667 | O8: =M8/$I$58 -> 10.822511 | R8: 17847 | T8: 0 | U8: =R8+S8-T8 -> 17847 | W8: =J8 -> 25000 | X8: =W8-U8 -> 7153
B9: Archivado | D9: Facturado | E9: Confirmado | F9: T4 libre | G9: Echavarria | H9: 25000 | I9: 1 | J9: =H9*I9 -> 25000 | M9: =J9/0.6 -> 41666.667 | O9: =M9/$I$58 -> 10.822511 | R9: 15200 | T9: 0 | U9: =R9+S9-T9 -> 15200 | W9: =J9 -> 25000 | X9: =W9-U9 -> 9800
B10: Archivado | D10: Facturado | E10: Confirmado | F10: Vitamina D 25 hidroxi | G10: Echavarria | H10: 45000 | I10: 1 | J10: =H10*I10 -> 45000 | M10: =J10/0.6 -> 75000 | O10: =M10/$I$58 -> 19.480519 | R10: 31500 | T10: 0 | U10: =R10+S10-T10 -> 31500 | W10: =J10 -> 45000 | X10: =W10-U10 -> 13500
B11: Archivado | D11: Facturado | E11: Confirmado | F11: Uroanálisis | G11: Echavarria | H11: 15000 | I11: 1 | J11: =H11*I11 -> 15000 | M11: =J11/0.6 -> 25000 | O11: =M11/$I$58 -> 6.4935065 | R11: 6300 | T11: 0 | U11: =R11+S11-T11 -> 6300 | W11: =J11 -> 15000 | X11: =W11-U11 -> 8700
B12: Archivado | D12: Facturado | E12: Confirmado | F12: ALT- Alanina transferasa | G12: Echavarria | H12: 20000 | I12: 1 | J12: =H12*I12 -> 20000 | M12: =J12/0.6 -> 33333.333 | O12: =M12/$I$58 -> 8.6580087 | R12: 6715 | T12: 0 | U12: =R12+S12-T12 -> 6715 | W12: =J12 -> 20000 | X12: =W12-U12 -> 13285
B13: Archivado | D13: Facturado | E13: Confirmado | F13: AST - aspartato transferasa | G13: Echavarria | H13: 20000 | I13: 1 | J13: =H13*I13 -> 20000 | M13: =J13/0.6 -> 33333.333 | O13: =M13/$I$58 -> 8.6580087 | R13: 6712 | T13: 0 | U13: =R13+S13-T13 -> 6712 | W13: =J13 -> 20000 | X13: =W13-U13 -> 13288
B14: Archivado | D14: Facturado | E14: Confirmado | F14: Bilirrubina total y directa | G14: Echavarria | H14: 22000 | I14: 1 | J14: =H14*I14 -> 22000 | M14: =J14/0.6 -> 36666.667 | O14: =M14/$I$58 -> 9.5238095 | R14: 8858 | T14: 0 | U14: =R14+S14-T14 -> 8858 | W14: =J14 -> 22000 | X14: =W14-U14 -> 13142
B15: Archivado | D15: Facturado | E15: Confirmado | F15: Colesterol HDL | G15: Echavarria | H15: 10000 | I15: 1 | J15: =H15*I15 -> 10000 | M15: =J15/0.6 -> 16666.667 | O15: =M15/$I$58 -> 4.3290043 | R15: 22464 | T15: 0 | U15: =R15+S15-T15 -> 22464 | W15: =J15 -> 10000 | X15: =W15-U15 -> -12464
B16: Archivado | D16: Facturado | E16: Confirmado | F16: Colesterol LDL | G16: Echavarria | H16: 12000 | I16: 1 | J16: =H16*I16 -> 12000 | M16: =J16/0.6 -> 20000 | O16: =M16/$I$58 -> 5.1948052 | T16: 0 | U16: =R16+S16-T16 -> 0 | W16: =J16 -> 12000 | X16: =W16-U16 -> 12000
B17: Archivado | D17: Facturado | E17: Confirmado | F17: Colesterol total | G17: Echavarria | H17: 15000 | I17: 1 | J17: =H17*I17 -> 15000 | M17: =J17/0.6 -> 25000 | O17: =M17/$I$58 -> 6.4935065 | T17: 0 | U17: =R17+S17-T17 -> 0 | W17: =J17 -> 15000 | X17: =W17-U17 -> 15000
B18: Archivado | D18: Facturado | E18: Confirmado | F18: Creatinina | G18: Echavarria | H18: 20000 | I18: 1 | J18: =H18*I18 -> 20000 | M18: =J18/0.6 -> 33333.333 | O18: =M18/$I$58 -> 8.6580087 | R18: 5783 | T18: 0 | U18: =R18+S18-T18 -> 5783 | W18: =J18 -> 20000 | X18: =W18-U18 -> 14217
B19: Archivado | D19: Facturado | E19: Confirmado | F19: Gamma glutamil transferasa | G19: Echavarria | H19: 34000 | I19: 1 | J19: =H19*I19 -> 34000 | M19: =J19/0.6 -> 56666.667 | O19: =M19/$I$58 -> 14.718615 | R19: 9239 | T19: 0 | U19: =R19+S19-T19 -> 9239 | W19: =J19 -> 34000 | X19: =W19-U19 -> 24761
B20: Archivado | D20: Facturado | E20: Confirmado | F20: Glucosa sérica | G20: Echavarria | H20: 20000 | I20: 1 | J20: =H20*I20 -> 20000 | M20: =J20/0.6 -> 33333.333 | O20: =M20/$I$58 -> 8.6580087 | R20: 5322 | T20: 0 | U20: =R20+S20-T20 -> 5322 | W20: =J20 -> 20000 | X20: =W20-U20 -> 14678
B21: Archivado | D21: Facturado | E21: Confirmado | F21: Triglicéridos | G21: Echavarria | H21: 10000 | I21: 1 | J21: =H21*I21 -> 10000 | M21: =J21/0.6 -> 16666.667 | O21: =M21/$I$58 -> 4.3290043 | T21: 0 | U21: =R21+S21-T21 -> 0 | W21: =J21 -> 10000 | X21: =W21-U21 -> 10000
B22: Archivado | D22: Facturado | E22: Confirmado | F22: TSH | G22: Echavarria | H22: 35000 | I22: 1 | J22: =H22*I22 -> 35000 | M22: =J22/0.6 -> 58333.333 | O22: =M22/$I$58 -> 15.151515 | R22: 24047 | T22: 0 | U22: =R22+S22-T22 -> 24047 | W22: =J22 -> 35000 | X22: =W22-U22 -> 10953
B23: Archivado | D23: Facturado | E23: Confirmado | F23: Anticuerpos de peroxidasa tiroidea (TPO Ab) - Tiroideos AC Microsomales | G23: Echavarria | H23: 70000 | I23: 1 | J23: =H23*I23 -> 70000 | M23: =J23/0.8 -> 87500 | O23: =M23/$I$58 -> 22.727273 | R23: 34050 | T23: 0 | U23: =R23+S23-T23 -> 34050 | W23: =J23 -> 70000 | X23: =W23-U23 -> 35950
B24: Archivado | D24: Facturado | E24: Confirmado | F24: Anticuerpos del receptor de tirotropina (TRAb) | G24: Echavarria | H24: 90000 | I24: 1 | J24: =H24*I24 -> 90000 | M24: =J24/0.8 -> 112500 | O24: =M24/$I$58 -> 29.220779 | R24: 114270 | T24: 0 | U24: =R24+S24-T24 -> 114270 | W24: =J24 -> 90000 | X24: =W24-U24 -> -24270
B25: Archivado | D25: Facturado | E25: Confirmado | F25: Autoanticuerpos de tiroglobulina (Tg Ab) Tiroides AC Tiroglobulinicos | G25: Echavarria | H25: 100000 | I25: 1 | J25: =H25*I25 -> 100000 | M25: =J25/0.75 -> 133333.33 | O25: =M25/$I$58 -> 34.632035 | R25: 34500 | T25: 0 | U25: =R25+S25-T25 -> 34500 | W25: =J25 -> 100000 | X25: =W25-U25 -> 65500
B26: Archivado | D26: Facturado | E26: Confirmado | F26: CA 19-9 Antígeno de cáncer de tubo digestivo | G26: Echavarria | H26: 75000 | I26: 1 | J26: =H26*I26 -> 75000 | M26: =J26/0.6 -> 125000 | O26: =M26/$I$58 -> 32.467532 | R26: 38400 | T26: 0 | U26: =R26+S26-T26 -> 38400 | W26: =J26 -> 75000 | X26: =W26-U26 -> 36600
B27: Archivado | D27: Facturado | E27: Confirmado | F27: CA-125 - Antígeno de cáncer de ovario | G27: Echavarria | H27: 58000 | I27: 1 | J27: =H27*I27 -> 58000 | M27: =J27/0.6 -> 96666.667 | O27: =M27/$I$58 -> 25.108225 | R27: 31500 | T27: 0 | U27: =R27+S27-T27 -> 31500 | W27: =J27 -> 58000 | X27: =W27-U27 -> 26500
B28: Archivado | D28: Facturado | E28: Confirmado | F28: Dimero D | G28: Echavarria | H28: 30000 | I28: 1 | J28: =H28*I28 -> 30000 | M28: =J28/0.6 -> 50000 | O28: =M28/$I$58 -> 12.987013 | R28: 26000 | T28: 0 | U28: =R28+S28-T28 -> 26000 | W28: =J28 -> 30000 | X28: =W28-U28 -> 4000
B29: Archivado | D29: Facturado | E29: Confirmado | F29: Homocisteína sérica (HCYSP) | G29: Echavarria | H29: 108000 | I29: 1 | J29: =H29*I29 -> 108000 | M29: =J29/0.8 -> 135000 | O29: =M29/$I$58 -> 35.064935 | R29: 107297 | T29: 0 | U29: =R29+S29-T29 -> 107297 | W29: =J29 -> 108000 | X29: =W29-U29 -> 703
B30: Archivado | D30: Facturado | E30: Confirmado | F30: Nitrógeno Ureico en Sangre (BUN) | G30: Echavarria | H30: 20000 | I30: 1 | J30: =H30*I30 -> 20000 | M30: =J30/0.6 -> 33333.333 | O30: =M30/$I$58 -> 8.6580087 | R30: 5520 | T30: 0 | U30: =R30+S30-T30 -> 5520 | W30: =J30 -> 20000 | X30: =W30-U30 -> 14480
B31: Archivado | D31: Facturado | E31: Confirmado | F31: CEA (carcinoembrionario Antígeno) | G31: Echavarria | H31: 60000 | I31: 1 | J31: =H31*I31 -> 60000 | M31: =J31/0.6 -> 100000 | O31: =M31/$I$58 -> 25.974026 | R31: 31141 | T31: 0 | U31: =R31+S31-T31 -> 31141 | W31: =J31 -> 60000 | X31: =W31-U31 -> 28859
B32: No se realizó | D32: DSM | E32: Confirmado | F32: Citología | G32: Idime | H32: 30000 | I32: 1 | J32: =H32*I32 -> 30000 | M32: =J32/0.6 -> 50000 | O32: =M32/$I$58 -> 12.987013 | R32: 17500 | T32: 0 | U32: =R32+S32-T32 -> 17500 | W32: =J32 -> 30000 | X32: =W32-U32 -> 12500 | Z32: IDIME | AB32: 45768
B33: Archivado | D33: DSM | E33: Confirmado | F33: CA 15-3 Antígeno de cáncer de mama | G33: Idime | H33: 78000 | I33: 1 | J33: =H33*I33 -> 78000 | M33: =J33/0.6 -> 130000 | O33: =M33/$I$58 -> 33.766234 | R33: 33600 | T33: 0 | U33: =R33+S33-T33 -> 33600 | W33: =J33 -> 78000 | X33: =W33-U33 -> 44400
B34: Archivado | D34: DSM | E34: Confirmado | F34: Antígeno leucocitario humano B27 (HLA-B27) | G34: Idime | H34: 116000 | I34: 1 | J34: =H34*I34 -> 116000 | M34: =J34/0.8 -> 145000 | O34: =M34/$I$58 -> 37.662338 | R34: 100000 | T34: 0 | U34: =R34+S34-T34 -> 100000 | W34: =J34 -> 116000 | X34: =W34-U34 -> 16000
B35: Archivado | D35: DSM | E35: Confirmado | F35: Hemoglobina Glicosilada | G35: Idime | H35: 35000 | I35: 1 | J35: =H35*I35 -> 35000 | M35: =J35/0.6 -> 58333.333 | O35: =M35/$I$58 -> 15.151515 | R35: 16100 | T35: 0 | U35: =R35+S35-T35 -> 16100 | W35: =J35 -> 35000 | X35: =W35-U35 -> 18900
B36: Archivado | D36: Facturado | E36: Confirmada | F36: Doppler arterial miembros inferiores | G36: CIMA | H36: 255000 | I36: 1 | J36: =H36*I36 -> 255000 | M36: =J36/0.8 -> 318750 | O36: =M36/$I$58 -> 82.792208 | R36: 190000 | T36: =(R36+S36)*2% -> 3800 | U36: =(R36+S36)-T36 -> 186200 | W36: =J36 -> 255000 | X36: =W36-U36 -> 68800 | Z36: CIMA | AB36: 45763 | AC36: 500000 | AD36: Bancolombia Jurídica | AE36: Transferencia | AF36: Por cajero automático
B37: Archivado | D37: Facturado | E37: Confirmada | F37: Doppler venoso de miembros inferiores | G37: CIMA | H37: 221000 | I37: 1 | J37: =H37*I37 -> 221000 | M37: =J37/0.8 -> 276250 | O37: =M37/$I$58 -> 71.753247 | R37: 190000 | T37: =(R37+S37)*2% -> 3800 | U37: =(R37+S37)-T37 -> 186200 | W37: =J37 -> 221000 | X37: =W37-U37 -> 34800
B38: Archivado | D38: Facturado | E38: Confirmada | F38: Prueba de esfuerzo | G38: In care | H38: 240000 | I38: 1 | J38: =H38*I38 -> 240000 | M38: =J38/0.8 -> 300000 | O38: =M38/$I$58 -> 77.922078 | R38: 204000 | T38: =(R38+S38)*2% -> 4080 | U38: =(R38+S38)-T38 -> 199920 | W38: =J38 -> 240000 | X38: =W38-R38 -> 36000 | Z38: Incare | AB38: 45763 | AC38: 200000 | AD38: Bancolombia Jurídica | AE38: Transferencia | AF38: Por cajero automático
B39: Archivado | D39: Facturado | E39: Confirmada | F39: Tomografía Axial Computarizada (TAC) Pelvis | G39: IVS | H39: 220000 | I39: 1 | J39: =H39*I39 -> 220000 | M39: =J39/0.8 -> 275000 | O39: =M39/$I$58 -> 71.428571 | R39: 195040 | T39: =(R39+S39)*2% -> 3900.8 | U39: =(R39+S39)-T39 -> 191139.2 | W39: =J39 -> 220000 | X39: =W39-R39 -> 24960 | Z39: IVS Imágenes salud y vida | AB39: 45763 | AC39: 69598 | AD39: Bancolombia Jurídica | AE39: Transferencia | AF39: Por cajero automático
B40: Archivado | D40: Facturado | E40: Confirmada | F40: Consulta con especialista en Urología | G40: Diego | H40: 280000 | I40: 1 | J40: =H40*I40 -> 280000 | M40: =J40/0.9 -> 311111.11 | O40: =M40/$I$58 -> 80.808081 | R40: 240000 | T40: 0 | U40: =(R40+S40)-T40 -> 240000 | W40: =J40 -> 280000 | X40: =W40-R40 -> 40000 | Z40: Diego Alejandro López Bernal | AB40: 45763 | AC40: 240000 | AD40: Bancolombia Jurídica | AE40: Transferencia | AF40: Por cajero automático
B41: Archivado | D41: DSM | E41: Confirmada | F41: Consulta con Medicina general - entrevista virtual planeación | G41: Marcos Yepes | H41: 80000 | I41: 1 | J41: =H41*I41 -> 80000 | M41: =J41/0.85 -> 94117.647 | O41: =M41/$I$58 -> 24.446142 | R41: 80000 | T41: =R41*10% -> 8000 | U41: =(R41+S41)-T41 -> 72000 | W41: =J41 -> 80000 | X41: =W41-R41 -> 0 | Z41: Marcos Yepes | AC41: 72000 | AD41: Jenny caja menor | AE41: Transferencia | AF41: Bancolombia Jenny
B42: Archivado | D42: DSM | E42: Confirmada | F42: Consulta con Medicina general - entrevista virtual revisión | G42: Marcos Yepes | H42: 80000 | I42: 1 | J42: =H42*I42 -> 80000 | M42: =J42/0.85 -> 94117.647 | O42: =M42/$I$58 -> 24.446142 | R42: 80000 | T42: =R42*10% -> 8000 | U42: =(R42+S42)-T42 -> 72000 | W42: =J42 -> 80000 | X42: =W42-R42 -> 0
B43: Archivado | C43: Archivado | D43: Facturado | E43: Emitido | F43: Póliza de asistencia médica al viajero - producto visitor por 05 días | G43: Colasistencia | H43: 3000 | I43: 8 | J43: =H43*I43 -> 24000 | K43: =H43*I43 -> 24000 | M43: =J43/0.6 -> 40000 | N43: =K43/0.6 -> 40000 | O43: =M43/$I$58 -> 10.38961 | P43: =N43/$I$58 -> 10.38961 | R43: =2750*8 -> 22000 | S43: =2750*8 -> 22000 | T43: 0 | U43: =R43+S43-T43 -> 44000 | W43: =J43+K43 -> 48000 | X43: =W43-R43 -> 26000 | Z43: Colasistencia | AB43: 45762 | AC43: 137500 | AD43: Bancolombia Jurídica | AE43: Por la página web | AF43: Tarjeta débito
D44: DSM | E44: Comprado | F44: Sim card | G44: Claro | H44: 6000 | I44: 1 | K44: =H44*I44 -> 6000 | N44: =K44/0.6 -> 10000 | P44: =N44/$I$58 -> 2.5974026 | S44: 22000 | T44: 0 | U44: =R44+S44-T44 -> 22000 | W44: =J44+K44 -> 6000 | X44: =W44-S44 -> -16000 | Z44: Claro | AB44: 45764 | AC44: 22000 | AD44: Jenny caja menor | AE44: Transferencia | AF44: Bancolombia Jenny
D45: Facturado | E45: Recargado | F45: Recarga de datos 10 GB * 7 días | G45: Claro | H45: 11500 | I45: 1 | K45: =H45*I45 -> 11500 | N45: =K45/0.85 -> 13529.412 | P45: =N45/$I$58 -> 3.5141329
D46: DSM | E46: Confirmado | F46: 08 Traslados one way para consultas médicas | H46: 32000 | I46: 8 | J46: =H46*I46 -> 256000 | M46: =J46/0.95 -> 269473.68 | N46: =K46/0.95 -> 0 | O46: =M46/$I$58 -> 69.993165 | P46: =N46/$I$58 -> 0 | Q46: =O46/8 -> 8.7491456
D47: Facturado | E47: Confirmado | F47: Traslado aeropuerto - hotel - aeropuerto | G47: Taxi van | H47: 135000 | I47: 2 | J47: =H47*I47/2 -> 135000 | K47: =H47*I47/2 -> 135000 | M47: =J47/0.9 -> 150000 | N47: =K47/0.9 -> 150000 | O47: =M47/$I$58 -> 38.961039 | P47: =N47/$I$58 -> 38.961039 | R47: 120000 | S47: 110000 | T47: 0 | U47: =R47+S47-T47 -> 230000 | W47: =J47+K47 -> 270000 | X47: =W47-U47 -> 40000 | Z47: Taxi van | AB47: 45763 | AC47: 230000 | AD47: Bancolombia Jurídica | AE47: Transferencia | AF47: Por cajero automático
D48: Facturado | E48: Confirmado | F48: Tour Comuna Trece compartido | G48: Aeroturex | H48: =79000-7900 -> 71100 | I48: 1 | J48: =H48*I48 -> 71100 | K48: =H48*I48 -> 71100 | M48: =J48/0.9 -> 79000 | N48: =K48/0.9 -> 79000 | O48: =M48/$I$58 -> 20.519481 | P48: =N48/$I$58 -> 20.519481 | R48: =J48+J49 -> 160200 | T48: 0 | U48: =R48+S48-T48 -> 160200 | W48: =U48 -> 160200 | X48: 0 | Z48: Aeroturex | AB48: 45763 | AC48: 160200 | AD48: Bancolombia Jurídica | AE48: Transferencia | AF48: Por cajero automático
D49: Facturado | E49: Confirmado | F49: Chiva Rumbera | G49: Aeroturex | H49: =99000-9900 -> 89100 | I49: 1 | J49: =H49*I49 -> 89100 | K49: =H49*I49 -> 89100 | M49: =J49/0.9 -> 99000 | N49: =K49/0.9 -> 99000 | O49: =M49/$I$58 -> 25.714286 | P49: =N49/$I$58 -> 25.714286 | S49: =K48+K49 -> 160200 | T49: 0 | U49: =R49+S49-T49 -> 160200 | W49: =U49 -> 160200 | X49: 0 | Z49: Aeroturex | AB49: 45789 | AC49: =160200+35000 -> 195200 | AD49: Jenny Bancolombia | AE49: Transferencia | AF49: Bancolombia Jenny
D50: No se pago | E50: Confirmado | F50: Medical Trip Colombia SAS - Acompañamiento virtual permanente en Español | G50: Jenny Acosta | H50: 250000 | I50: 0.5 | J50: =H50*I50 -> 125000 | M50: =J50/0.98 -> 127551.02 | N50: =K50/0.98 -> 0 | O50: =M50/$I$58 -> 33.130135 | P50: =N50/$I$58 -> 0
D51: DSM | E51: Confirmado | F51: Acompañamiento presencial en español para citas y exámenes | G51: Yenny Roberto | H51: 180000 | I51: 2 | J51: =H51*I51 -> 360000 | M51: =J51/0.98 -> 367346.94 | N51: =K51/0.98 -> 0 | O51: =M51/$I$58 -> 95.414789 | P51: =N51/$I$58 -> 0
D52: DSM | E52: Confirmado | F52: Caja menor | H52: 15000 | I52: 1 | J52: =H52*I52 -> 15000 | AB52: 45763 | AC52: 250000 | AD52: Bancolombia Jurídica | AE52: Retiro efectivo | AF52: Depósito nequi corresponsal
I53: Total neto | J53: =SUM(J6:J52) -> 3719200 | K53: =SUM(K6:K52) -> 336700 | O53: =SUM(O6:O52) -> 1226.4203 | P53: =SUM(P6:P52) -> 101.69595
I54: 0.2 | J54: =J53/0.79 -> 4707848.1 | K54: =K53/0.92 -> 365978.26
H55: Gastos bancarios | I55: 4 * 1000 | J55: =J54*4/1000 -> 18831.392 | K55: =K54*4/1000 -> 1463.913 | O55: =J55/I58 -> 4.8912708 | P55: =K55/J58 -> 0.00030814814
H56: Gastos bancarios | I56: Transferencia nacional | J56: =(6000*4) -> 24000 | O56: =J56/I58 -> 6.2337662 | P56: =K56/J58 -> 0
H57: Gastos bancarios | I57: Transferencia internacional
H58: Tasa del dólar | I58: 3850 | J58: =SUM(J54:J57) -> 4750679.5 | K58: =SUM(K54:K57) -> 367442.17 | O58: =SUM(O53:O57) -> 1237.5453 | P58: =SUM(P53:P57) -> 101.69626
J59: =J58/I58 -> 1233.9427 | K59: =K58/I58 -> 95.439526

Sheet CARPETA
B4: CARPETA RUTHMILDA
A6: Archivada | B6: Medicina general - Historia clínica - Entrevista virtual de planeación | C6: ok
A7: Archivada | B7: Medicina general - Historia clínica - Entrevista virtual de control | C7: ok
A8: Archivada | B8: *Laboratorios clínicos | C8: ok
B10: Historia clínica de Ginecología y Obstetricia | C10: ok
A11: Archivada | B11: *Ecografía pélvica dinámica | C11: ok
A13: Archivada | B13: Historia clínica de Urología | C13: ok
A14: Archivada | B14: *Tomografía Axial Computarizada (TAC) Pelvis | C14: ok
A15: Archivada | B15: *Cistología | C15: ok
A16: Archivada | B16: *Urodinamia | C16: ok
A18: Archivada | B18: Historia clínica de Cardiología
A19: Archivada | B19: *Doppler arterial miembros inferiores | C19: ok
A20: Archivada | B20: *Doppler venoso de miembros inferiores
A21: Archivada | B21: *Prueba de esfuerzo
B23: ESTUDIOS PENDIENTES X REALIZAR
B24: Tomografía coronoria
B25: Holter

Sheet ITINERARIO
B3: ITINERARIO:
B4: Dia | C4: Fecha | D4: Hora | E4: Actividad | F4: ACP horas | G4: Traslados
B5: 1 | C5: 45764 | D5: Jueves | E5: Día festivo - semana santa
D6: 10:26 pm | E6: Recibimiento en el aeropuerto
D7: 11:00 pm | E7: Traslado a aeropuerto - hotel en el Poblado
D8: 12:00 pm | E8: Alojamiento
B9: 2 | C9: 45765 | D9: Viernes | E9: Día festivo - semana santa
E10: Mañana libre
D11: 02:15 pm | E11: El tour sale y llega al parque el poblado
D12: 02:30 pm - 06:30 pm | E12: Tour compartido a la comuna trece
B13: 3 | C13: 45766 | D13: Sábado
E14: La noche anterior tomar un aromática y papaya a las 10pm
D15: 06:30 am | E15: Toma de muestras de sangre laboratorio clínico a domicilio en su hotel
E16: Desayuno ligero
D17: 10:00 am | E17: Traslado hotel - centro médico | F17: 0.5 | G17: 1
D18: 11:00 am | E18: =COSTEO!F39 -> Tomografía Axial Computarizada (TAC) Pelvis
D19: 12:00 pm | E19: Traslado centro médico hotel | G19: 1
E20: Tiempo para almorzar y descansar
D21: 06:45 pm | E21: El tour sale y llega al parque el poblado
D22: 07:00 pm - 11:00 pm | E22: Chiva rumbera
B23: 4 | C23: 45767 | D23: Domingo
E24: Día libre
B25: 5 | C25: 45768 | D25: Lunes
E26: La noche anterior tomar un aromática y papaya a las 10pm
D27: 06:00 am | E27: Encuentro en su hotel, para trasladarlo al centro médico | F27: 0.5 | G27: 1
D28: 06:30 am | E28: Toma de muestra de sangre
D29: 07:00 am | E29: Citología
D30: 07:30 am | E30: Traslado centro médico - centro médico
D31: 08:30 am | E31: =COSTEO!F36 -> Doppler arterial miembros inferiores
D32: 09:00am | E32: =COSTEO!F37 -> Doppler venoso de miembros inferiores
D33: 10:00 am | E33: Traslado centro médico - hotel | G33: 1
E34: Tiempo para desayunar
E35: Tiempo para Almorzar
D36: 01:00 pm | E36: Traslado hotel - centro médico | G36: 1
D37: 02:00 pm | E37: =COSTEO!F38 -> Prueba de esfuerzo | F37: 0.5
D38: 03:00 pm | E38: Consulta con especialista en Urología
E39: Traslado centro médico hotel | G39: 1
B40: 6 | C40: 45769 | D40: Martes
D41: 06:00 am | E41: Traslado Hotel - centro médico | F41: 1 | G41: 1
E42: =COSTEO!E40 -> Confirmada
E43: =COSTEO!E41 -> Confirmada
D44: 11:00 am | E44: Consulta con Urología
E45: Traslado centro médico - Hotel | G45: 1
D46: 03:15 pm | E46: Traslado Hotel - centro médico | G46: 1
D47: 04:00 pm | E47: =COSTEO!E43 -> Emitido
E48: =COSTEO!E44 -> Comprado
E49: Traslado centro médico - Hotel | G49: 1
B50: 7 | C50: 45770 | D50: Miércoles
D51: 11:15 pm | E51: Traslado Hotel - centro médico | F51: 0.5 | G51: 1
D52: 12:00 pm | E52: =COSTEO!E45 -> Recargado
D53: 01:00 pm | E53: Traslado centro médico - Hotel | G53: 1
E54: Tarde libre

Sheet Pago
F2: INCARE
C3: ECHAVARRIA | D3: IDIME | F3: =COSTEO!F38 -> Prueba de esfuerzo | G3: 204000
B4: =COSTEO!F5 -> Domicilio | C4: =COSTEO!R5 -> 21600 | G4: =G3*2% -> 4080
A5: 1 | B5: =COSTEO!F6 -> Ferritina | C5: =COSTEO!R6 -> 27300 | G5: =G3-G4 -> 199920
A6: 2 | B6: =COSTEO!F7 -> Hemograma completo | C6: =COSTEO!R7 -> 11550
A7: 3 | B7: =COSTEO!F8 -> T3 libre | C7: =COSTEO!R8 -> 17847
A8: 4 | B8: =COSTEO!F9 -> T4 libre | C8: =COSTEO!R9 -> 15200
A9: 5 | B9: =COSTEO!F10 -> Vitamina D 25 hidroxi | C9: =COSTEO!R10 -> 31500 | F9: =COSTEO!F36 -> Doppler arterial miembros inferiores | G9: 255000
A10: 6 | B10: =COSTEO!F11 -> Uroanálisis | C10: =COSTEO!R11 -> 6300 | F10: =COSTEO!F37 -> Doppler venoso de miembros inferiores | G10: 221000
A11: 7 | B11: =COSTEO!F12 -> ALT- Alanina transferasa | C11: =COSTEO!R12 -> 6715
A12: 8 | B12: =COSTEO!F13 -> AST - aspartato transferasa | C12: =COSTEO!R13 -> 6712 | F12: Total a facturar | G12: =SUM(G9:G10) -> 476000
A13: 9 | B13: =COSTEO!F14 -> Bilirrubina total y directa | C13: =COSTEO!R14 -> 8858 | F13: Retención en la fuente 2% | G13: =G12*2% -> 9520
A14: 10 | B14: Perfil lipidico | C14: =COSTEO!R15 -> 22464 | F14: Total a pagar | G14: =G12-G13 -> 466480
A15: 11 | B15: =COSTEO!F18 -> Creatinina | C15: =COSTEO!R18 -> 5783
A16: 12 | B16: =COSTEO!F19 -> Gamma glutamil transferasa | C16: =COSTEO!R19 -> 9239
A17: 13 | B17: =COSTEO!F20 -> Glucosa sérica | C17: =COSTEO!R20 -> 5322
A18: 14 | B18: =COSTEO!F22 -> TSH | C18: =COSTEO!R22 -> 24047
A19: 15 | B19: =COSTEO!F23 -> Anticuerpos de peroxidasa tiroidea (TPO Ab) - Tiroideos AC Microsomales | C19: =COSTEO!R23 -> 34050
A20: 16 | B20: =COSTEO!F24 -> Anticuerpos del receptor de tirotropina (TRAb) | C20: =COSTEO!R24 -> 114270
A21: 17 | B21: =COSTEO!F25 -> Autoanticuerpos de tiroglobulina (Tg Ab) Tiroides AC Tiroglobulinicos | C21: =COSTEO!R25 -> 34500
A22: 18 | B22: =COSTEO!F26 -> CA 19-9 Antígeno de cáncer de tubo digestivo | C22: =COSTEO!R26 -> 38400
A23: 19 | B23: =COSTEO!F27 -> CA-125 - Antígeno de cáncer de ovario | C23: =COSTEO!R27 -> 31500
A24: 20 | B24: =COSTEO!F28 -> Dimero D | C24: =COSTEO!R28 -> 26000
A25: 21 | B25: =COSTEO!F29 -> Homocisteína sérica (HCYSP) | C25: 104976
A26: 22 | B26: =COSTEO!F30 -> Nitrógeno Ureico en Sangre (BUN) | C26: =COSTEO!R30 -> 5520
A27: 23 | B27: =COSTEO!F31 -> CEA (carcinoembrionario Antígeno) | C27: =COSTEO!R31 -> 31141
B28: Total a pagar en Echavarría | C28: =SUM(C4:C27) -> 640794
B31: =COSTEO!F33 -> CA 15-3 Antígeno de cáncer de mama | C31: 33600
B32: =COSTEO!F34 -> Antígeno leucocitario humano B27 (HLA-B27) | C32: 100000
B33: =COSTEO!F35 -> Hemoglobina Glicosilada | C33: 16100
B34: Total a pagar en Idime | C34: =SUM(C31:C33) -> 149700
B36: 3043733052
B49: =COSTEO!F36 -> Doppler arterial miembros inferiores
B50: =COSTEO!F37 -> Doppler venoso de miembros inferiores
B51: =COSTEO!F38 -> Prueba de esfuerzo
B52: =COSTEO!F39 -> Tomografía Axial Computarizada (TAC) Pelvis
B53: =COSTEO!F40 -> Consulta con especialista en Urología
B54: =COSTEO!F41 -> Consulta con Medicina general - entrevista virtual planeación
B55: =COSTEO!F42 -> Consulta con Medicina general - entrevista virtual revisión
B56: =COSTEO!F43 -> Póliza de asistencia médica al viajero - producto visitor por 05 días
B57: =COSTEO!F44 -> Sim card
B58: =COSTEO!F45 -> Recarga de datos 10 GB * 7 días
B59: =COSTEO!F46 -> 08 Traslados one way para consultas médicas
B60: =COSTEO!F47 -> Traslado aeropuerto - hotel - aeropuerto
B61: =COSTEO!F50 -> Medical Trip Colombia SAS - Acompañamiento virtual permanente en Español
B62: =COSTEO!F51 -> Acompañamiento presencial en español para citas y exámenes
B63: =COSTEO!F52 -> Caja menor
B64: =COSTEO!F53
B65: =COSTEO!F54
B66: =COSTEO!F55
B67: =COSTEO!F56
B68: =COSTEO!F57
B69: =COSTEO!F58
B70: =COSTEO!F59
B71: =COSTEO!F60
B72: =COSTEO!F61
... B109: =COSTEO!F98

Sheet  Confirmación de 
B2: Fecha | C2: 45766
B3: Día | C3: Sábado
B4: Hora | C4: 06:00 am
B5: Sede | C5: Domicilio Laureles o Poblado
B6: Cliente | C6: Medical Trip Colombia SAS
B7: Correo | C7: reservasmedical@gmail.com
B8: Teléfono | C8: 315 772 1914
B9: Paciente Nombre | C9: Ruthmilda
B10: Paciente Apeliido | C10: Pietersz
B11: Pasaporte | C11: NY1FDD0K1
B12: Fecha de nacimiento | C12: 18 de abril de 1955.
B13: Servicio | C13: Exámenes de laboratorio cliníco para dos domicilios
B16: Fecha | C16: 45766 | K16: ALOJAMIENTO
B17: Hora | C17: 10:00 am | K17: Check in
B18: Sede | C18: IVS Punto Clave | K18: Check out
B19: Cliente | C19: Medical Trip Colombia SAS | K19: Record localizador
B20: Correo | C20: reservasmedical@gmail.com | K20: Dirección
B21: Teléfono | C21: 315 772 1914 | K21: Tipo de habitación
B22: Paciente Nombre | C22: Ruthmilda | K22: Desayuno
B23: Paciente Apeliido | C23: Pietersz
B24: Pasaporte | C24: NY1FDD0K1
B25: Fecha de nacimiento | C25: 18 de abril de 1955.
B26: Servicio | C26: Tomografía simple Axial Computarizada (TAC) Pelvis
C29: SOLICITUD DE RESERVA
B30: Fecha | C30: 45768
B31: Día | C31: Lunes
B32: Hora | C32: 08:30 am
B33: Sede | C33: Hernan Ocazionez - Poblado
B34: Cliente | C34: Medical Trip Colombia SAS
B35: Correo | C35: reservasmedical@gmail.com
B36: Teléfono | C36: 315 772 1914
B37: País | C37: Curazao
B38: Paciente Nombre | C38: Ruthmilda
B39: Paciente Apeliido | C39: Pietersz
B40: Pasaporte | C40: NY1FDD0K1
B41: Fecha de nacimiento | C41: 18 de abril de 1955.
B42: Servicio | C42: Ecografía de abdomen total
... B54: Servicio | C54: Prueba de esfuerzo
B57: Fecha | C57: 45768
B58: Hora | C58: 03:40 pm
B59: Sede | C59: El Tesoro
B60: Cliente | C60: Medical Trip Colombia SAS
B61: Correo | C61: reservasmedical@gmail.com
B62: Teléfono | C62: 315 772 1914
B63: Paciente Nombre | C63: Ruthmilda
B64: Paciente Apeliido | C64: Pietersz
B65: Pasaporte | C65: NY1FDD0K1
B66: Fecha de nacimiento | C66: 18 de abril de 1955.
B67: Servicio | C67: Cita con especialista en Urologia
C70: SOLICITUD DE RESERVA
B71: Servicio | C71: Citología
B72: Servicio | C72: Ecografía de abdomen total
B73: Servicio | C73: Doppler arterial miembros inferiores
B74: Servicio | C74: Doppler venoso miembros inferiores
B75: Fecha | C75: 45768
B76: Día | C76: Lunes
B77: Hora | C77: 08:00 am
B78: Sede | C78: Ciudad del Rio
B79: Cliente | C79: Medical Trip Colombia SAS
B80: Correo | C80: reservasmedical@gmail.com
B81: Teléfono | C81: 315 772 1914
B82: País | C82: Curazao
B83: Paciente Nombre | C83: Ruthmilda
B84: Paciente Apeliido | C84: Pietersz
B85: Pasaporte | C85: NY1FDD0K1
B86: Fecha de nacimiento | C86: 18 de abril de 1955.
C91: SOLICITUD DE RESERVA
B92: Fecha | C92: 45764
B93: Día | C93: Jueves
B94: Hora | C94: 0.9375
B95: RECOGIDA | C95: Aeropuerto José María Córdoba
B96: Vuelo | C96: AV 9314
B97: Ruta | C97: Bogotá - Medellín
B98: Pasajero | C98: Ruthmilda Pietersz - Cedric
B99: Pasaporte | C99: NY1FDD0K1
B100: Teléfono | C100: WhatsApp + 599 9 5158448
B101: DESTINO | C101: Hotel The Somos Calle 10 A No 40 - 19 El Poblado - Medellín
B102: No pasajeros | C102: Dos personas
B103: Equipaje | C103: 2 maletas de 23 kilos + 2 maletas de 10 kilos
B104: Tipo de vehículo | C104: Carro
B105: Cliente | C105: Medical Trip Colombia SAS
B106: Correo | C106: reservasmedical@gmail.com
... B108: Forma de pago | C108: Transferencia Medical Trip Colombia
C111: SOLICITUD DE RESERVA de TRANSPORTE
B112: Fecha | C112: 45771
B113: Día | C113: Jueves
B114: Hora | C114: 05:00 am
B115: RECOGIDA | C115: Hotel The Somos Calle 10 A No 40 - 19 El Poblado - Medellín
B116: Vuelo | C116: AV 9303
B117: Ruta | C117: Medellín - Bogotá
B118: Pasajero | C118: Ruthmilda Pietersz - Cedric Piertersz
B119: Pasaporte | C119: NY1FDD0K1
B120: Teléfono | C120: WhatsApp + 599 9 5158448
B121: DESTINO | C121: Aeropuerto José María Córdoba
B122: No pasajeros | C122: Dos personas
B123: Equipaje | C123: 2 maletas de 23 kilos + 2 maletas de 10 kilos
B124: Tipo de vehículo | C124: Carro
... B128: Forma de pago | C128: Transferencia Medical Trip Colombia
C131: SOLICITUD DE RESERVA
B132: Servicio | C132: TOUR COMPARTIDO COMUNA 13
...

Sheet Anterior cancelado - Copia de  
B2: Fecha | C2: 45766
B3: Día | C3: Sábado
B4: Hora | C4: 06:00 am
B5: Sede | C5: Domicilio Laureles o Poblado
B6: Cliente | C6: Medical Trip Colombia SAS
B7: Correo | C7: reservasmedical@gmail.com
B8: Teléfono | C8: 315 772 1914
B9: Paciente Nombre | C9: Ruthmilda
B10: Paciente Apeliido | C10: Pietersz
B11: Pasaporte | C11: NY1FDD0K1
B12: Fecha de nacimiento | C12: 18 de abril de 1955.
B13: Servicio | C13: Exámenes de laboratorio cliníco para dos domicilios
B16: Fecha | C16: 45766 | K16: ALOJAMIENTO
B17: Hora | C17: 10:00 am | K17: Check in
B18: Sede | C18: IVS Punto Clave | K18: Check out
B19: Cliente | C19: Medical Trip Colombia SAS | K19: Record localizador
B20: Correo | C20: reservasmedical@gmail.com | K20: Dirección
B21: Teléfono | C21: 315 772 1914 | K21: Tipo de habitación
B22: Paciente Nombre | C22: Ruthmilda | K22: Desayuno
B23: Paciente Apeliido | C23: Pietersz
B24: Pasaporte | C24: NY1FDD0K1
B25: Fecha de nacimiento | C25: 18 de abril de 1955.
B26: Servicio | C26: Tomografía simple Axial Computarizada (TAC) Pelvis
C29: SOLICITUD DE RESERVA
B30: Fecha | C30: 45768
B31: Día | C31: Lunes
B32: Hora | C32: 08:30 am
B33: Sede | C33: Hernan Ocazionez - Poblado
B34: Cliente | C34: Medical Trip Colombia SAS
B35: Correo | C35: reservasmedical@gmail.com
B36: Teléfono | C36: 315 772 1914
B37: País | C37: Curazao
B38: Paciente Nombre | C38: Ruthmilda
B39: Paciente Apeliido | C39: Pietersz
B40: Pasaporte | C40: NY1FDD0K1
B41: Fecha de nacimiento | C41: 18 de abril de 1955.
B42: Servicio | C42: Ecografía de abdomen total - CANCELADA
... B54: Servicio | C54: Prueba de esfuerzo
B57: Fecha | C57: 45768
B58: Hora | C58: 03:40 pm
B59: Sede | C59: El Tesoro
B60: Cliente | C60: Medical Trip Colombia SAS
B61: Correo | C61: reservasmedical@gmail.com
B62: Teléfono | C62: 315 772 1914
B63: Paciente Nombre | C63: Ruthmilda
B64: Paciente Apeliido | C64: Pietersz
B65: Pasaporte | C65: NY1FDD0K1
B66: Fecha de nacimiento | C66: 18 de abril de 1955.
B67: Servicio | C67: Cita con especialista en Urologia
C70: SOLICITUD DE RESERVA
B71: Fecha | C71: 45769
B72: Día | C72: Martes
B73: Hora | C73: 02:45 pm - 03:00 pm
B74: Sede | C74: El Tesoro
B75: Cliente | C75: Medical Trip Colombia SAS
B76: Correo | C76: reservasmedical@gmail.com
B77: Teléfono | C77: 315 772 1914
B78: País | C78: Curazao
B79: Paciente Nombre | C79: Ruthmilda
B80: Paciente Apeliido | C80: Pietersz
B81: Pasaporte | C81: NY1FDD0K1
B82: Fecha de nacimiento | C82: 18 de abril de 1955.
B83: Servicio | C83: Doppler arterial miembros inferiores
B84: Servicio | C84: Doppler venoso miembros inferiores
C88: SOLICITUD DE RESERVA
B89: Fecha | C89: 45764
B90: Día | C90: Jueves
B91: Hora | C91: 0.9375
B92: RECOGIDA | C92: Aeropuerto José María Córdoba
B93: Vuelo | C93: AV 9314
B94: Ruta | C94: Bogotá - Medellín
B95: Pasajero | C95: Ruthmilda Pietersz - Cedric
B96: Pasaporte | C96: NY1FDD0K1
B97: Teléfono | C97: WhatsApp + 599 9 5158448
B98: DESTINO | C98: Hotel The Somos Calle 10 A No 40 - 19 El Poblado - Medellín
B99: No pasajeros | C99: Dos personas
B100: Equipaje | C100: 2 maletas de 23 kilos + 2 maletas de 10 kilos
B101: Tipo de vehículo | C101: Carro
B102: Cliente | C102: Medical Trip Colombia SAS
B103: Correo | C103: reservasmedical@gmail.com
... B105: Forma de pago | C105: Transferencia Medical Trip Colombia
C108: SOLICITUD DE RESERVA de TRANSPORTE
B109: Fecha | C109: 45771
B110: Día | C110: Jueves
B111: Hora | C111: 05:00 am
B112: RECOGIDA | C112: Hotel The Somos Calle 10 A No 40 - 19 El Poblado - Medellín
B113: Vuelo | C113: AV 9303
B114: Ruta | C114: Medellín - Bogotá
B115: Pasajero | C115: Ruthmilda Pietersz - Cedric Piertersz
B116: Pasaporte | C116: NY1FDD0K1
B117: Teléfono | C117: WhatsApp + 599 9 5158448
B118: DESTINO | C118: Aeropuerto José María Córdoba
B119: No pasajeros | C119: Dos personas
B120: Equipaje | C120: 2 maletas de 23 kilos + 2 maletas de 10 kilos
B121: Tipo de vehículo | C121: Carro
... B125: Forma de pago | C125: Transferencia Medical Trip Colombia
C128: SOLICITUD DE RESERVA
B129: Servicio | C129: TOUR COMPARTIDO COMUNA 13
B130: Fecha | C130: 45765
B131: Día | C131: VIERNES
...

Sheet Detalle de los servicios
B3: DETALLE DE SERVICIOS | C3: RUTHMILDA | D3: CEDRIC
B4: =COSTEO!F6 -> Ferritina | C4: =COSTEO!O6 -> 17.316017
B5: =COSTEO!F7 -> Hemograma completo | C5: =COSTEO!O7 -> 12.987013
B6: =COSTEO!F8 -> T3 libre | C6: =COSTEO!O8 -> 10.822511
B7: =COSTEO!F9 -> T4 libre | C7: =COSTEO!O9 -> 10.822511
B8: =COSTEO!F10 -> Vitamina D 25 hidroxi | C8: =COSTEO!O10 -> 19.480519
B9: =COSTEO!F11 -> Uroanálisis | C9: =COSTEO!O11 -> 6.4935065
B10: =COSTEO!F32 -> Citología | C10: =COSTEO!O32 -> 12.987013
B11: =COSTEO!F12 -> ALT- Alanina transferasa | C11: =COSTEO!O12 -> 8.6580087
B12: =COSTEO!F13 -> AST - aspartato transferasa | C12: =COSTEO!O13 -> 8.6580087
B13: =COSTEO!F14 -> Bilirrubina total y directa | C13: =COSTEO!O14 -> 9.5238095
B14: =COSTEO!F15 -> Colesterol HDL | C14: =COSTEO!O15 -> 4.3290043
B15: =COSTEO!F16 -> Colesterol LDL | C15: =COSTEO!O16 -> 5.1948052
B16: =COSTEO!F17 -> Colesterol total | C16: =COSTEO!O17 -> 6.4935065
B17: =COSTEO!F18 -> Creatinina | C17: =COSTEO!O18 -> 8.6580087
B18: =COSTEO!F19 -> Gamma glutamil transferasa | C18: =COSTEO!O19 -> 14.718615
B19: =COSTEO!F20 -> Glucosa sérica | C19: =COSTEO!O20 -> 8.6580087
B20: =COSTEO!F35 -> Hemoglobina Glicosilada | C20: =COSTEO!O35 -> 15.151515
B21: =COSTEO!F21 -> Triglicéridos | C21: =COSTEO!O21 -> 4.3290043
B22: =COSTEO!F22 -> TSH | C22: =COSTEO!O22 -> 15.151515
B23: =COSTEO!F5 -> Domicilio | C23: =COSTEO!O5 -> 9.0909091
B24: =COSTEO!F23 -> Anticuerpos de peroxidasa tiroidea (TPO Ab) - Tiroideos AC Microsomales | C24: =COSTEO!O23 -> 22.727273
B25: =COSTEO!F24 -> Anticuerpos del receptor de tirotropina (TRAb) | C25: =COSTEO!O24 -> 29.220779
B26: =COSTEO!F34 -> Antígeno leucocitario humano B27 (HLA-B27) | C26: =COSTEO!O34 -> 37.662338
B27: =COSTEO!F25 -> Autoanticuerpos de tiroglobulina (Tg Ab) Tiroides AC Tiroglobulinicos | C27: =COSTEO!O25 -> 34.632035
B28: =COSTEO!F33 -> CA 15-3 Antígeno de cáncer de mama | C28: =COSTEO!O33 -> 33.766234
B29: =COSTEO!F26 -> CA 19-9 Antígeno de cáncer de tubo digestivo | C29: =COSTEO!O26 -> 32.467532
B30: =COSTEO!F27 -> CA-125 - Antígeno de cáncer de ovario | C30: =COSTEO!O27 -> 25.108225
B31: =COSTEO!F28 -> Dimero D | C31: =COSTEO!O28 -> 12.987013
B32: =COSTEO!F29 -> Homocisteína sérica (HCYSP) | C32: =COSTEO!O29 -> 35.064935
B33: =COSTEO!F30 -> Nitrógeno Ureico en Sangre (BUN) | C33: =COSTEO!O30 -> 8.6580087
B34: =COSTEO!F31 -> CEA (carcinoembrionario Antígeno) | C34: =COSTEO!O31 -> 25.974026
B35: =COSTEO!F36 -> Doppler arterial miembros inferiores | C35: =COSTEO!O36 -> 82.792208
B36: =COSTEO!F37 -> Doppler venoso de miembros inferiores | C36: =COSTEO!O37 -> 71.753247
B37: =COSTEO!F38 -> Prueba de esfuerzo | C37: =COSTEO!O38 -> 77.922078
B38: =COSTEO!F39 -> Tomografía Axial Computarizada (TAC) Pelvis | C38: =COSTEO!O39 -> 71.428571
B39: =COSTEO!F40 -> Consulta con especialista en Urología | C39: =COSTEO!O40 -> 80.808081
B40: =COSTEO!F41 -> Consulta con Medicina general - entrevista virtual planeación | C40: =COSTEO!O41 -> 24.446142
B41: =COSTEO!F42 -> Consulta con Medicina general - entrevista virtual revisión | C41: =COSTEO!O42 -> 24.446142
B42: =COSTEO!F43 -> Póliza de asistencia médica al viajero - producto visitor por 05 días | C42: =COSTEO!O43 -> 10.38961 | D42: =COSTEO!P43 -> 10.38961
B43: =COSTEO!F44 -> Sim card | C43: =COSTEO!O44 | D43: =COSTEO!P44 -> 2.5974026
B44: =COSTEO!F45 -> Recarga de datos 10 GB * 7 días | C44: =COSTEO!O45 | D44: =COSTEO!P45 -> 3.5141329
B45: =COSTEO!F46 -> 08 Traslados one way para consultas médicas | C45: =COSTEO!O46 -> 69.993165
B46: =COSTEO!F47 -> Traslado aeropuerto - hotel - aeropuerto | C46: =COSTEO!O47 -> 38.961039 | D46: =COSTEO!P47 -> 38.961039
B47: =COSTEO!F48 -> Tour Comuna Trece compartido | C47: =COSTEO!O48 -> 20.519481 | D47: =COSTEO!P48 -> 20.519481
B48: =COSTEO!F49 -> Chiva Rumbera | C48: =COSTEO!O49 -> 25.714286 | D48: =COSTEO!P49 -> 25.714286
B49: =COSTEO!F50 -> Medical Trip Colombia SAS - Acompañamiento virtual permanente en Español | C49: =COSTEO!O50 -> 33.130135
B50: =COSTEO!F51 -> Acompañamiento presencial en español para citas y exámenes | C50: =COSTEO!O51 -> 95.414789
B51: =COSTEO!I55 -> 4 * 1000 | C51: =COSTEO!O55 -> 4.8912708
B52: =COSTEO!I56 -> Transferencia nacional | C52: =COSTEO!O56 -> 6.2337662
B53: PRECIO TOTAL | C53: =SUM(C4:C52) -> 1246.6362 | D53: =SUM(D4:D52) -> 101.69595

Sheet Vuelo
F2: 3VK3DY
F3: pietersz
L4: 3VK3DY
B23: 23JOV7
