Workbook

Sheet Pasaporte - HC
A15: Nombre | C15: Rainer | E15: Nombre | F15: Natifa
A16: Nombre | E16: Nombre
A17: Apellido | C17: Inecia | E17: Apellido | F17: Francisca
A18: Apellido de casada | E18: Apellido de casada
A19: Género: . | C19: Masculino | E19: Género: . | F19: Femenino
A20: Pasaporte | C20: NWP2J35K1 | E20: Pasaporte | F20: NX7J77K53
A21: Fecha de nacimiento | C21: 32190 | E21: Fecha de nacimiento | F21: 30 Agost 1990
A22: Edad | C22: 37 | E22: Edad | F22: 34
A23: Estado civil | C23: En una Relación | E23: Estado civil | F23: En una Relación
A24: Dirección | E24: Dirección
A25: Nacionalidad y domicilio: | C25: Burgemeestar Augustijnstraat 32, Países Bajos | E25: Nacionalidad y domicilio: | F25: Burgemeestar Augustijnstraat 32, Países Bajos
A26: Email: | C26: rainer.inecia88@gmail.com | E26: Email: | F26: ncfrancisca@gmail.com
A27: Teléfono | C27: 31682221015 | E27: Teléfono | F27: =+31610674497 -> 31610674497
A28: Profesión | C28: Obstetra | E28: Profesión | F28: Obstetra
A29: RH | E29: RH
A30: Seguro | C30: Silveren Kruis | E30: Seguro | F30: Silveren Kruis
A31: Peso | C31: 108 | E31: Peso
A32: Altura | C32: 1.67 | E32: Altura
A33: Idioma | C33: holandés, español, papiamento, inglés | E33: Idioma | F33: Idiomas: holandés, español, papiamento, inglés
A35: Salud | C35: Chequeo general para descartar causas de síntomas de larga duración como: dolor de estómago, dolor al defecar con hemorroides, ronquidos intensos nocturnos que requieren un dispositivo para la apnea del sueño. Aún no tiene PSA, presenta algunas alteraciones visuales y necesita evaluar su alto riesgo cardiovascular e iniciar el proceso de pérdida de peso mientras aprende a comer saludablemente. Además, es necesario descartar hipertrigliceridemia en un examen previo confuso. | E35: Salud | F35: Chequeo general para descartar causas de síntomas de larga duración, como: dolores de cabeza 4 veces por semana, problemas de refracción visual. Se despierta con dolor de cabeza. Toma medicamentos constantemente. Sensación de vómito, dolor en las rodillas y taquicardia. Orina con frecuencia. Presenta inflamación y ha tomado antibióticos para estos episodios debido a la presencia de sangre en su orina. Lleva una vida sedentaria, presenta bruxismo con picaduras y probablemente prediabetes.

Sheet ITINERARIO
B3: ITINERARIO:
B4: Dia | C4: Fecha | D4: Hora | E4: Actividad | F4: ACP horas | G4: Traslado cerca | H4: Traslado lejos
C5: DIA 01 | D5: 45889 | E5: MIÉRCOLES
E6: Vuelo Curazao - Medellín
E7: Traslado a aeropuerto - hotel
E8: Alojamiento
C9: DIA 02 | D9: 45890 | E9: JUEVES
E10: No desayunar
D11: 06:00 am | E11: Traslado Hotel - centro médico | F11: 1.1 | G11: 1
A12: MISMA SEDE | B12: IVS | C12: EL | D12: 07:00 am | E12: Tomografía de abdomen total
A13: MISMA SEDE | B13: IVS | C13: ELLA | E13: Tomografía de cabeza
A14: MISMA SEDE | B14: IVS | C14: ELLA | E14: Tomografía de abdomen y pelvis
A15: MISMA SEDE | E15: Radiografía de tórax
A16: MISMA SEDE | E16: Ecografía de mama
E17: Tiempo para desayunar
E18: Traslado centro médico - centro médico | G18: 1
B19: SAN DIEGO | C19: ELLA | E19: Consulta con especialista en Oftalmología
B20: SAN DIEGO | C20: EL | E20: Consulta con especialista en Oftalmología
E21: Traslado centro médico - hotel | G21: 1
E22: TARDE LIBRE
C23: DIA 03 | D23: 45891 | E23: VIERNES
E24: No desayunar
E25: Traslado Hotel - centro médico | F25: 1.1 | G25: 1
A26: El Tesoro | B26: Synlab | C26: ELLA Y EL | D26: 07:00 am | E26: Toma de muestras de sangre laboratorio clínico
A27: El Tesoro | B27: Synlab | C27: ELLA | E27: Citología cervical
E28: Tiempo para desayunar
A29: El Tesoro | B29: Incare | C29: ELLA Y EL | E29: Electrocardiograma
A30: El Tesoro | B30: Incare | C30: ELLA Y EL | E30: Ecocardiograma
A31: El Tesoro | B31: Incare | C31: ELLA Y EL | E31: Prueba de esfuerzo
E32: Tiempo para almorzar
A33: El Tesoro | B33: Univershe | C33: ELLA | E33: Citología transvaginal
A34: El Tesoro | B34: Univershe | C34: ELLA | E34: Cita con especialista en Ginecología
D35: 02:00 pm | E35: Traslado centro médico - hotel
E36: TARDE LIBRE | G36: 1
C37: DIA 04 | D37: 45892 | E37: SÁBADO
E38: No desayunar
E39: Traslado Hotel - centro médico | F39: 0.5 | G39: 1
B40: Las Américas | C40: EL | D40: 07:00 am | E40: Endoscopia con biopsia
E41: Traslado centro médico - hotel | G41: 1
E42: Tiempo para desayunar y descansar
D43: 11:00 am | E43: Espirometria a domicilio en su hotel
E44: TARDE LIBRE
C45: DIA 05 | D45: 45893 | E45: DOMINGO
E46: DIA LIBRE
C47: DIA 06 | D47: 45894 | E47: LUNES
E48: Tiempo para desayunar
E49: Traslado Hotel - centro médico | F49: 0.5 | G49: 1
A50: Oviedo | B50: Dra Patricia Pareja | C50: EL | D50: 09:00 am | E50: Consulta con especialista en Otorrinolaringología
A51: Oviedo | B51: Dra Patricia Pareja | C51: EL | D51: 12:00 pm | E51: Somnoscopia o Endoscopia del Sueño
E52: Traslado centro médico - hotel | G52: 1
E53: TARDE LIBRE
C54: DIA 07 | D54: 45895 | E54: MARTES
E55: Tiempo para desayunar
E56: Traslado Hotel - centro médico | F56: 1 | H56: 1
B57: HPTU | D57: ELLA | E57: Consulta con especialista en Endocrinología
B58: HPTU | D58: EL | E58: Consulta con especialista en Gastroenterología
E59: Tiempo para almorzar
B60: HPTU | D60: ELLA | E60: Consulta con especialista en Neurología
E61: Traslado centro médico - centro médico | H61: 1
E62: TARDE LIBRE
C63: DIA 08 | D63: 45896 | E63: MIÉRCOLES
E64: DIA LIBRE
C65: DIA 09 | D65: 45897 | E65: JUEVES
E66: DIA LIBRE
C67: DIA 10 | D67: 45898 | E67: VIERNES
E68: DIA LIBRE
C69: DIA 11 | D69: 45899 | E69: SÁBADO
E70: Desayuno en el hotel
E71: Traslado hotel - aeropuerto
E72: Vuelo internacional Curazao - Medellín
F73: =SUM(F5:F72) -> 4.2 | G73: =SUM(G5:G72) -> 9 | H73: =SUM(H5:H72) -> 2

Sheet COSTEO
Y2: Libro diario contable | AG2: Factura electrónica
C3: PAGOS | Q3: PAGOS | V3: ESTADO DE CUENTA | Y3: PAGOS | AG3: FACTURA
B4: ACV documentos | C4: Contabilidad | D4: Operativo | E4: Concepto | G4: Valor | H4: Días | I4: ELLA | J4: EL | L4: ELLA | M4: EL | N4: ELLA | O4: EL | S4: Retención en la fuente | T4: Valor pagado | V4: Valor Neto cobrado al cliente | W4: DIFERENCIA | Y4: PROVEEDOR - NOMBRE COMERCIAL | Z4: ID | AA4: Fecha del pago | AB4: Valor del pago | AC4: Forma de pago de donde salió el dinero | AD4: Tipo de movimiento | AE4: Comentarios | AG4: Fecha de la factura | AH4: FACTURA O CUENTA COBRO | AI4: VALOR REAL DE LA FACTURA | AJ4: CONCEPTO | AL4: CONCEPTO
E5: Póliza de asistencia médica al viajero - producto visitor por 11 días | G5: 3500 | H5: 11 | I5: =G5*H5 -> 38500 | J5: =G5*H5 -> 38500 | L5: =I5/0.7 -> 55000 | M5: =J5/0.7 -> 55000 | N5: =L5/$H$95 -> 14.473684 | O5: =M5/$H$95 -> 14.473684
E6: Sim card física | G6: 6000 | H6: 1 | I6: =G6*H6 -> 6000 | J6: =G6*H6 -> 6000 | L6: =I6/0.6 -> 10000 | M6: =J6/0.6 -> 10000 | N6: =L6/$H$95 -> 2.6315789 | O6: =M6/$H$95 -> 2.6315789
E7: Recarga de datos de 10 GB | G7: 12000 | H7: 1 | I7: =G7*H7 -> 12000 | J7: =G7*H7 -> 12000 | L7: =I7/0.6 -> 20000 | M7: =J7/0.6 -> 20000 | N7: =L7/$H$95 -> 5.2631579 | O7: =M7/$H$95 -> 5.2631579
E8: Traslado aeropuerto - hotel - aeropuerto | G8: 151000 | H8: 2 | I8: =G8*H8/2 -> 151000 | J8: =G8*H8/2 -> 151000 | L8: =I8/0.95 -> 158947.37 | M8: =J8/0.95 -> 158947.37 | N8: =L8/$H$95 -> 41.828255 | O8: =M8/$H$95 -> 41.828255
E9: PAQUETE DE CHEQUEO MÉDICO | I9: 1450000 | J9: 1400000 | N9: 450 | O9: 450
E10: LABORATORIOS CLÍNICOS
B11: ok | D11: EL | E11: Antígeno de próstata | I11: No
B12: ok | D12: EL | E12: Coprológico
B13: ok | D13: X | E13: Citología cervical | J13: No
B14: ok | D14: EL | E14: Vitamina D25
B15: ok | D15: EL | E15: Vitamina B12
B16: ok | D16: EL | E16: Perfil lipídico
B17: ok | D17: EL | E17: Colesterol HDL
B18: ok | D18: EL | E18: Colesterol LDL
B19: ok | D19: EL | E19: Colesterol total
B20: ok | D20: EL | E20: Triglicéridos
B21: ok | D21: EL | E21: Perfil Hepático
B22: ok | D22: EL | E22: ALT- Alanina transferasa
B23: ok | D23: EL | E23: AST - aspartato transferasa
B24: ok | D24: EL | E24: Bilirrubina total y directa
B25: ok | D25: EL | E25: Gama Glutamil transferasa
... B42: ok | D42: EL | E42: Radiografía de tórax
B43: ok | D43: X | E43: Ecografía de mamas | J43: No
B44: X | C44: X | D44: X | E44: Ecografía de abdomen total | I44: No | J44: No | N44: No | O44: No
B45: ok | D45: EL | E45: Electrocardiograma
B46: X | C46: X | D46: X | E46: Cita con especialista en MEDICINA INTERNA | I46: No | J46: No | N46: No | O46: No
E47: ORDENES MÉDICAS
E48: LABORATORIOS CLÍNICOS
B49: ok | C49: ELLA | E49: AMH hormona antimulleriana | G49: 150000 | H49: 1 | I49: =G49*H49 -> 150000 | J49: No | L49: =I49/0.6 -> 250000 | M49: No | N49: =L49/$H$95 -> 65.789474 | O49: No
B50: ok | C50: ELLA | E50: Estradiol total | G50: 36000 | H50: 1 | I50: =G50*H50 -> 36000 | J50: No | L50: =I50/0.6 -> 60000 | M50: No | N50: =L50/$H$95 -> 15.789474 | O50: No
B51: ok | C51: ELLA | E51: FSH Hormona foliculoestimulante | G51: 39000 | H51: 1 | I51: =G51*H51 -> 39000 | J51: No | L51: =I51/0.6 -> 65000 | M51: No | N51: =L51/$H$95 -> 17.105263 | O51: No
B52: ok | C52: ELLA | E52: LH Hormona Luteinizante | G52: 38000 | H52: 1 | I52: =G52*H52 -> 38000 | J52: No | L52: =I52/0.6 -> 63333.333 | M52: No | N52: =L52/$H$95 -> 16.666667 | O52: No
B53: ok | C53: ELLA | E53: Prolactina | G53: 35000 | H53: 1 | I53: =G53*H53 -> 35000 | J53: No | L53: =I53/0.6 -> 58333.333 | M53: No | N53: =L53/$H$95 -> 15.350877 | O53: No
B54: ok | C54: ELLA | E54: Testosterona total | G54: 42000 | H54: 1 | I54: =G54*H54 -> 42000 | J54: No | L54: =I54/0.6 -> 70000 | M54: No | N54: =L54/$H$95 -> 18.421053 | O54: No
B55: ok | C55: ELLA | E55: Androstenediona | G55: 40000 | H55: 1 | I55: =G55*H55 -> 40000 | J55: No | L55: =I55/0.6 -> 66666.667 | M55: No | N55: =L55/$H$95 -> 17.54386 | O55: No
B56: ok | C56: ELLA | E56: Hormona Dehidroepiandrosterona-Sulfato (DHEA-S) | G56: 40000 | H56: 1 | I56: =G56*H56 -> 40000 | J56: No | L56: =I56/0.6 -> 66666.667 | M56: No | N56: =L56/$H$95 -> 17.54386 | O56: No
B57: ok | C57: ELLA | E57: Hidroxiprogesterona (17 OHP) | G57: 70000 | H57: 1 | I57: =G57*H57 -> 70000 | J57: No | L57: =I57/0.6 -> 116666.67 | M57: No | N57: =L57/$H$95 -> 30.701754 | O57: No
B58: ok | C58: ELLA | D58: EL | E58: G6PD (glucosa-6-fosfato deshidrogenasa) Prueba cualitativa | G58: 42000 | H58: 1 | I58: =G58*H58 -> 42000 | J58: =G58*H58 -> 42000 | L58: =I58/0.6 -> 70000 | M58: =J58/0.6 -> 70000 | N58: =L58/$H$95 -> 18.421053 | O58: =M58/$H$95 -> 18.421053
B59: ok | C59: ELLA | D59: EL | E59: G6PD (glucosa-6-fosfato deshidrogenasa) Prueba cuantitativa | G59: 60000 | H59: 1 | I59: =G59*H59 -> 60000 | J59: =G59*H59 -> 60000 | L59: =I59/0.6 -> 100000 | M59: =J59/0.6 -> 100000 | N59: =L59/$H$95 -> 26.315789 | O59: =M59/$H$95 -> 26.315789
B60: ok | C60: ELLA | E60: Frotis de sangre periférica - (extendido de sangre periférica estudio de morfología) | G60: 45000 | H60: 1 | I60: =G60*H60 -> 45000 | J60: No | L60: =I60/0.6 -> 75000 | M60: No | N60: =L60/$H$95 -> 19.736842 | O60: No
B61: ok | C61: ELLA | E61: Test de sicklemia: (Células Falciformes-drepanocitosis) | G61: 40000 | H61: 1 | I61: =G61*H61 -> 40000 | J61: No | L61: =I61/0.6 -> 66666.667 | M61: No | N61: =L61/$H$95 -> 17.54386 | O61: No
B62: ok | C62: ELLA | E62: Insulina Pre y post glucosa | G62: 60000 | H62: 1 | I62: =G62*H62 -> 60000 | J62: No | L62: =I62/0.6 -> 100000 | M62: No | N62: =L62/$H$95 -> 26.315789 | O62: No
B63: ok | C63: ELLA | E63: Curva de glucosa. | G63: 60000 | H63: 1 | I63: =G63*H63 -> 60000 | J63: No | L63: =I63/0.6 -> 100000 | M63: No | N63: =L63/$H$95 -> 26.315789 | O63: No
B64: ok | D64: EL | E64: Paratohormona | G64: 116000 | H64: 1 | I64: No | J64: =G64*H64 -> 116000 | L64: No | M64: =J64/0.6 -> 193333.33 | N64: No | O64: =M64/$H$95 -> 50.877193
B65: ok | C65: ELLA | D65: EL | E65: Homocisteína | G65: 108000 | H65: 1 | I65: =G65*H65 -> 108000 | J65: =G65*H65 -> 108000 | L65: =I65/0.6 -> 180000 | M65: =J65/0.6 -> 180000 | N65: =L65/$H$95 -> 47.368421 | O65: =M65/$H$95 -> 47.368421
B66: ok | E66: IMÁGENES DIAGNÓSTICAS
B67: ok | D67: EL | E67: Esofagoduoendoscopia | G67: 350000 | H67: 1 | I67: No | J67: =G67*H67 -> 350000 | L67: No | M67: =J67/0.7 -> 500000 | N67: No | O67: =M67/$H$95 -> 131.57895
B68: ok | D68: EL | E68: Una biopsia para la endoscopia | G68: 131000 | H68: 1 | I68: No | J68: =G68*H68 -> 131000 | L68: No | M68: =J68/0.9 -> 145555.56 | N68: No | O68: =M68/$H$95 -> 38.304094
B69: ok | C69: ELLA | D69: EL | E69: Ecocardiografía | G69: 320000 | H69: 1 | I69: =G69*H69 -> 320000 | J69: =G69*H69 -> 320000 | L69: =I69/0.7 -> 457142.86 | M69: =J69/0.7 -> 457142.86 | N69: =L69/$H$95 -> 120.30075 | O69: =M69/$H$95 -> 120.30075
B70: ok | C70: ELLA | D70: EL | E70: Prueba de esfuerzo | G70: 260000 | H70: 1 | I70: =G70*H70 -> 260000 | J70: =G70*H70 -> 260000 | L70: =I70/0.7 -> 371428.57 | M70: =J70/0.7 -> 371428.57 | N70: =L70/$H$95 -> 97.744361 | O70: =M70/$H$95 -> 97.744361
B71: ok | D71: EL | E71: Tomografía de abdomen total | G71: 280000 | H71: 1 | I71: No | J71: =G71*H71 -> 280000 | L71: No | M71: =J71/0.75 -> 373333.33 | N71: No | O71: =M71/$H$95 -> 98.245614
B72: ok | C72: ELLA | E72: Tomografía de cabeza | G72: 280000 | H72: 1 | I72: =G72*H72 -> 280000 | J72: No | L72: =I72/0.72 -> 388888.89 | M72: No | N72: =L72/$H$95 -> 102.33918 | O72: No
B73: ok | C73: ELLA | E73: Tomografía de abdomen y pelvis | G73: 330000 | H73: 1 | I73: =G73*H73 -> 330000 | J73: No | L73: =I73/0.7 -> 471428.57 | M73: No | N73: =L73/$H$95 -> 124.06015 | O73: No
D74: EL | E74: Somnoscopia o Endoscopia del Sueño - incluye Sala de quirófano + anestesia + honorarios médicos + insumos | G74: 2800000 | H74: 1 | I74: No | J74: =G74*H74 -> 2800000 | L74: No | M74: =J74/0.95 -> 2947368.4 | N74: No | O74: =M74/$H$95 -> 775.62327
B75: ok | D75: EL | E75: Espirometría | G75: 0 | H75: 1 | I75: No | J75: 0 | L75: No | M75: =J75/0.75 -> 0 | N75: No | O75: =M75/$H$95 -> 0
B76: ok | C76: ELLA | E76: Ecografía transvaginal | G76: 120000 | H76: 1 | I76: 0 | J76: No | L76: =I76/0.7 -> 0 | M76: No | N76: =L76/$H$95 -> 0 | O76: No
E77: ESPECIALISTAS
E78: Consulta con CARDIOLOGÍA | G78: 280000 | H78: 1 | I78: =G78*H78 -> 280000 | J78: =G78*H78 -> 280000 | L78: =I78/0.95 -> 294736.84 | M78: =J78/0.95 -> 294736.84 | N78: =L78/$H$95 -> 77.562327 | O78: =M78/$H$95 -> 77.562327
D79: EL | E79: Consulta con OTORRINOLARINGOLOGO | G79: 300000 | H79: 1 | I79: No | J79: =G79*H79 -> 300000 | L79: No | M79: =J79/0.95 -> 315789.47 | N79: No | O79: =M79/$H$95 -> 83.102493
B80: ok | C80: ELLA | D80: EL | E80: Consulta con OFTALMOLOGÍA | G80: 280000 | H80: 1 | I80: =G80*H80 -> 280000 | J80: =G80*H80 -> 280000 | L80: =I80/0.95 -> 294736.84 | M80: =J80/0.95 -> 294736.84 | N80: =L80/$H$95 -> 77.562327 | O80: =M80/$H$95 -> 77.562327
D81: EL | E81: Consulta con GASTROENTERÓLOGO | G81: 280000 | H81: 1 | I81: No | J81: 0 | L81: No | M81: =J81/0.95 -> 0 | N81: No | O81: =M81/$H$95 -> 0
B82: ok | C82: ELLA | E82: Consulta con GINECOLOGÍA | G82: 280000 | H82: 1 | I82: =G82*H82 -> 280000 | J82: No | L82: =I82/0.95 -> 294736.84 | M82: No | N82: =L82/$H$95 -> 77.562327 | O82: No
C83: ELLA | E83: Consulta con ENDOCRINÓLOGO | G83: 300000 | H83: 1 | I83: =G83*H83 -> 300000 | J83: No | L83: =I83/0.95 -> 315789.47 | M83: No | N83: =L83/$H$95 -> 83.102493 | O83: No
C84: ELLA | E84: Consulta con NEUROLOGÍA | G84: 300000 | H84: 1 | I84: 0 | J84: No | L84: =I84/0.95 -> 0 | M84: No | N84: =L84/$H$95 -> 0 | O84: No
E85: 02 Traslados hotel - clínica por trayecto largo | G85: 45000 | H85: 2 | I85: =G85*H85/2 -> 45000 | J85: =G85*H85/2 -> 45000 | L85: =I85/0.95 -> 47368.421 | M85: =J85/0.95 -> 47368.421 | N85: =L85/$H$95 -> 12.465374 | O85: =M85/$H$95 -> 12.465374
E86: 09 Traslados hotel - clínica por trayecto Corto | G86: 35000 | H86: 9 | I86: =G86*H86/2 -> 157500 | J86: =G86*H86/2 -> 157500 | L86: =I86/0.95 -> 165789.47 | M86: =J86/0.95 -> 165789.47 | N86: =L86/$H$95 -> 43.628809 | O86: =M86/$H$95 -> 43.628809
E87: Servicios Medical Trip Colombia: Acompañamiento Virtual | G87: 180000 | H87: 1 | I87: =G87*H87/2 -> 90000 | J87: =G87*H87/2 -> 90000 | L87: =I87/0.95 -> 94736.842 | M87: =J87/0.95 -> 94736.842 | N87: =L87/$H$95 -> 24.930748 | O87: =M87/$H$95 -> 24.930748
E88: Servicios Medical Trip Colombia: Acompañamiento presencial | G88: 180000 | H88: 4.2 | I88: =G88*H88/2 -> 378000 | J88: =G88*H88/2 -> 378000 | L88: =I88/0.95 -> 397894.74 | M88: =J88/0.95 -> 397894.74 | N88: =L88/$H$95 -> 104.70914 | O88: =M88/$H$95 -> 104.70914
E89: Caja menor | G89: 20000 | H89: 1 | I89: =+G89*H89 -> 20000 | J89: =G89*H89 -> 20000
H90: Total neto | I90: =SUM(I5:I89) -> 5583000 | J90: =SUM(J5:J89) -> 7625000
H91: 0.2 | I91: =I90/0.784 -> 7121173.5 | J91: =J90/0.837 -> 9109916.4 | N91: =SUM(N5:N90) -> 1857.0945 | O91: =SUM(O5:O90) -> 2342.9374
G92: Gastos bancarios | H92: 4 * 1000 | I92: =I91*4/1000 -> 28484.694 | J92: =J91*4/1000 -> 36439.665 | N92: =I92/$H$95 -> 7.4959721 | O92: =J92/$H$95 -> 9.5893857
G93: Gastos bancarios | H93: Transferencia nacional | I93: 6000 | J93: 6000 | N93: =I93/$H$95 -> 1.5789474 | O93: =J93/$H$95 -> 1.5789474
G94: Gastos bancarios | H94: Transferencia internacional
G95: Tasa del dólar | H95: 3800 | I95: =SUM(I91:I94) -> 7155658.2 | J95: =SUM(J91:J94) -> 9152356 | N95: =SUM(N91:N94) -> 1866.1694 | O95: =SUM(O91:O94) -> 2354.1057
I96: =I95/H95 -> 1883.0679 | J96: =J95/H95 -> 2408.5147

Sheet Detalle de los servicios
B4: DETALLE DE SERVICIOS | C4: Natifa | D4: Rainer
B5: =COSTEO!E5 -> Póliza de asistencia médica al viajero - producto visitor por 11 días | C5: =COSTEO!N5 -> 14.473684 | D5: =COSTEO!O5 -> 14.473684
B6: =COSTEO!E6 -> Sim card física | C6: =COSTEO!N6 -> 2.6315789 | D6: =COSTEO!O6 -> 2.6315789
B7: =COSTEO!E7 -> Recarga de datos de 10 GB | C7: =COSTEO!N7 -> 5.2631579 | D7: =COSTEO!O7 -> 5.2631579
B8: =COSTEO!E8 -> Traslado aeropuerto - hotel - aeropuerto | C8: =COSTEO!N8 -> 41.828255 | D8: =COSTEO!O8 -> 41.828255
B9: =COSTEO!E9 -> PAQUETE DE CHEQUEO MÉDICO | C9: =COSTEO!N9 -> 450 | D9: =COSTEO!O9 -> 450
B10: =COSTEO!E10 -> LABORATORIOS CLÍNICOS | C10: =COSTEO!N10 | D10: =COSTEO!O10
B11: =COSTEO!E11 -> Antígeno de próstata | C11: =COSTEO!N11 | D11: =COSTEO!O11
B12: =COSTEO!E12 -> Coprológico | C12: =COSTEO!N12 | D12: =COSTEO!O12
B13: =COSTEO!E13 -> Citología cervical | C13: =COSTEO!N13 | D13: =COSTEO!O13
B14: =COSTEO!E14 -> Vitamina D25 | C14: =COSTEO!N14 | D14: =COSTEO!O14
B15: =COSTEO!E15 -> Vitamina B12 | C15: =COSTEO!N15 | D15: =COSTEO!O15
B16: =COSTEO!E16 -> Perfil lipídico | C16: =COSTEO!N16 | D16: =COSTEO!O16
... B46: =COSTEO!E46 -> Cita con especialista en MEDICINA INTERNA | C46: =COSTEO!N46 -> No | D46: =COSTEO!O46 -> No
B47: =COSTEO!E47 -> ORDENES MÉDICAS | C47: =COSTEO!F47 | D47: =COSTEO!G47
B48: =COSTEO!E48 -> LABORATORIOS CLÍNICOS | C48: =COSTEO!F48 | D48: =COSTEO!G48
B49: =COSTEO!E49 -> AMH hormona antimulleriana | C49: =COSTEO!N49 -> 65.789474 | D49: =COSTEO!O49 -> No | F49: PERFIL HORMONAL
B50: =COSTEO!E50 -> Estradiol total | C50: =COSTEO!N50 -> 15.789474 | D50: =COSTEO!O50 -> No | F50: =B50 -> Estradiol total | G50: =C50 -> 15.789474
B51: =COSTEO!E51 -> FSH Hormona foliculoestimulante | C51: =COSTEO!N51 -> 17.105263 | D51: =COSTEO!O51 -> No | F51: =B51 -> FSH Hormona foliculoestimulante | G51: =C51 -> 17.105263
B52: =COSTEO!E52 -> LH Hormona Luteinizante | C52: =COSTEO!N52 -> 16.666667 | D52: =COSTEO!O52 -> No | F52: =B52 -> LH Hormona Luteinizante | G52: =C52 -> 16.666667
B53: =COSTEO!E53 -> Prolactina | C53: =COSTEO!N53 -> 15.350877 | D53: =COSTEO!O53 -> No | F53: =B53 -> Prolactina | G53: =C53 -> 15.350877
B54: =COSTEO!E54 -> Testosterona total | C54: =COSTEO!N54 -> 18.421053 | D54: =COSTEO!O54 -> No | F54: Progesterona | G54: =C54 -> 18.421053
B55: =COSTEO!E55 -> Androstenediona | C55: =COSTEO!N55 -> 17.54386 | D55: =COSTEO!O55 -> No | F55: TOTAL | G55: =SUM(G50:G54) -> 83.333333
B56: =COSTEO!E56 -> Hormona Dehidroepiandrosterona-Sulfato (DHEA-S) | C56: =COSTEO!N56 -> 17.54386 | D56: =COSTEO!O56 -> No
B57: =COSTEO!E57 -> Hidroxiprogesterona (17 OHP) | C57: =COSTEO!N57 -> 30.701754 | D57: =COSTEO!O57 -> No
B58: =COSTEO!E58 -> G6PD (glucosa-6-fosfato deshidrogenasa) Prueba cualitativa | C58: =COSTEO!N58 -> 18.421053 | D58: =COSTEO!O58 -> 18.421053
B59: =COSTEO!E59 -> G6PD (glucosa-6-fosfato deshidrogenasa) Prueba cuantitativa | C59: =COSTEO!N59 -> 26.315789 | D59: =COSTEO!O59 -> 26.315789
B60: =COSTEO!E60 -> Frotis de sangre periférica - (extendido de sangre periférica estudio de morfología) | C60: =COSTEO!N60 -> 19.736842 | D60: =COSTEO!O60 -> No
B61: =COSTEO!E61 -> Test de sicklemia: (Células Falciformes-drepanocitosis) | C61: =COSTEO!N61 -> 17.54386 | D61: =COSTEO!O61 -> No
B62: =COSTEO!E62 -> Insulina Pre y post glucosa | C62: =COSTEO!N62 -> 26.315789 | D62: =COSTEO!O62 -> No
B63: =COSTEO!E63 -> Curva de glucosa. | C63: =COSTEO!N63 -> 26.315789 | D63: =COSTEO!O63 -> No
B64: =COSTEO!E64 -> Paratohormona | C64: =COSTEO!N64 -> No | D64: =COSTEO!O64 -> 50.877193
B65: =COSTEO!E65 -> Homocisteína | C65: =COSTEO!N65 -> 47.368421 | D65: =COSTEO!O65 -> 47.368421
B66: =COSTEO!E66 -> IMÁGENES DIAGNÓSTICAS | C66: =COSTEO!F66 | D66: =COSTEO!G66
B67: =COSTEO!E67 -> Esofagoduoendoscopia | C67: =COSTEO!N67 -> No | D67: =COSTEO!O67 -> 131.57895
B68: =COSTEO!E68 -> Una biopsia para la endoscopia | C68: =COSTEO!N68 -> No | D68: =COSTEO!O68 -> 38.304094
B69: =COSTEO!E69 -> Ecocardiografía | C69: =COSTEO!N69 -> 120.30075 | D69: =COSTEO!O69 -> 120.30075
B70: =COSTEO!E70 -> Prueba de esfuerzo | C70: =COSTEO!N70 -> 97.744361 | D70: =COSTEO!O70 -> 97.744361
B71: =COSTEO!E71 -> Tomografía de abdomen total | C71: =COSTEO!N71 -> No | D71: =COSTEO!O71 -> 98.245614
B72: =COSTEO!E72 -> Tomografía de cabeza | C72: =COSTEO!N72 -> 102.33918 | D72: =COSTEO!O72 -> No
B73: =COSTEO!E73 -> Tomografía de abdomen y pelvis | C73: =COSTEO!N73 -> 124.06015 | D73: =COSTEO!O73 -> No
B74: =COSTEO!E74 -> Somnoscopia o Endoscopia del Sueño - incluye Sala de quirófano + anestesia + honorarios médicos + insumos | C74: =COSTEO!N74 -> No | D74: =COSTEO!O74 -> 775.62327
B75: =COSTEO!E75 -> Espirometría | C75: =COSTEO!N75 -> No | D75: =COSTEO!O75 -> 0
B76: =COSTEO!E76 -> Ecografía transvaginal | C76: =COSTEO!N76 -> 0 | D76: =COSTEO!O76 -> No
B77: =COSTEO!E77 -> ESPECIALISTAS | C77: =COSTEO!F77 | D77: =COSTEO!G77
B78: =COSTEO!E78 -> Consulta con CARDIOLOGÍA | C78: =COSTEO!N78 -> 77.562327 | D78: =COSTEO!O78 -> 77.562327
B79: =COSTEO!E79 -> Consulta con OTORRINOLARINGOLOGO | C79: =COSTEO!N79 -> No | D79: =COSTEO!O79 -> 83.102493
B80: =COSTEO!E80 -> Consulta con OFTALMOLOGÍA | C80: =COSTEO!N80 -> 77.562327 | D80: =COSTEO!O80 -> 77.562327
B81: =COSTEO!E81 -> Consulta con GASTROENTERÓLOGO | C81: =COSTEO!N81 -> No | D81: =COSTEO!O81 -> 0
B82: =COSTEO!E82 -> Consulta con GINECOLOGÍA | C82: =COSTEO!N82 -> 77.562327 | D82: =COSTEO!O82 -> No
B83: =COSTEO!E83 -> Consulta con ENDOCRINÓLOGO | C83: =COSTEO!N83 -> 83.102493 | D83: =COSTEO!O83 -> No
B84: =COSTEO!E84 -> Consulta con NEUROLOGÍA | C84: =COSTEO!N84 -> 0 | D84: =COSTEO!O84 -> No
B85: =COSTEO!E85 -> 02 Traslados hotel - clínica por trayecto largo | C85: =COSTEO!N85 -> 12.465374 | D85: =COSTEO!O85 -> 12.465374
B86: =COSTEO!E86 -> 09 Traslados hotel - clínica por trayecto Corto | C86: =COSTEO!N86 -> 43.628809 | D86: =COSTEO!O86 -> 43.628809
B87: =COSTEO!E87 -> Servicios Medical Trip Colombia: Acompañamiento Virtual | C87: =COSTEO!N87 -> 24.930748 | D87: =COSTEO!O87 -> 24.930748
B88: =COSTEO!E88 -> Servicios Medical Trip Colombia: Acompañamiento presencial | C88: =COSTEO!N88 -> 104.70914 | D88: =COSTEO!O88 -> 104.70914
B89: 4 * 1000 Impuesto bancario | C89: =COSTEO!N92 -> 7.4959721 | D89: =COSTEO!O92 -> 9.5893857
B90: Cargos bancarios por pagos | C90: =COSTEO!N93 -> 1.5789474 | D90: =COSTEO!O93 -> 1.5789474
B91: TOTAL A PAGAR | C91: =SUM(C5:C90) -> 1866.1694 | D91: =SUM(D5:D90) -> 2354.1057
B94: DETALLE DE SERVICIOS | C94: Natifa
B95: Póliza de asistencia médica al viajero - producto visitor por 11 días | C95: 14.473684
B96: Sim card física | C96: 2.6315789
B97: Recarga de datos de 10 GB | C97: 5.2631579
B98: Traslado aeropuerto - hotel - aeropuerto | C98: 41.828255
B99: PAQUETE DE CHEQUEO MÉDICO | C99: 450
B100: LABORATORIOS CLÍNICOS
B101: Coprológico
B102: Citología cervical
B103: Vitamina D25
B104: Vitamina B12
B105: Perfil lipídico
B106: Colesterol HDL
B107: Colesterol LDL
B108: Colesterol total
B109: Triglicéridos
B110: Perfil Hepático
B111: ALT- Alanina transferasa
... B132: Ecografía de mamas
B133: Ecografía de abdomen total | C133: No
B134: Electrocardiograma
B135: Cita con especialista en MEDICINA INTERNA | C135: No
B136: ORDENES MÉDICAS
B137: LABORATORIOS CLÍNICOS
B138: AMH hormona antimulleriana | C138: 65.789474
B139: Estradiol total | C139: 15.789474
B140: FSH Hormona foliculoestimulante | C140: 17.105263
B141: LH Hormona Luteinizante | C141: 16.666667
B142: Prolactina | C142: 15.350877
B143: Testosterona total | C143: 18.421053
B144: Androstenediona | C144: 17.54386
B145: Hormona Dehidroepiandrosterona-Sulfato (DHEA-S) | C145: 17.54386
B146: Hidroxiprogesterona (17 OHP) | C146: 30.701754
B147: G6PD (glucosa-6-fosfato deshidrogenasa) Prueba cualitativa | C147: 18.421053
B148: G6PD (glucosa-6-fosfato deshidrogenasa) Prueba cuantitativa | C148: 26.315789
B149: Frotis de sangre periférica - (extendido de sangre periférica estudio de morfología) | C149: 19.736842
... B153: Homocisteína | C153: 47.368421
B154: IMÁGENES DIAGNÓSTICAS
B155: Ecocardiografía | C155: 120.30075
B156: Prueba de esfuerzo | C156: 97.744361
B157: Tomografía de cabeza | C157: 102.33918
...

Sheet Vuelo
