Workbook

Sheet PASAPORTES
A19: Nombre 1 | B19: REEMY | C19: Pasaporte | D19: NU8RDD5P0 | G19: Nombre 1 | H19: ANTHONY | M19: NO VIAJO
A20: Nombre 2 | B20: BREDLEY | C20: Fecha de nacimiento | D20: 27917 | G20: Nombre 2 | H20: LORETO | M20: Nombre 1 | N20: WILLET | O20: Pasaporte | P20: NY2CD34L2
A21: Apellido | B21: POPPEN | C21: Edad | D21: =2025-1976 -> 49 | G21: Apellido | H21: BRAAFHART | M21: Nombre 2 | O21: Fecha de nacimiento | P21: 27427
A22: País | B22: Curazao | G22: País | H22: CURAZAO | M22: Apellido | N22: PETERNELLA | O22: Edad | P22: 50
A23: Email: | B23: r.poppen@gmail.com | G23: Pasaporte | H23: NY5KHJH23 | M23: País | N23: Curazao
A24: Teléfono | B24: 59995230179 | G24: Fecha de nacimiento | H24: 22625 | M24: Email: | N24: aulinepeternella@gmail.com
G25: Edad | H25: 63 | M25: Teléfono | N25: 59995652026
G26: Email: | H26: langetpouwpouw@gmail.com
G27: Teléfono | H27: 599 9 521 0899
G28: Peso | H28: 87
G29: Altura | H29: 174
G30: Padre | H30: General Maduro
G31: Madre | H31: Fallecida
A45: Nombre 1 | B45: RAISON | C45: Pasaporte | D45: NUK8RP3R5 | G45: Nombre 1 | I45: Pasaporte
A46: Nombre 2 | B46: MARCELO | C46: Fecha de nacimiento | D46: 30332 | G46: Nombre 2 | I46: Fecha de nacimiento
A47: Apellido | B47: GURIBALDI | C47: Edad | D47: 42 | G47: Apellido | I47: Edad
A48: País | B48: Curazao | G48: País
A49: Email: | B49: raisonguribaldi@gmail.com | G49: Email:
A50: Teléfono | B50: 59995183047 | G50: Teléfono

Sheet CARPETA - ARCHIVO
A3: ANTHONY | G3: REEMY
A4: ARCHIVO DIGITAL | B4: LABORATORIOS CLÍNICOS | C4: ARCHIVO DIGITAL | D4: IMÁGENES DIAGNÓSTICAS | E4: ARCHIVO DIGITAL | F4: Especialista | G4: ARCHIVO DIGITAL | H4: IMÁGENES DIAGNÓSTICAS | I4: ARCHIVO DIGITAL | J4: Especialista
A5: ok | B5: Antígeno de próstata | C5: ok | D5: Tomografía de abdomen y pélvis | E5: ok | F5: Cardiologo | G5: ok | H5: Procedimiento de flasma de rodillas | I5: ok | J5: Especialista en Músculo esquelético
A6: ok | B6: Coprológico | C6: ok | D6: Radiografía de tórax | E6: ok | F6: Gastroenterologo
A7: ok | B7: Vitamina D25 | C7: ok | D7: Ecocardiografía | E7: ok | F7: Neurologo
A8: ok | B8: Vitamina B12 | C8: ok | D8: Prueba de esfuerzo | E8: ok | F8: Fisiatra
B9: Perfil lipídico | C9: ok | D9: Electrocardiograma | E9: ok | F9: Urologo
A10: ok | B10: Colesterol HDL | C10: ok | D10: Ecografía prostática Trasrectal | E10: ok | F10: Medico Funcional
A11: ok | B11: Colesterol LDL | C11: ok | D11: Esofagogastroduodenoscopia preferiblemente bajo sedación
A12: ok | B12: Colesterol total | C12: ok | D12: Electromiografía y velocidad de conducción nerviosa de los músculos faciales y nervios faciales
A13: ok | B13: Triglicéridos | C13: ok | D13: Resultado de Biopsia
B14: Perfil Hepático
A15: ok | B15: ALT- Alanina transferasa
A16: ok | B16: AST - aspartato transferasa
A17: ok | B17: Bilirrubina total y directa
A18: ok | B18: Gamma glutamil transferasa
B19: Perfil Renal
A20: ok | B20: Creatinina
A21: ok | B21: Uroanálisis
A22: ok | B22: Nitrógeno Ureico en Sangre (BUN)
B23: Sangre
A24: ok | B24: Hemograma completo
A25: ok | B25: Ferritina
A26: ok | B26: Glucosa sérica
B27: Perfil Tiroideo
A28: ok | B28: T4 total
A29: ok | B29: TSH
B30: Enfermedades de transmisión sexual
A31: ok | B31: VDRL
A32: ok | B32: VIH 1 Y 2, Anticuerpos
A33: ok | B33: Hemoglobina Glicosilada
A34: ok | B34: Ionograma: calcio - sodio - fósforo - potasio
A35: ok | B35: Homocisteína
A36: ok | B36: Parathormona
A37: ok | B37: HEPATITIS A ANTICUERPOS TOTALES SEMIAUTOMATIZADO O AUTOMATIZADO
A38: ok | B38: HEPATITIS B ANTICUERPOS CENTRAL TOTALES [ANTI-CORE HBC] SEMIAUTOMATIZADO O AUTOMAT1
A39: ok | B39: HEPATITIS B ANTICUERPOS S [ANTI-HBS] SEMIAUTOMATIZADO O AUTOMATIZADO
A40: ok | B40: HEPATITIS B ANTÍGENO DE SUPERFICIE [AG HBS]
A41: ok | B41: HEPATITIS C, ANTICUERPO [ANTI-HVC]

Sheet ITINERARIO
C4: ITINERARIO:
D5: 1 | E5: 45878 | F5: SÁBADO | G5: ACP REEMY | H5: TRASLADOS REEMY | I5: ACP ANTHONY | J5: TRASLADOS ANTHONY CERCA | K5: TRASLADOS ANTHONY LEJOS
E6: 07:00 pm | F6: Llegada vuelo internacional Curazao - Medellín
B7: TAXI VAN | C7: confirmada | F7: Traslado aeropuerto - hotel Minivan
B8: Hotel Novelty | C8: confirmada | F8: Alojamiento
D9: 2 | E9: 45879 | F9: DOMINGO
F10: NO DESAYUNAR
B11: AEROTUREX | C11: confirmada | E11: 09:00 am | F11: Traslado hotel - clínica | I11: 0.5 | J11: 1
A12: Calle 80 | B12: IVS | C12: confirmada | D12: Anthony | E12: 10:00 am | F12: Tomografía de abdomen y pélvis
A13: Calle 80 | B13: IVS | C13: confirmada | D13: Anthony | E13: 10:30 am | F13: Radiografía de tórax
B14: AEROTUREX | C14: confirmada | E14: 11:00 am | F14: Traslado clínica - clínica | J14: 1
F15: Desayuno en el hotel
F16: DÍA LIBRE
D17: 3 | E17: 45880 | F17: LUNES
E18: 06:00 am | F18: Comer fruta - jugo - caldo comida ligera
B19: AEROTUREX | C19: confirmada | E19: 09:00 am | F19: Traslado hotel - clínica | I19: 0.5 | J19: 1
A20: Las Vegas | B20: Incare | C20: confirmada | D20: Anthony | E20: 09:30 am | F20: Ecocardiografía
A21: Las Vegas | B21: Incare | C21: confirmada | D21: Anthony | E21: 09:45 am | F21: Prueba de esfuerzo
A22: Las Vegas | B22: Incare | C22: confirmada | D22: Anthony | E22: 11:00 am | F22: Electrocardiograma
A23: Las Vegas | B23: Incare | C23: confirmada | D23: Anthony | E23: 11:30 am | F23: Consulta con especialista en CARDIOLOGÍA
F24: Toma de muestras de sangre para laboratorios
B25: Carolina | E25: 01:20 pm | F25: Traslado clínica - hotel | J25: 1
F26: TARDE LIBRE
D27: 4 | E27: 45881 | F27: MARTES
F28: NO DESAYUNAR - NO AGUA
B29: Yenny | C29: Confirmado | D29: Anthony | E29: 08:00 am | F29: Traslado hotel - clínica | I29: 0.5 | J29: 1
A30: Las Vegas | B30: Echavarria | C30: Confirmado | D30: Anthony | E30: 08:30 am | F30: Toma de muestras de sangre para laboratorios
C31: Confirmado | D31: Anthony | F31: Traslado centro médico - centro médico
A32: Calle 80 las américas | B32: Unidad Gastroenterológica | C32: Confirmado | D32: Anthony | E32: 10:00 am | F32: Endoscopia con sedación
B33: Yenny | C33: Confirmado | D33: Anthony | E33: 11:00 am | F33: Traslado clínica hotel | J33: 1
D34: Anthony | E34: 11:30 am | F34: Tiempo para comer
D35: Anthony | F35: No comer nada más
D36: Anthony | F36: Tiempo para descansar
D37: Anthony | E37: 02:00 pm | F37: Tiempo para hacer limpieza con enema
B38: Yenny | C38: Confirmado | D38: Reemy | E38: 01:30 pm | F38: Traslado hotel - clínica | G38: 0.5 | H38: 1
A39: Poblado sector Patio Bonito | B39: Resonancia especializada Cra 46 #7-211 | C39: confirmado | D39: Reemy | E39: 02:20 pm | F39: Resonancia de dos rodillas
B40: Yenny | C40: Confirmado | D40: Reemy | E40: 03:30 pm | F40: Traslado clínica hotel | H40: 1
D41: Anthony | E41: 05:00 pm | F41: Traslado hotel - clínica
B42: Las Vegas | C42: Confirmado | D42: Anthony | E42: 05:30 pm | F42: Ecografía prostática
D43: Anthony | E43: 06:30 pm | F43: Traslado clínica hotel
D44: 5 | E44: 45882 | F44: MIÉRCOLES
F45: Desayuno en el hotel
C46: Yenny | F46: Traslado hotel - clínica | K46: 1
B47: HPTU | C47: confirmada | D47: Anthony | E47: 07:00 am | F47: Electromiografía y velocidad de conducción nerviosa de los músculos faciales y nervios faciales.
C48: Yenny | E48: 10:30 am | F48: Traslado hotel - clínica | K48: 1
A49: DR SOTO | B49: Carrera 80A # 32 ee-72 edif. offix 33 Consultorio 1015 Laureles la 33 | C49: confirmada | D49: Reemy | E49: 11:00 am | F49: Cita con especialista en Músculo esquelético
E50: 12:00 pm | F50: Traslado clínica hotel
B51: Yenny | E51: 12:30 am | F51: Traslado hotel - clínica | K51: 1
B52: HPTU | C52: confirmada | D52: Anthony | E52: 01:15 pm | F52: Consulta con especialista en GASTROENTEROLOGÍA
B53: HPTU | C53: confirmada | D53: Anthony | E53: 03:00 pm | F53: Cita con especialista en NEUROLOGÍA
F54: Traslado clínica hotel | K54: 1
D55: 6 | E55: 45883 | F55: JUEVES
F56: Desayuno en el hotel
B57: Aeroturex | E57: 10:30 am | F57: Traslado hotel - clínica | K57: 1
B58: Carrera 80A # 32 ee-72 edif. offix 33 Consultorio 1015 Laureles la 33 | C58: confirmada | D58: Reemy | E58: 11:00 am | F58: Procedimiento de flasma de rodillas
B59: HPTU | C59: confirmada | D59: Anthony | E59: 11:30 am | F59: Cita con especialista en FISIATRÍA
B60: HPTU | C60: confirmada | D60: Anthony | E60: 12:20 pm | F60: Cita especialista en UROLOGÍA
E61: 02:00 pm | F61: Traslado clínica - hotel | K61: 1
F62: Traslado hotel - clínica | G62: 0.5 | H62: 1
F64: Traslado clínica - hotel | H64: 1
C65: 7 | D65: 7 | E65: 45884 | F65: VIERNES - día libre
C66: 8 | D66: 8 | E66: 45885 | F66: SÁBADO
F67: Traslado hotel - aeropuerto
E68: 09:15 am | F68: Vuelo internacional Medellín - Curazao
G69: =SUM(G6:G68) -> 1 | H69: =SUM(H6:H68) -> 4 | I69: =SUM(I6:I68) -> 1.5 | J69: =SUM(J6:J68) -> 6 | K69: =SUM(K6:K68) -> 6

Sheet PROXIMO VIAJE

Sheet RVA011-7-COSTEO
AC3: Libro diario contable
C4: PAGOS | P4: 3800 | T4: PAGOS | Z4: ESTADO DE CUENTA | AC4: PAGOS
B5: ACV documentos | C5: Contabilidad | D5: Operativo | E5: Concepto | F5: Proveedor | G5: Valor | H5: Días | I5: Empresa | J5: Reemy | K5: Anthony | L5: Raison | N5: Comisionable | O5: Empresa | P5: Reemy | Q5: Anthony | R5: Raison | T5: Reemy | U5: Anthony | W5: Retención en la fuente | X5: Valor pagado | Z5: Valor Neto cobrado al cliente | AA5: DIFERENCIA | AC5: PROVEEDOR - NOMBRE COMERCIAL | AD5: ID | AE5: Fecha del pago | AF5: Valor del pago | AG5: Forma de pago de donde salió el dinero | AH5: Tipo de movimiento | AI5: Comentarios
B6: e-mail | C6: Facturado | D6: Comprado | E6: Compra de 50 bolsos | G6: =((38500+(38500*19%))) -> 45815 | H6: 50 | I6: =G6*H6 -> 2290750 | N6: =I6 -> 2290750 | O6: =N6/$P$4 -> 602.82895
B7: e-mail | C7: Facturado | D7: Confirmado | E7: Costo de envío de los bolsos desde Bogotá a Medellín | G7: 70000 | H7: 1 | I7: =G7*H7 -> 70000 | N7: =I7/0.8 -> 87500 | O7: =N7/$P$4 -> 23.026316
C8: Facturado | D8: Confirmado | E8: Medical Trip Colombia - servicios de cotización , compra de los bolsos | G8: 200000 | H8: 1 | I8: =G8*H8 -> 200000 | N8: =I8/0.8 -> 250000 | O8: =N8/$P$4 -> 65.789474
B9: e-mail | C9: DSM 125 | D9: Emitido | E9: Tres tiquetes aéreo vía wingo en tarifa economica full | F9: Copa Airlines | H9: 1 | J9: 2842060 | K9: 2842060 | L9: 2842060 | N9: 2842060 | P9: 680 | Q9: 680 | R9: 680
B10: e-mail | C10: DSM 125 | D10: Confirmado | E10: Tarifa administrativa emisión de tiquetes | F10: Copa Airlines | H10: 1 | J10: 139400 | K10: 139400 | L10: 139400 | N10: 139400 | P10: 40 | Q10: 40 | R10: 40
B11: e-mail | C11: DSM 126 | D11: Emitido | E11: Cambio de nombre del pasajero | F11: Wingo | H11: 1 | K11: =100*4170 -> 417000 | N11: =K11 -> 417000 | Q11: 100
B12: e-mail | C12: Facturado | D12: Emitido | E12: Póliza de asistencia médica al viajero | F12: Colasistencia | G12: 3500 | H12: 8 | J12: =G12*H12 -> 28000 | K12: =G12*H12 -> 28000 | L12: =G12*H12 -> 28000 | N12: =J12/0.45 -> 62222.222 | P12: =N12/$P$4 -> 16.374269 | Q12: =N12/$P$4 -> 16.374269 | R12: =N12/$P$4 -> 16.374269 | T12: =2450*8 -> 19600 | U12: =2450*8 -> 19600 | V12: =2450*8 -> 19600 | W12: 0 | X12: =T12+U12+V12 -> 58800 | Z12: =J12+K12+L12 -> 84000 | AA12: =Z12-T12-U12-V12 -> 25200 | AC12: COLASISTENCIA | AE12: 45875 | AF12: 1265000 | AG12: JURIDICA BANCOLOMBIA | AH12: TRANSFERENCIA
C13: DSM | D13: Comprada | E13: Sim card física | F13: Claro | G13: 6000 | H13: 1 | K13: =G13*H13 -> 6000 | L13: =G13*H13 -> 6000 | N13: =K13/0.4 -> 15000 | Q13: =N13/$P$4 -> 3.9473684 | R13: =N13/$P$4 -> 3.9473684 | U13: 5000 | V13: 5000 | W13: 0 | X13: =T13+U13+V13 -> 10000 | Z13: =K13+L13 -> 12000 | AA13: =Z13-T13-U13-V13 -> 2000 | AC13: YENNY ROBERTO
B14: e-mail | C14: Facturado | D14: Recargada | E14: Recarga de 10 gigas de datos | F14: Claro | G14: 12000 | H14: 1 | J14: =G14*H14 -> 12000 | K14: =G14*H14 -> 12000 | L14: =G14*H14 -> 12000 | N14: =J14/0.4 -> 30000 | P14: =N14/$P$4 -> 7.8947368 | Q14: =N14/$P$4 -> 7.8947368 | R14: =N14/$P$4 -> 7.8947368 | T14: 12000 | U14: 12000 | V14: 12000 | W14: 0 | X14: =T14+U14+V14 -> 36000 | Z14: =J14+K14+L14 -> 36000 | AA14: =Z14-T14-U14-V14 -> 0 | AC14: CLARO | AE14: 44782 | AF14: 36000 | AG14: JURIDICA BANCOLOMBIA | AH14: PSE
B15: REVISAR SALDO A FAVOR | C15: Facturado | D15: Confirmado | E15: Traslado aeropuerto - hotel - aeropuerto en MINIVAN | F15: Taxi van | G15: 305000 | H15: 2 | J15: =G15*H15 -> 610000 | N15: =J15/0.9 -> 677777.78 | P15: =(N15/$P$4)/3 -> 59.454191 | Q15: =P15 -> 59.454191 | R15: =P15 -> 59.454191 | T15: 480000 | W15: 0 | X15: =T15+U15+V15 -> 480000 | Z15: =J15+K15+L15 -> 610000 | AA15: =Z15-T15-U15-V15 -> 130000 | AC15: TAXIVAN | AE15: 44782 | AF15: 240000 | AG15: JURIDICA BANCOLOMBIA | AH15: TRANSFERENCIA
B16: e-mail | C16: Facturado | D16: reserva: NOV4267/NCT2025 | E16: Alojamiento en suite Deluxe Reemy Poppen | F16: Novelty | G16: 434596.82 | H16: 7 | J16: =G16*H16 -> 3042177.8 | N16: =J16 -> 3042177.8 | P16: =N16/$P$4 -> 800.57309 | T16: =N16 -> 3042177.8 | U16: =N17 -> 2682931.4 | V16: =N18 -> 2682885.2 | W16: =(T16+U16+V16)*3.5% -> 294279.8 | X16: =(T16+U16+V16)-W16 -> 8113714.6 | AC16: TAXIVAN | AE16: 45884 | AF16: 220000 | AG16: JURIDICA BANCOLOMBIA | AH16: TRANSFERENCIA
B17: e-mail | C17: Facturado | D17: reserva: NOV4264/NCT2025 | E17: Habitación Individual para una persona Anthony | F17: Novelty | G17: 383275.92 | H17: 7 | K17: =G17*H17 -> 2682931.4 | N17: =K17 -> 2682931.4 | Q17: =N17/$P$4 -> 706.03458 | AC17: NOVELTY SUITES | AF17: 7700000 | AG17: JURIDICA BANCOLOMBIA | AH17: TRANSFERENCIA
B18: e-mail | C18: Facturado | D18: reserva: NOV4266/NCT2025 | E18: Habitación Individual para una persona Raison Guribaldi | F18: Novelty | G18: 383269.32 | H18: 7 | L18: =G18*H18 -> 2682885.2 | N18: =L18 -> 2682885.2 | R18: =N18/$P$4 -> 706.02243 | AC18: NOVELTY SUITES | AE18: RTE RVA011-5 | AF18: 459221 | AG18: SALDO A FAVOR 45.506
E19: PAQUETE DE CHEQUEO MÉDICO | K19: 1200000 | N19: =K19/0.7 -> 1714285.7 | Q19: 450
B20: Archivado | C20: DMS | D20: Confirmado | E20: Entrevista con médico funcional virtual | F20: Marcos Yepes | U20: 150000 | W20: =U20*2% -> 3000 | X20: =U20-W20 -> 147000 | AC20: MARCOS YEPES | AE20: 45868 | AF20: 144000 | AG20: YENNY CAMBIO DOLARES | AH20: DEPOSITO EN BANCO
D21: NO | E21: Domicilio | F21: Echavarria | U21: 624498 | W21: 0 | X21: =U21-W21 -> 624498 | AC21: ECHAVRRIA | AE21: 44782 | AF21: 624498 | AG21: JURIDICA BANCOLOMBIA | AH21: TRANSFERENCIA
B22: e-mail | C22: Facturado | D22: Confirmado | E22: Antígeno de próstata | F22: Echavarria
B23: e-mail | C23: Facturado | D23: Confirmado | E23: Coprológico | F23: Echavarria
B24: e-mail | C24: Facturado | D24: Confirmado | E24: Vitamina D25 | F24: Echavarria
B25: e-mail | C25: Facturado | D25: Confirmado | E25: Vitamina B12 | F25: Echavarria
E26: Perfil lipídico
B27: e-mail | C27: Facturado | D27: Confirmado | E27: Colesterol HDL | F27: Echavarria
B28: e-mail | C28: Facturado | D28: Confirmado | E28: Colesterol LDL | F28: Echavarria
B29: e-mail | C29: Facturado | D29: Confirmado | E29: Colesterol total | F29: Echavarria
B30: e-mail | C30: Facturado | D30: Confirmado | E30: Triglicéridos | F30: Echavarria
E31: Perfil Hepático
B32: e-mail | C32: Facturado | D32: Confirmado | E32: ALT- Alanina transferasa | F32: Echavarria
B33: e-mail | C33: Facturado | D33: Confirmado | E33: AST - aspartato transferasa | F33: Echavarria
B34: e-mail | C34: Facturado | D34: Confirmado | E34: Bilirrubina total y directa | F34: Echavarria
B35: e-mail | C35: Facturado | D35: Confirmado | E35: Gamma glutamil transferasa | F35: Echavarria
E36: Perfil Renal
B37: e-mail | C37: Facturado | D37: Confirmado | E37: Creatinina | F37: Echavarria
B38: e-mail | C38: Facturado | D38: Confirmado | E38: Uroanálisis | F38: Echavarria
B39: e-mail | C39: Facturado | D39: Confirmado | E39: Nitrógeno Ureico en Sangre (BUN) | F39: Echavarria
E40: Sangre
B41: e-mail | C41: Facturado | D41: Confirmado | E41: Hemograma completo | F41: Echavarria
B42: e-mail | C42: Facturado | D42: Confirmado | E42: Ferritina | F42: Echavarria
B43: e-mail | C43: Facturado | D43: Confirmado | E43: Glucosa sérica | F43: Echavarria
E44: Perfil Tiroideo
B45: e-mail | C45: Facturado | D45: Confirmado | E45: T4 total | F45: Echavarria
B46: e-mail | C46: Facturado | D46: Confirmado | E46: TSH | F46: Echavarria
E47: Enfermedades de transmisión sexual
B48: e-mail | C48: Facturado | D48: Confirmado | E48: VDRL | F48: Echavarria
B49: e-mail | C49: Facturado | D49: Confirmado | E49: VIH 1 Y 2, Anticuerpos | F49: Echavarria
B50: e-mail | C50: Facturado | D50: Confirmado | E50: Hemoglobina Glicosilada | F50: Echavarria | G50: 50000 | H50: 1 | K50: =G50*H50 -> 50000 | N50: =K50/0.6 -> 83333.333 | Q50: =N50/$P$4 -> 21.929825 | AF50: =AF64-AF63 -> 94380
B51: e-mail | C51: Facturado | D51: Confirmado | E51: Ionograma: calcio - sodio - fósforo - potasio | F51: Echavarria | G51: 110000 | H51: 1 | K51: =G51*H51 -> 110000 | N51: =K51/0.6 -> 183333.33 | Q51: =N51/$P$4 -> 48.245614
B52: e-mail | C52: Facturado | D52: Confirmado | E52: Homocisteína | F52: Echavarria | G52: 108000 | H52: 1 | K52: =G52*H52 -> 108000 | N52: =K52/0.75 -> 144000 | Q52: =N52/$P$4 -> 37.894737
B53: e-mail | C53: Facturado | D53: Confirmado | E53: Parathormona | F53: Echavarria | G53: 116000 | H53: 1 | K53: =G53*H53 -> 116000 | N53: =K53/0.6 -> 193333.33 | Q53: =N53/$P$4 -> 50.877193
B54: e-mail | C54: Facturado | D54: Confirmado | E54: HEPATITIS A ANTICUERPOS TOTALES SEMIAUTOMATIZADO O AUTOMATIZADO | F54: Echavarria | G54: 60000 | H54: 1 | K54: =G54*H54 -> 60000 | N54: =K54/0.6 -> 100000 | Q54: =N54/$P$4 -> 26.315789
B55: e-mail | C55: Facturado | D55: Confirmado | E55: HEPATITIS B ANTICUERPOS CENTRAL TOTALES [ANTI-CORE HBC] SEMIAUTOMATIZADO O AUTOMAT1 | F55: Echavarria | G55: 85000 | H55: 1 | K55: =G55*H55 -> 85000 | N55: =K55/0.6 -> 141666.67 | Q55: =N55/$P$4 -> 37.280702
B56: e-mail | C56: Facturado | D56: Confirmado | E56: HEPATITIS B ANTICUERPOS S [ANTI-HBS] SEMIAUTOMATIZADO O AUTOMATIZADO | F56: Echavarria | G56: 65000 | H56: 1 | K56: =G56*H56 -> 65000 | N56: =K56/0.6 -> 108333.33 | Q56: =N56/$P$4 -> 28.508772
B57: e-mail | C57: Facturado | D57: Confirmado | E57: HEPATITIS B ANTÍGENO DE SUPERFICIE [AG HBS] | F57: Echavarria | G57: 75000 | H57: 1 | K57: =G57*H57 -> 75000 | N57: =K57/0.6 -> 125000 | Q57: =N57/$P$4 -> 32.894737
B58: e-mail | C58: Facturado | D58: Confirmado | E58: HEPATITIS C, ANTICUERPO [ANTI-HVC] | F58: Echavarria | G58: 80000 | H58: 1 | K58: =G58*H58 -> 80000 | N58: =K58/0.6 -> 133333.33 | Q58: =N58/$P$4 -> 35.087719
B59: e-mail | C59: Facturado | D59: Confirmado | E59: G6PD (glucosa-6-fosfato deshidrogenasa) Prueba cualitativa | F59: Echavarria | G59: 50000 | H59: 1 | K59: =G59*H59 -> 50000 | N59: =K59/0.6 -> 83333.333 | Q59: =N59/$P$4 -> 21.929825
D60: NO LA HACEN | E60: G6PD (glucosa-6-fosfato deshidrogenasa) Prueba cuantitativa | F60: Echavarria | G60: 50000 | H60: 1 | K60: =G60*H60 -> 50000 | N60: =K60/0.6 -> 83333.333 | Q60: =N60/$P$4 -> 21.929825
E61: Imágenes diagnósticas
B62: e-mail | C62: Facturado | D62: Confirmado | E62: Radiografía de tórax | F62: IVS | U62: 64400 | W62: =U62*2% -> 1288 | X62: =U62-W62 -> 63112
B63: e-mail | C63: Facturado | D63: Confirmado | E63: Tomografía de abdomen y pélvis | F63: IVS | G63: 300000 | H63: 1 | K63: =G63*H63 -> 300000 | N63: =K63/0.7 -> 428571.43 | Q63: =N63/$P$4 -> 112.78195 | U63: 227046 | W63: =U63*2% -> 4540.92 | X63: =U63-W63 -> 222505.08 | AC63: IVS | AE63: 45878 | AF63: 191237 | AG63: JURIDICA BANCOLOMBIA | AH63: TRANSFERENCIA
E64: ESTUDIOS PERSONALIZADOS | AC64: IVS | AE64: 45875 | AF64: 285617 | AG64: JURIDICA BANCOLOMBIA | AH64: TRANSFERENCIA
B65: e-mail | C65: DSM | D65: Confirmado | E65: Ecografía de próstata transrectal | F65: LAS VEGAS | G65: 200000 | H65: 1 | K65: =G65*H65 -> 200000 | N65: =K65/0.7 -> 285714.29 | Q65: =N65/$P$4 -> 75.18797 | AC65: CAROLINA / LAS VEGAS | AE65: 45880 | AF65: 128000 | AG65: JURIDICA BANCOLOMBIA | AH65: TRANSFERENCIA | AI65: SE ENVIO EL DINERO A CAROLINA Y ELLA PAGO CON SU TARJETA DEBITO
C66: Facturado | D66: Confirmado | E66: Cita con especialista en UROLOGÍA | F66: HPTU | G66: 290000 | H66: 1 | K66: =G66*H66 -> 290000 | N66: =K66/0.9 -> 322222.22 | Q66: =N66/$P$4 -> 84.795322 | W66: =U66*2% -> 0 | X66: =U66-W66 -> 0 | Z66: =K66 -> 290000 | AA66: =Z66-U66 -> 290000 | AC66: HPTU - DOCTOR | AE66: 45878 | AF66: 150000 | AG66: JURIDICA BANCOLOMBIA | AH66: TRANSFERENCIA
B67: e-mail | C67: Facturado | D67: Confirmado | E67: Electrocardiograma | F67: INCARE | U67: 42500 | W67: =U67*2% -> 850 | X67: =U67-W67 -> 41650 | Z67: =G67 | AA67: =Z67-U67 -> -42500 | AC67: INCARE | AE67: 45875 | AF67: 716380 | AG67: JURIDICA BANCOLOMBIA | AH67: TRANSFERENCIA
B68: e-mail | C68: Facturado | D68: Confirmado | E68: Prueba de esfuerzo | F68: INCARE | G68: 450000 | H68: 1 | K68: =G68*H68 -> 450000 | N68: =K68/0.7 -> 642857.14 | Q68: =N68/$P$4 -> 169.17293 | U68: 204000 | W68: =U68*2% -> 4080 | X68: =U68-W68 -> 199920 | Z68: =K68 -> 450000 | AA68: =Z68-U68 -> 246000
B69: e-mail | C69: Facturado | D69: Confirmado | E69: Ecocardiograma | F69: INCARE | G69: 300000 | H69: 1 | K69: =G69*H69 -> 300000 | N69: =K69/0.6 -> 500000 | Q69: =N69/$P$4 -> 131.57895 | U69: 314500 | W69: =U69*2% -> 6290 | X69: =U69-W69 -> 308210 | Z69: =K69 -> 300000 | AA69: =Z69-U69 -> -14500
B70: e-mail | C70: Facturado | D70: Confirmado | E70: Cita con especialista en CARDIOLOGÍA | F70: INCARE | G70: 290000 | H70: 1 | K70: =G70*H70 -> 290000 | N70: =K70/0.9 -> 322222.22 | Q70: =N70/$P$4 -> 84.795322 | U70: 170000 | W70: =U70*2% -> 3400 | X70: =U70-W70 -> 166600 | Z70: =K70 -> 290000 | AA70: =Z70-U70 -> 120000
B71: e-mail | C71: Facturado | D71: Confirmado | E71: Electromiografía facial | F71: HPTU | G71: 290000 | H71: 1 | K71: =G71*H71 -> 290000 | N71: =K71/0.7 -> 414285.71 | Q71: =N71/$P$4 -> 109.02256 | U71: 297800 | W71: 0 | X71: =U71-W71 -> 297800 | Z71: =K71 -> 290000 | AA71: =Z71-U71 -> -7800 | AC71: HPTU | AE71: 45875 | AF71: 297800 | AG71: JURIDICA BANCOLOMBIA | AH71: TRANSFERENCIA
B72: e-mail | C72: Facturado | D72: Confirmado | E72: Cita con especialista en FISIATRÍA | F72: HPTU | G72: 290000 | H72: 1 | K72: =G72*H72 -> 290000 | N72: =K72/0.9 -> 322222.22 | Q72: =N72/$P$4 -> 84.795322 | U72: 150000 | W72: 0 | X72: =U72-W72 -> 150000 | Z72: =K72 -> 290000 | AA72: =Z72-U72 -> 140000 | AC72: HPTU | AE72: 45875 | AF72: 150000 | AG72: JURIDICA BANCOLOMBIA | AH72: TRANSFERENCIA
B73: e-mail | C73: Facturado | D73: Confirmado | E73: Cita con especialista en NEUROLOGÍA | F73: HPTU | G73: 290000 | H73: 1 | K73: =G73*H73 -> 290000 | N73: =K73/0.9 -> 322222.22 | Q73: =N73/$P$4 -> 84.795322 | U73: 175000 | W73: 0 | X73: =U73-W73 -> 175000 | Z73: =K73 -> 290000 | AA73: =Z73-U73 -> 115000 | AC73: HPTU | AE73: 45875 | AF73: 175000 | AG73: JURIDICA BANCOLOMBIA | AH73: TRANSFERENCIA
B74: e-mail | C74: Facturado | D74: Confirmado | E74: Cita con especialista en GASTROENTEROLOGÍA | F74: HPTU | G74: 290000 | H74: 1 | K74: =G74*H74 -> 290000 | N74: =K74/0.9 -> 322222.22 | Q74: =N74/$P$4 -> 84.795322 | U74: 175000 | W74: 0 | X74: =U74-W74 -> 175000 | Z74: =K74 -> 290000 | AA74: =Z74-U74 -> 115000 | AC74: HPTU | AE74: 45875 | AF74: 175000 | AG74: JURIDICA BANCOLOMBIA | AH74: TRANSFERENCIA | AI74: SALDO A FAVOR SE APLICA PARA RVA201
B75: e-mail | C75: Facturado | D75: Confirmado | E75: Esofagoduo endoscopia con sedación | G75: 450000 | H75: 1 | K75: =G75*H75 -> 450000 | N75: =K75/0.7 -> 642857.14 | Q75: =N75/$P$4 -> 169.17293 | U75: 332000 | W75: =U75*2% -> 6640 | X75: =U75-W75 -> 325360 | Z75: =K75 -> 450000 | AA75: =Z75-U75 -> 118000 | AC75: UNIDAD GASTROENTEROLOGICA | AE75: 45875 | AF75: 453740 | AG75: JURIDICA BANCOLOMBIA | AH75: TRANSFERENCIA
B76: e-mail | C76: Facturado | D76: Confirmado | E76: Una biopsia | G76: 130000 | H76: 1 | K76: =G76*H76 -> 130000 | N76: =K76/0.9 -> 144444.44 | Q76: =N76/$P$4 -> 38.011696 | U76: 131000 | W76: =U76*2% -> 2620 | X76: =U76-W76 -> 128380 | Z76: =K76 -> 130000 | AA76: =Z76-U76 -> -1000
B77: NO | C77: Facturado | D77: NO LA HACEN | E77: Resonancia de rodilla simple rodilla derecha | G77: 640000 | H77: 1 | J77: =G77*H77 -> 640000 | N77: =J77/0.6 -> 1066666.7 | P77: =N77/$P$4 -> 280.70175 | T77: =990000/2 -> 495000 | W77: =T77*2% -> 9900 | X77: =(T77+U77+V77)-W77 -> 485100 | AC77: TAXIVAN
B78: NO | C78: Facturado | D78: NO LA HACEN | E78: Resonancia de rodilla simple rodilla izquierda | G78: 640000 | H78: 1 | J78: =G78*H78 -> 640000 | N78: =J78/0.6 -> 1066666.7 | P78: =N78/$P$4 -> 280.70175 | T78: =990000/2 -> 495000 | W78: =T78*2% -> 9900 | X78: =(T78+U78+V78)-W78 -> 485100 | AC78: MEDIALFA | AE78: 45881 | AF78: 453740 | AG78: JURIDICA BANCOLOMBIA | AH78: TRANSFERENCIA
B79: e-mail | C79: Facturado | D79: Confirmado | E79: Consulta con especialista en Ortopedia | F79: SOTO | G79: 300000 | H79: 1 | J79: =G79*H79 -> 300000 | N79: =J79/0.93 -> 322580.65 | P79: =N79/$P$4 -> 84.889643 | T79: 150000 | W79: =T79*2% -> 3000 | X79: =(T79+U79+V79)-W79 -> 147000 | Z79: =J79 -> 300000 | AA79: =Z79-U79 -> 300000 | AC79: DR SOTO | AE79: 45868 | AF79: 294000 | AG79: JURIDICA BANCOLOMBIA | AH79: TRANSFERENCIA | AI79: RVA180-1 Y RVA011-7
B80: e-mail | C80: Facturado | D80: Confirmado | E80: 04 Traslados hotel - clínica - Hotel Reemy | F80: Aeroturex | G80: 40000 | H80: 4 | J80: =G80*H80 -> 160000 | N80: =J80/0.9 -> 177777.78 | P80: =N80/$P$4 -> 46.783626 | AC80: AEROTUREX | AE80: 45902 | AF80: 527000 | AG80: RICHARD PRESTAMO BANCOLOMBIA | AH80: TRANSFERENCIA
B81: e-mail | C81: Facturado | D81: Confirmado | E81: 06 Traslados hotel - clínica - Hotel Anthony | F81: Aeroturex | G81: 40000 | H81: 6 | K81: =G81*H81 -> 240000 | N81: =K81/0.9 -> 266666.67 | Q81: =N81/$P$4 -> 70.175439
B82: Archivado | C82: DSM | D82: Confirmado | E82: Acompañamiento presencial en español para citas y exámenes Reemy | G82: 180000 | H82: 1 | J82: =G82*H82 -> 180000 | N82: =J82/0.9 -> 200000 | P82: =N82/$P$4 -> 52.631579
B83: Archivado | C83: DSM | D83: Confirmado | E83: Acompañamiento presencial en español para citas y exámenes Anthony | G83: 180000 | H83: 3 | K83: =G83*H83 -> 540000 | N83: =K83/0.9 -> 600000 | Q83: =N83/$P$4 -> 157.89474
B84: Archivado | C84: DSM | D84: Confirmado | E84: Acompañamiento virtual permanente en Español | F84: Carolina | G84: 250000 | H84: 1 | J84: =G84*H84 -> 250000 | N84: =J84/0.9 -> 277777.78 | P84: =N84/$P$4 -> 73.099415
B85: Archivado | C85: DSM | D85: Confirmado | E85: Medical Trip Colombia SAS - Acompañamiento virtual permanente en ESPAÑOL | G85: 250000 | H85: 2 | K85: =G85*H85 -> 500000 | N85: =K85/0.9 -> 555555.56 | Q85: =N85/$P$4 -> 146.19883
B86: Archivado | C86: DSM | D86: Confirmado | E86: Caja menor | G86: 20000 | H86: 1 | J86: =G86*H86 -> 20000 | K86: =G86*H86 -> 20000 | L86: =G86*H86 -> 20000 | T86: =N86 | U86: =N87 | V86: =N88
G87: Total NETO | I87: =SUM(I6:I86) -> 2560750 | J87: =SUM(J6:J86) -> 8863637.8 | K87: =SUM(K6:K86) -> 13046391 | L87: =SUM(L6:L86) -> 5730345.2
G88: Total comisionable | I88: =I87/0.975 -> 2626410.3 | J88: =J87/0.9266 -> 9565764.9 | K88: =K87/0.8565 -> 15232214 | L88: =L87/0.9965 -> 5750471.9 | O88: =SUM(O6:O87) -> 691.64474 | P88: =SUM(P6:P87) -> 2423.1041 | Q88: =SUM(Q6:Q87) -> 4029.7745 | R88: =SUM(R6:R87) -> 1513.693 | T88: LIQUIDACIÓN GBIZ
G89: 4 * 1000 | I89: =I88*4/1000 -> 10505.641 | J89: =J88*4/1000 -> 38263.06 | K89: =K88*4/1000 -> 60928.857 | L89: =L88*4/1000 -> 23001.888 | O89: =I89/$P$4 -> 2.7646424 | P89: =J89/$P$4 -> 10.069226 | Q89: =K89/$P$4 -> 16.03391 | R89: =L89/$P$4 -> 6.0531283 | T89: =I87-I88 -> -65660.256 | U89: =J88-J87 -> 702127.14 | V89: 1800000 | W89: =L88-L87 -> 20126.652
G90: Transferencias nacionales | I90: =6000*1 -> 6000 | J90: =6000*2 -> 12000 | K90: =6000*5 -> 30000 | O90: =I90/$P$4 -> 1.5789474 | P90: =J90/$P$4 -> 3.1578947 | Q90: =K90/$P$4 -> 7.8947368 | R90: =L90/$P$4 -> 0
G91: Transferencia internacional | I91: =5*4100 -> 20500 | J91: =30*4100 -> 123000 | K91: =30*4100 -> 123000 | L91: =20*4100 -> 82000 | O91: =I91/$P$4 -> 5.3947368 | P91: =J91/$P$4 -> 32.368421 | Q91: =K91/$P$4 -> 32.368421 | R91: =L91/$P$4 -> 21.578947 | T91: TOTAL COMISION
G92: TOTAL A PAGAR EN COP | I92: =SUM(I88:I91) -> 2663415.9 | J92: =SUM(J88:J91) -> 9739028 | K92: =SUM(K88:K91) -> 15446143 | L92: =SUM(L88:L91) -> 5855473.8 | T92: =SUM(T89:W89) -> 2456593.5 | U92: 100
G93: TOTAL A PAGAR EN USD | I93: =I92/3800 -> 700.89892 | J93: =J92/3800 -> 2562.9021 | K93: =K92/3800 -> 4064.7745 | L93: =L92/3800 -> 1540.9142 | O93: =SUM(O88:O92) -> 701.38306 | P93: =SUM(P88:P92) -> 2468.6996 | Q93: =SUM(Q88:Q92) -> 4086.0716 | R93: =SUM(R88:R92) -> 1541.3251 | T93: =T92*0.33 -> 810675.87 | U93: =T93*U92/T92 -> 33 | V93: =T93/3800 -> 213.33575
I94: =I88-I87 -> 65660.256 | J94: =J88-J87 -> 702127.14 | K94: =K88-K87 -> 2185822.7 | L94: =L88-L87 -> 20126.652 | O94: =O93+P93+Q93+R93 -> 8797.4793 | P94: =O94*3800 -> 33430421
I95: =I94+J94+K94+L94 -> 2973736.8 | O95: 500 | P95: =O94*4150 -> 36509539
O96: =O94-O95 -> 8297.4793
P97: =P93+Q93+R93 -> 8096.0962
E101: Tarifa administrativa emisión de tiquetes | F101: Copa Airlines | H101: 1 | J101: 139400 | K101: 139400 | L101: 139400 | N101: 139400 | P101: 40 | Q101: 40 | R101: 40
E102: 04 Traslados hotel - clínica - Hotel Reemy | F102: Aeroturex | G102: 40000 | H102: 4 | J102: =G102*H102 -> 160000 | N102: =J102/0.9 -> 177777.78 | P102: =N102/$P$4 -> 46.783626
E103: 06 Traslados hotel - clínica - Hotel Anthony | F103: Aeroturex | G103: 40000 | H103: 6 | K103: =G103*H103 -> 240000 | N103: =K103/0.9 -> 266666.67 | Q103: =N103/$P$4 -> 70.175439
E104: Acompañamiento presencial en español para citas y exámenes Reemy | G104: 180000 | H104: 1 | J104: =G104*H104 -> 180000 | N104: =J104/0.9 -> 200000 | P104: =N104/$P$4 -> 52.631579
E105: Acompañamiento presencial en español para citas y exámenes Anthony | G105: 180000 | H105: 3 | K105: =G105*H105 -> 540000 | N105: =K105/0.9 -> 600000 | Q105: =N105/$P$4 -> 157.89474
...

Sheet RVA011-8-COSTEO
U3: Libro diario contable
C4: PAGOS | L4: 3800 | N4: PAGOS | R4: ESTADO DE CUENTA | U4: PAGOS
B5: ACV documentos | C5: Contabilidad | D5: Operativo | E5: Concepto | F5: Proveedor | G5: Valor | H5: Días | I5: Reemy | K5: Comisionable | L5: Reemy | N5: Reemy | O5: Retención en la fuente | P5: Valor pagado | R5: Valor Neto cobrado al cliente | S5: DIFERENCIA | U5: PROVEEDOR - NOMBRE COMERCIAL | V5: ID | W5: Fecha del pago | X5: Valor del pago | Y5: Forma de pago de donde salió el dinero | Z5: Tipo de movimiento | AA5: Comentarios
D6: Confirmado | E6: Aplicación de Plasma en dos rodillas con traslados | G6: 1600000 | H6: 2 | I6: =G6*H6 -> 3200000 | K6: =I6/0.8878 -> 3604415.4 | L6: =K6/$L$4 -> 948.53037 | N6: =2480000/0.98 -> 2530612.2 | O6: =N6*2% -> 50612.245 | P6: =N6-O6 -> 2480000 | R6: =I6 -> 3200000 | S6: =R6-N6 -> 669387.76 | U6: DR. JUAN CAMILO SOTO | W6: 45883 | X6: 2480000 | Y6: JENNY BANCOLOMBIA | Z6: TRANSFERENCIA
D7: Confirmado | E7: Servicios de aplicación de inyección + Medicamentos | G7: 100000 | H7: 1 | I7: =G7*H7 -> 100000 | K7: 100000 | L7: =K7/$L$4 -> 26.315789
D8: Confirmado | E8: Servicios de enfermería 12 horas + fajas | G8: 226000 | H8: 1 | I8: =G8*H8 -> 226000 | K8: 230000 | L8: =K8/$L$4 -> 60.526316
E9: Productos Millicent | G9: 215000 | H9: 1 | I9: =G9*H9 -> 215000 | K9: =I9/0.9 -> 238888.89 | L9: =K9/$L$4 -> 62.865497
D10: Confirmado | E10: Medicamento amiga | G10: 100000 | H10: 1 | I10: =G10*H10 -> 100000 | K10: 150000 | L10: =K10/$L$4 -> 39.473684
K11: TOTAL A PAGAR | L11: =SUM(L6:L10) -> 1137.7117
E14: Saldo a favor
E15: ='RVA011-7-COSTEO'!E77 -> Resonancia de rodilla simple rodilla derecha | F15: ='RVA011-7-COSTEO'!P77 -> 280.70175
E16: ='RVA011-7-COSTEO'!E78 -> Resonancia de rodilla simple rodilla izquierda | F16: ='RVA011-7-COSTEO'!P78 -> 280.70175
F17: =SUM(F15:F16) -> 561.40351
E19: Liquidación | F19: 45884
D20: RVA011-8 | E20: Servicios | F20: =L11 -> 1137.7117
D21: RVA011-7 | E21: Saldo a favor servicios | F21: =F17 -> 561.40351
D22: RVA011-7 | E22: Valor mayor pagado | F22: 64
E23: Saldo por pagar | F23: =F20-F21-F22 -> 512.30815
E25: ANTHONY | F25: 45884
E26: Tour Comuna trece | F26: 79000
E27: Traslados hotel-parque-hotel | F27: 50000
E28: Saldo por pagar en pesos | F28: =SUM(F26:F27) -> 129000
E29: USD en dólares | F29: =F28/3800 -> 33.947368

Sheet DETALLE DE LOS SERVICIOS
B3: Concepto | C3: Empresa | D3: Reemy | E3: Anthony | F3: Raison
B4: Compra de 50 bolsos | C4: 602.82895
B5: Costo de envío de los bolsos desde Bogotá a Medellín | C5: 23.026316
B6: Medical Trip Colombia - servicios de cotización , compra de los bolsos | C6: 65.789474
B7: Tres tiquetes aéreo vía wingo en tarifa economica full | D7: 680 | E7: 680 | F7: 680
B8: Tarifa administrativa emisión de tiquetes | D8: 40 | E8: 40 | F8: 40
B9: Cambio de nombre del pasajero | E9: 100
B10: Póliza de asistencia médica al viajero | D10: 16.374269 | E10: 16.374269 | F10: 16.374269
B11: Sim card física | E11: 3.5087719 | F11: 3.5087719
B12: Recarga de 10 gigas de datos | D12: 7.8947368 | E12: 7.8947368 | F12: 7.8947368
B13: Traslado aeropuerto - hotel - aeropuerto en MINIVAN | D13: 59.454191 | E13: 59.454191 | F13: 59.454191
B14: Alojamiento en suite Deluxe Reemy Poppen | D14: 800.57309
B15: Habitación Individual para una persona Willet Peternella | E15: 706.03458
B16: Habitación Individual para una persona Raison Guribaldi | F16: 706.02243
B17: PAQUETE DE CHEQUEO MÉDICO | E17: 450
B18: Entrevista con médico funcional virtual
B19: Domicilio
B20: Antígeno de próstata
B21: Coprológico
B22: Vitamina D25
B23: Vitamina B12
B24: Perfil lipídico
B25: Colesterol HDL
B26: Colesterol LDL
B27: Colesterol total
B28: Triglicéridos
B29: Perfil Hepático
... B51: ESTUDIOS PERSONALIZADOS
B52: Hemoglobina Glicosilada | E52: 21.929825
B53: Ionograma: calcio - sodio - fósforo - potasio | E53: 48.245614
B54: Homocisteína | E54: 37.894737
B55: Parathormona | E55: 50.877193
B56: HEPATITIS A ANTICUERPOS TOTALES SEMIAUTOMATIZADO O AUTOMATIZADO | E56: 26.315789
B57: HEPATITIS B ANTICUERPOS CENTRAL TOTALES [ANTI-CORE HBC] SEMIAUTOMATIZADO O AUTOMAT1 | E57: 37.280702
B58: HEPATITIS B ANTICUERPOS S [ANTI-HBS] SEMIAUTOMATIZADO O AUTOMATIZADO | E58: 28.508772
B59: HEPATITIS B ANTÍGENO DE SUPERFICIE [AG HBS] | E59: 32.894737
B60: HEPATITIS C, ANTICUERPO [ANTI-HVC] | E60: 35.087719
B61: G6PD (glucosa-6-fosfato deshidrogenasa) Prueba cualitativa | E61: 21.929825
B62: G6PD (glucosa-6-fosfato deshidrogenasa) Prueba cuantitativa | E62: 21.929825
B63: Ecografía de próstata transrectal | E63: 75.18797
... B73: Cita con especialista en GASTROENTEROLOGÍA | E73: 84.795322
B74: Resonancia de rodilla simple rodilla derecha | D74: 280.70175
B75: Resonancia de rodilla simple rodilla izquierda | D75: 280.70175
B76: Consulta con especialista en Ortopedia | D76: 84.889643
B77: 04 Traslados hotel - clínica - Hotel Reemy | D77: 46.783626
B78: 06 Traslados hotel - clínica - Hotel Anthony | E78: 70.175439
B79: Acompañamiento presencial en español para citas y exámenes Reemy | D79: 52.631579
B80: Acompañamiento presencial en español para citas y exámenes Anthony | E80: 157.89474
B81: Acompañamiento virtual permanente en Español | D81: 73.099415
B82: Medical Trip Colombia SAS - Acompañamiento virtual permanente en ESPAÑOL | E82: 146.19883
B83: Caja menor
B84: ='RVA011-7-COSTEO'!E88 | C84: 691.64474 | D84: 2423.1041 | E84: 3916.5539 | F84: 1513.2544
B85: ='RVA011-7-COSTEO'!E89 | C85: 2.7646424 | D85: 22.565392 | E85: 15.665212 | F85: 6.0531283
B86: ='RVA011-7-COSTEO'!E90 | C86: 1.5789474 | D86: 3.1578947 | E86: 7.8947368 | F86: 0
B87: ='RVA011-7-COSTEO'!E91 | C87: 5.3947368 | D87: 32.368421 | E87: 32.368421 | F87: 21.578947
B88: ='RVA011-7-COSTEO'!E92
B89: ='RVA011-7-COSTEO'!E93 | C89: 701.38306 | D89: 2481.1958 | E89: 3972.4823 | F89: 1540.8865
B90: ='RVA011-7-COSTEO'!E94 | C90: 8695.9476
B91: ='RVA011-7-COSTEO'!E95 | C91: 500
B92: ='RVA011-7-COSTEO'!E96 | C92: =C90-C91 -> 8195.9476
B93: ='RVA011-7-COSTEO'!E97
C94: Empresa | D94: =C89-C91 -> 201.38306
B95: ='RVA011-7-COSTEO'!E99 | C95: Anthony | D95: =E89 -> 3972.4823 | F95: MEDICAL | G95: =D95+D94 -> 4173.8654
B96: ='RVA011-7-COSTEO'!E100 | C96: Reemy | D96: =D89 -> 2481.1958 | F96: CASH | G96: =D96+D97 -> 4022.0822
C97: Raison | D97: =F89 -> 1540.8865
B98: ='RVA011-7-COSTEO'!E101 -> Tarifa administrativa emisión de tiquetes | C98: Total | D98: =SUM(D94:D97) -> 8195.9476
B99: ='RVA011-7-COSTEO'!E102 -> 04 Traslados hotel - clínica - Hotel Reemy
B100: ='RVA011-7-COSTEO'!E103 -> 06 Traslados hotel - clínica - Hotel Anthony
B101: ='RVA011-7-COSTEO'!E104 -> Acompañamiento presencial en español para citas y exámenes Reemy | D101: SALDO A FAVOR
B102: ='RVA011-7-COSTEO'!E105 -> Acompañamiento presencial en español para citas y exámenes Anthony
B103: ='RVA011-7-COSTEO'!E106 -> Acompañamiento virtual permanente en Español | L103: ='RVA011-7-COSTEO'!P106 -> 73.099415
B104: ='RVA011-7-COSTEO'!E107 -> Medical Trip Colombia SAS - Acompañamiento virtual permanente en ESPAÑOL | L104: ='RVA011-7-COSTEO'!P107
B105: ='RVA011-7-COSTEO'!E108 -> Caja menor | L105: ='RVA011-7-COSTEO'!P108
B106: ='RVA011-7-COSTEO'!E109 | L106: ='RVA011-7-COSTEO'!P109 -> 212.51462
B107: ='RVA011-7-COSTEO'!E110 | L107: ='RVA011-7-COSTEO'!P110 -> 666.78363
B108: ='RVA011-7-COSTEO'!E111 | L108: ='RVA011-7-COSTEO'!P111
B109: ='RVA011-7-COSTEO'!E112 | L109: ='RVA011-7-COSTEO'!P112
B110: ='RVA011-7-COSTEO'!E113 | L110: ='RVA011-7-COSTEO'!P113
B111: ='RVA011-7-COSTEO'!E114 | L111: ='RVA011-7-COSTEO'!P114
B112: ='RVA011-7-COSTEO'!E115 | L112: ='RVA011-7-COSTEO'!P115
B113: ='RVA011-7-COSTEO'!E116 | L113: ='RVA011-7-COSTEO'!P116
B114: ='RVA011-7-COSTEO'!E117 | L114: ='RVA011-7-COSTEO'!P117
... B123: ='RVA011-7-COSTEO'!E126 | L123: ='RVA011-7-COSTEO'!P126

Sheet CONFIRMACIÓN DE SERVICIOS
A1: Medialfa
B2: TAC ABDOMEN Y PELVIS
N5: 3145355801 | O5: ANTHONY
N6: 3145354536 | O6: RAISON
O7: REEMY
B21: RX TÓRAX
B43: ECOCARDIOGRAFÍA | H43: PRUEBA DE ESFUERZO | L43: ELECTROCARDIOGRAMA
B63: ECOGRAFÍA PROSTÁTICA
B90: CARDIOLOGÍA
B107: ENDOSCOPIA

Sheet Hoja 26
B3: Concepto | C3: Empresa | D3: Reemy | E3: Anthony | F3: Raison
B4: Compra de 50 bolsos | C4: 602.82895
B5: Costo de envío de los bolsos desde Bogotá a Medellín | C5: 23.026316
B6: Medical Trip Colombia - servicios de cotización , compra de los bolsos | C6: 65.789474
B7: Tres tiquetes aéreo vía wingo en tarifa economica full | D7: 680 | E7: 680 | F7: 680
B8: Tarifa administrativa emisión de tiquetes | D8: 40 | E8: 40 | F8: 40
B9: Cambio de nombre del pasajero | E9: 100
B10: Póliza de asistencia médica al viajero | D10: 16.374269 | E10: 16.374269 | F10: 16.374269
B11: Sim card física | D11: 3.5087719 | E11: 3.5087719 | F11: 3.5087719
B12: Recarga de 10 gigas de datos | D12: 7.8947368 | E12: 7.8947368 | F12: 7.8947368
B13: Traslado aeropuerto - hotel - aeropuerto en MINIVAN | D13: 59.454191 | E13: 59.454191 | F13: 59.454191
B14: Alojamiento en suite Deluxe Reemy Poppen | D14: 800.57309
B15: Habitación Individual para una persona Willet Peternella | E15: 706.03458
B16: Habitación Individual para una persona Raison Guribaldi | F16: 706.02243
B17: PAQUETE DE CHEQUEO MÉDICO | E17: 450
B18: Entrevista con médico funcional virtual
B19: Domicilio
B20: Antígeno de próstata
B21: Coprológico
B22: Vitamina D25
B23: Vitamina B12
B24: Perfil lipídico
B25: Colesterol HDL
B26: Colesterol LDL
B27: Colesterol total
B28: Triglicéridos
B29: Perfil Hepático
... B51: ÓRDENES MÉDICAS
B52: Hemoglobina Glicosilada | E52: 21.929825
B53: Ionograma: calcio - sodio - fósforo - potasio | E53: 48.245614
B54: Homocisteína | E54: 37.894737
B55: Parathormona | E55: 50.877193
B56: HEPATITIS A ANTICUERPOS TOTALES SEMIAUTOMATIZADO O AUTOMATIZADO | E56: 26.315789
B57: HEPATITIS B ANTICUERPOS CENTRAL TOTALES [ANTI-CORE HBC] SEMIAUTOMATIZADO O AUTOMAT1 | E57: 37.280702
B58: HEPATITIS B ANTICUERPOS S [ANTI-HBS] SEMIAUTOMATIZADO O AUTOMATIZADO | E58: 28.508772
B59: HEPATITIS B ANTÍGENO DE SUPERFICIE [AG HBS] | E59: 32.894737
B60: HEPATITIS C, ANTICUERPO [ANTI-HVC] | E60: 35.087719
B61: G6PD (glucosa-6-fosfato deshidrogenasa) Prueba cualitativa | E61: 21.929825
B62: G6PD (glucosa-6-fosfato deshidrogenasa) Prueba cuantitativa | E62: 21.929825
B63: Ecografía de próstata transrectal | E63: 75.18797
... B73: Cita con especialista en GASTROENTEROLOGÍA | E73: 84.795322
B74: Resonancia de rodilla simple rodilla derecha | D74: 280.70175
B75: Resonancia de rodilla simple rodilla izquierda | D75: 280.70175
B76: Consulta con especialista en Ortopedia | D76: 84.889643
B77: Tratamiento de aplicación de ácido hialurónico para rodilla izquierda | D77: 730.99415
B78: Tratamiento de aplicación de ácido hialurónico para rodilla derecha | D78: 730.99415
B79: Tratamiento de aplicación de plasma rico en plaquetas para rodilla izquierda | D79: 877.19298
B80: Tratamiento de aplicación de plasma rico en plaquetas para rodilla derecha | D80: 877.19298
B81: 04 Traslados hotel - clínica - Hotel Reemy | D81: 46.783626
B82: 06 Traslados hotel - clínica - Hotel Anthony | E82: 70.175439
B83: Acompañamiento presencial en español para citas y exámenes Reemy | D83: 52.631579
B84: Acompañamiento presencial en español para citas y exámenes Anthony | E84: 157.89474
B85: Acompañamiento virtual permanente en Español Reemy | D85: 73.099415
B86: Medical Trip Colombia SAS - Acompañamiento virtual permanente en español Anthony | E86: 146.19883
B87: Impuesto bancario 4 * 1000 | C87: 2.7646424 | D87: 22.572208 | E87: 15.665212 | F87: 6.0531283
B88: Gastos bancarios transferencias nacionales | C88: 1.5789474 | D88: 3.1578947 | E88: 7.8947368 | F88: 0
B89: Gastos bancarios transferencias internacionales | C89: 5.3947368 | D89: 32.368421 | E89: 32.368421 | F89: 21.578947
B90: TOTAL | C90: 701.38306 | D90: 5690.2962 | E90: 3983.2718 | F90: 1540.8865
B91: GRAN TOTAL | C91: 11915.837

Sheet HOTEL
G13: 492432
G14: =G13*19% -> 93562.08
G15: =G13-G14 -> 398869.92
C19: Reemy | D19: Raison | E19: Anthony | I19: Anthony
C20: Tarifa con Iva comisionable | D20: Tarifa con Iva comisionable | E20: Tarifa con Iva comisionable | I20: Tarifa con Iva comisionable | O20: =SUM('RVA011-7-COSTEO'!Q16:Q100) -> 11294.247 | P20: =SUM('RVA011-7-COSTEO'!R16:R100) -> 3788.6726
C21: 3755775 | D21: 3312261 | E21: 3312204 | G21: 353250.57 | H21: =G21*7 -> 2472754 | I21: 3312204 | K21: IVA 19 % | O21: =#REF!/$H$24 -> #REF! | P21: =K21/$H$24 -> #VALUE!
B22: IVA | C22: =C21*19% -> 713597.25 | D22: =D21*19% -> 629329.59 | E22: =E21*19% -> 629318.76 | G22: 48900 | H22: =G22*7 -> 342300 | I22: 342300 | J22: =I22*9% -> 30807 | K22: IVA 19 % | O22: =I22/$H$24 -> #DIV/0! | P22: =K22/$H$24 -> #VALUE!
C23: =C21-C22 -> 3042177.8 | D23: =D21-D22 -> 2682931.4 | E23: =E21-E22 -> 2682885.2 | G23: =G21+G22 -> 402150.57 | H23: =H21+H22 -> 2815054 | I23: =I21-I22 -> 2969904 | O23: =I23/$H$24 -> #DIV/0! | P23: =J23/$H$24 -> #DIV/0!
A24: RESERVO Y PRE PAGO | B24: X NOCHE | C24: =C23/7 -> 434596.82 | D24: =D23/7 -> 383275.92 | E24: =E23/7 -> 383269.32 | I24: =I23/7 -> 424272
A25: COBRAN | B25: x NOCHE | C25: 455393 | D25: 402000 | E25: 402000 | I25: 402000 | O25: =SUM(O20:O24) -> #REF! | P25: =SUM(P20:P23) -> #VALUE!
C26: =C25-C24 -> 20796.179 | D26: =D25-D24 -> 18724.084 | E26: =E25-E24 -> 18730.68 | F26: TOTAL | H26: =H21*19% -> 469823.26 | I26: =I25-I24 -> -22272
A27: DIFERENCIA | B27: 7 NOCHES | C27: =C26*7 -> 145573.25 | D27: =D26*7 -> 131068.59 | E27: =E26*7 -> 131114.76 | F27: =SUM(C27:E27) -> 407756.6 | I27: =I26*7 -> -155904
C29: =C24/3800 -> 114.36758 | D29: =D24/3800 -> 100.86208 | E29: =E24/3800 -> 100.86035
A30: 353250.57 2,472,754.00 2472754.00 11/08/2025 7 Restaurante incluido en tarifa 48900.00
B68: RAISON | C68: ANTHONY | D68: REEMY
B69: 2815054 | C69: 2815054 | D69: 3187755
A70: RETENCIÓN 3.5% | B70: =B69*3.5% -> 98526.89 | C70: =C69*3.5% -> 98526.89 | D70: =D69*3.5% -> 111571.43
A71: VALOR A PAGAR | B71: =B69-B70 -> 2716527.1 | C71: =C69-C70 -> 2716527.1 | D71: =D69-D70 -> 3076183.6 | E71: =SUM(B71:D71) -> 8509237.8 | F71: TOTAL
E72: 7700000 | F72: DEPÓSITO
E73: =E71-7700000 -> 809237.8 | F73: SALDO A PAGAR
B76: RAISON | C76: ANTHONY | D76: REEMY
B77: =(337286+48900)*7 -> 2703302 | C77: =(337286+48900)*7 -> 2703302 | D77: =(369429+48900)*7 -> 2928303
A80: RETENCIÓN 3.5% | B80: =B77*3.5% -> 94615.57 | C80: =C77*3.5% -> 94615.57 | D80: =D77*3.5% -> 102490.6
A81: VALOR A PAGAR | B81: =B77-B80 -> 2608686.4 | C81: =C77-C80 -> 2608686.4 | D81: =D77-D80 -> 2825812.4 | E81: =SUM(B81:D81) -> 8043185.3 | F81: TOTAL
E82: 7700000 | F82: DEPÓSITO
E83: =E81-7700000 -> 343185.26 | F83: SALDO A PAGAR

Sheet VUELOS
A1: 2302151378519
J5: HT61EF
K25: ACU00W
N33: 06:00 am
N34: 07:00 am
N35: 0.34375
N36: 09:15 am
