Workbook

Sheet PASAPORTE DATOS 
G14: Nombre | H14: Urvjn
G15: Apellido | H15: Faneijte
E16: KEVIN JONATHAN | G16: Telefóno | H16: 315 772 1914
G17: e-mail | H17: reservasmedical@gmail.com
A18: Nombre | B18: Urvin | D18: Nombre | E18: Stephen | G18: Nombre | H18: Urvjn | J18: Nombre | K18: Stephen
A19: Nombre | D19: Nombre | G19: Apellido | H19: Faneijte
A20: Apellido | B20: Faneijte | D20: Apellido | E20: ⁠Faneijte | G20: Género: . | H20: Masculino | J20: Apellido | K20: ⁠Faneijte
G21: Pasaporte | H21: NV953KL62 | J21: Género: . | K21: Masculino
A22: Género: . | B22: Masculino | D22: Género: . | E22: Masculino | G22: Fecha de nacimiento | H22: 23888 | J22: Pasaporte | K22: ⁠NRB56CJP6
A23: Pasaporte | B23: NV953KL62 | D23: Pasaporte | E23: NRB56CJP6 | G23: Edad | H23: 60 años | J23: Fecha de nacimiento | K23: ⁠04-03-1999
A24: Fecha de nacimiento | B24: 23888 | D24: Fecha de nacimiento | E24: ⁠04-03-1999 | G24: Dirección | H24: Curazao | J24: Edad | K24: 26 AÑOS
A25: Edad | B25: 60 años | D25: Edad | E25: 26 AÑOS | G25: Peso | H25: 160 kilos IMC: 51,77 kg Obesidad de grado 3 | J25: Peso | K25: ⁠62kg
A26: Estado civil | D26: Estado civil | G26: Altura | H26: 1,76 | J26: Altura | K26: ⁠170cm
A27: Dirección | B27: Curazao | D27: Dirección | E27: Curazao | G27: Telefóno | H27: 315 772 1914
A28: Nacionalidad y domicilio: | D28: Nacionalidad y domicilio: | G28: e-mail | H28: reservasmedical@gmail.com
A29: Email: | B29: stephen.8@live.com | D29: Email: | E29: ⁠Stephen.8@live.com
A30: Teléfono | D30: Teléfono
A31: Profesión | D31: Profesión
A32: RH | B32: no tengo | D32: RH
A33: Seguro | D33: Seguro
A34: Peso | B34: 160 kilos IMC: 51,77 kg Obesidad de grado 3 | D34: Peso | E34: ⁠62kg
A35: Altura | B35: 1,76 | D35: Altura | E35: ⁠170cm
A36: Idioma | B36: inglés, español, holandés. | D36: Idioma | G36: Idioma | H36: inglés, español, holandés.
A37: Estadia: | G37: Estadia:
D38: Salud
G40: Nombre | H40: Stephen
G41: Apellido | H41: ⁠Faneijte
G42: Género: . | H42: Masculino
G43: Pasaporte | H43: NRB56CJP6
G44: Fecha de nacimiento | H44: ⁠04-03-1999
G45: Edad | H45: 26 AÑOS
G46: Peso | H46: ⁠62kg
G47: Altura | H47: ⁠170cm
G48: Telefóno | H48: 315 772 1914
G49: e-mail | H49: reservasmedical@gmail.com

Sheet COSTEO
Z2: Libro diario contable
D3: PAGOS | R3: PAGOS | W3: ESTADO DE CUENTA | Z3: PAGOS
B4: ACV documentos URVIN | C4: ACV documentos STEPHEN | D4: Contabilidad | E4: Operativo | F4: Concepto | G4: Proveedor | H4: Valor | I4: Días | J4: Urvin | K4: Stephen | M4: Urvin | N4: Stephen | O4: Urvin | P4: Stephen | R4: Urvin | S4: Stephen | T4: Retención en la fuente | U4: Valor pagado | W4: Valor Neto cobrado al cliente | X4: DIFERENCIA | Z4: PROVEEDOR - NOMBRE COMERCIAL | AA4: ID | AB4: Fecha del pago | AC4: Valor del pago | AD4: Forma de pago de donde salió el dinero | AE4: Tipo de movimiento | AF4: Comentarios
B5: App | C5: App | D5: Pre compra | E5: Emitida | F5: Póliza de asistencia médica al viajero - producto visitor por 07 días | G5: Colasistencia | H5: 3500 | I5: 7 | J5: =H5*I5 -> 24500 | K5: =H5*I5 -> 24500 | M5: =J5/0.7 -> 35000 | N5: =K5/0.7 -> 35000 | O5: =M5/$I$80 -> 9.2105263 | P5: =N5/$I$80 -> 9.2105263 | R5: =2750*7 -> 19250 | S5: =2750*7 -> 19250 | T5: 0 | U5: =R5+S5 -> 38500 | W5: =J5+K5 -> 49000 | X5: =W5-R5-S5 -> 10500
F6: PAQUETE DE CHEQUEO MÉDICO | J6: 1300000 | K6: 1300000 | O6: 470 | P6: 470
F7: LABORATORIOS CLÍNICOS | T7: 0 | U7: =R7+S7 -> 0 | W7: =SUM(J6:J55) -> 2699000 | X7: =W7-R7-S7 -> 2699000 | Z7: CIMA OCUPACIONAL | AB7: SALDO A FAVOR
B8: Archivado | C8: Archivado | D8: FACTURADO | E8: Confirmado | F8: Antígeno de próstata | G8: CIMA | T8: 0 | U8: =R8+S8 -> 0 | W8: =SUM(K6:K56) -> 1300000 | X8: =W8-R8-S8 -> 1300000
B9: Archivado | C9: Archivado | D9: FACTURADO | E9: Confirmado | F9: Coprológico | G9: ECHAVARRIA | Z9: JOHANNS CAJA MENOR | AB9: 45950 | AC9: 16000 | AD9: Efectivo
B10: Archivado | C10: Archivado | D10: FACTURADO | E10: Confirmado | F10: Vitamina D25 | G10: CIMA
B11: Archivado | C11: Archivado | D11: FACTURADO | E11: Confirmado | F11: Vitamina B12 | G11: CIMA
F12: Perfil lipídico
B13: Archivado | C13: Archivado | D13: FACTURADO | E13: Confirmado | F13: Colesterol HDL | G13: CIMA
B14: Archivado | C14: Archivado | D14: FACTURADO | E14: Confirmado | F14: Colesterol LDL | G14: CIMA
B15: Archivado | C15: Archivado | D15: FACTURADO | E15: Confirmado | F15: Colesterol total | G15: CIMA
B16: Archivado | C16: Archivado | D16: FACTURADO | E16: Confirmado | F16: Triglicéridos | G16: CIMA
F17: Perfil Hepático
B18: Archivado | C18: Archivado | D18: FACTURADO | E18: Confirmado | F18: ALT- Alanina transferasa | G18: CIMA
B19: Archivado | C19: Archivado | D19: FACTURADO | E19: Confirmado | F19: AST - aspartato transferasa | G19: CIMA
B20: Archivado | C20: Archivado | D20: FACTURADO | E20: Confirmado | F20: Bilirrubina total y directa | G20: CIMA
B21: Archivado | C21: Archivado | D21: FACTURADO | E21: Confirmado | F21: Gama Glutamil transferasa | G21: CIMA
F22: Perfil Renal
B23: Archivado | C23: Archivado | D23: FACTURADO | E23: Confirmado | F23: Creatinina | G23: CIMA
B24: Archivado | D24: FACTURADO | E24: Confirmado | F24: e-GFR | G24: CIMA | H24: 10000 | I24: 1 | J24: =H24*I24 -> 10000 | K24: No | M24: =J24/0.6 -> 16666.667 | O24: =M24/$I$80 -> 4.3859649 | P24: No
B25: Archivado | C25: Archivado | D25: FACTURADO | E25: Confirmado | F25: Uroanálisis | G25: CIMA
B26: Archivado | C26: Archivado | D26: FACTURADO | E26: Confirmado | F26: Nitrógeno Ureico en Sangre (BUN) | G26: CIMA
B27: Archivado | D27: FACTURADO | E27: Confirmado | F27: Proteina 24 horas | G27: ECHAVARRIA | H27: 20000 | I27: 1 | J27: =H27*I27 -> 20000 | K27: No | M27: =J27/0.6 -> 33333.333 | O27: =M27/$I$80 -> 8.7719298 | P27: No
F28: Sangre
B29: Archivado | C29: Archivado | D29: FACTURADO | E29: Confirmado | F29: Hemograma completo | G29: CIMA
B30: Archivado | C30: Archivado | D30: FACTURADO | E30: Confirmado | F30: Hemoglobina glicosilada | G30: CIMA
B31: Archivado | C31: Archivado | D31: FACTURADO | E31: Confirmado | F31: Ferritina | G31: CIMA
B32: Archivado | C32: Archivado | D32: FACTURADO | E32: Confirmado | F32: Glucosa sérica | G32: CIMA
B33: Archivado | D33: FACTURADO | E33: Confirmado | F33: Tipo de sangre | G33: CIMA | H33: 20000 | I33: 1 | J33: =H33*I33 -> 20000 | K33: No | M33: =J33/0.6 -> 33333.333 | O33: =M33/$I$80 -> 8.7719298 | P33: No
B34: Archivado | D34: FACTURADO | E34: Confirmado | F34: Frotis de sangre periférica - (extendido de sangre periférica estudio de morfología) | G34: CIMA | H34: 45000 | I34: 1 | J34: =H34*I34 -> 45000 | K34: No | M34: =J34/0.6 -> 75000 | O34: =M34/$I$80 -> 19.736842 | P34: No
D35: FACTURADO | E35: Confirmado | F35: Test de sicklemia: (Células Falciformes-drepanocitosis) | G35: CIMA | H35: 40000 | I35: 1 | J35: =H35*I35 -> 40000 | K35: No | M35: =J35/0.6 -> 66666.667 | O35: =M35/$I$80 -> 17.54386 | P35: No
B36: OK RESULTADO | F36: Perfil Tiroideo
B37: Archivado | C37: Archivado | D37: FACTURADO | E37: Confirmado | F37: T4 libre | G37: CIMA
B38: Archivado | C38: Archivado | D38: FACTURADO | E38: Confirmado | F38: TSH | G38: CIMA
B39: Archivado | D39: FACTURADO | E39: Confirmado | F39: Paratohormona | G39: CIMA | H39: 116000 | I39: 1 | J39: =H39*I39 -> 116000 | K39: No | M39: =J39/0.8 -> 145000 | O39: =M39/$I$80 -> 38.157895 | P39: No
F40: Enfermedades de transmisión sexual
B41: Archivado | C41: Archivado | D41: FACTURADO | E41: Confirmado | F41: VDRL | G41: CIMA
B42: Archivado | C42: Archivado | D42: FACTURADO | E42: Confirmado | F42: VIH 1 Y 2, Anticuerpos | G42: CIMA
F43: Minerales
B44: Archivado | D44: FACTURADO | E44: Confirmado | F44: Fosforo | G44: CIMA | H44: 10000 | I44: 1 | J44: =H44*I44 -> 10000 | K44: No | M44: =J44/0.6 -> 16666.667 | N44: No | O44: =M44/$I$80 -> 4.3859649 | P44: No
B45: Archivado | D45: FACTURADO | E45: Confirmado | F45: Ionograma: calcio - sodio - cloro- potasio | G45: CIMA | H45: 90000 | I45: 1 | J45: =H45*I45 -> 90000 | K45: No | M45: =J45/0.8 -> 112500 | N45: No | O45: =M45/$I$80 -> 29.605263 | P45: No
F46: Corazón
B47: Archivado | D47: FACTURADO | E47: Confirmado | F47: Homocisteína | G47: CIMA | H47: 108000 | I47: 1 | J47: =H47*I47 -> 108000 | K47: No | M47: =J47/0.8 -> 135000 | N47: No | O47: =M47/$I$80 -> 35.526316 | P47: No
F48: IMÁGENES DIAGNÓSTICAS
B49: Archivado | C49: Archivado | D49: FACTURADO | E49: Confirmado | F49: Radiografía de tórax | G49: CIMA
B50: Archivado | C50: Archivado | D50: FACTURADO | E50: Confirmado | F50: Ecografía de abdomen total | G50: CIMA
B51: Archivado | C51: Archivado | D51: FACTURADO | E51: Confirmado | F51: Electrocardiograma | G51: CIMA
B52: Archivado | D52: FACTURADO | E52: Confirmado | F52: Ecocardiografía | G52: CIMA | H52: 320000 | I52: 1 | J52: =H52*I52 -> 320000 | K52: No | M52: =J52/0.8 -> 400000 | N52: No | O52: =M52/$I$80 -> 105.26316 | P52: No
B53: Archivado | D53: FACTURADO | E53: Confirmado | F53: Doppler venoso miembros inferiores | G53: CIMA | H53: 250000 | I53: 1 | J53: =H53*I53 -> 250000 | K53: No | M53: =J53/0.8 -> 312500 | N53: No | O53: =M53/$I$80 -> 82.236842 | P53: No
B54: Archivado | D54: FACTURADO | E54: Confirmado | F54: Doppler Arterial miembros inferiores | G54: CIMA | H54: 270000 | I54: 1 | J54: =H54*I54 -> 270000 | K54: No | M54: =J54/0.8 -> 337500 | N54: No | O54: =M54/$I$80 -> 88.815789 | P54: No
B55: Archivado | D55: FACTURADO | E55: Confirmado | F55: Radiografía comparativa de caderas | G55: CIMA | H55: 100000 | I55: 1 | J55: =H55*I55 -> 100000 | K55: No | M55: =J55/0.8 -> 125000 | N55: No | O55: =M55/$I$80 -> 32.894737 | P55: No
B56: Archivado | D56: FACTURADO | E56: Confirmado | F56: Tomografía de columna lumbar | G56: IVS | H56: 280000 | I56: 1 | J56: =H56*I56 -> 280000 | K56: No | M56: =J56/0.8 -> 350000 | N56: No | O56: =M56/$I$80 -> 92.105263 | P56: No | R56: 195040 | T56: =R56*2% -> 3900.8 | U56: =R56-T56 -> 191139.2 | W56: =J56 -> 280000 | X56: =W56-R56 -> 84960 | Z56: IVS | AB56: 45947 | AC56: 191139 | AD56: JURIDICA BANCOLOMBIA | AE56: TRANSFERENCIA
B57: Archivado | D57: FACTURADO | E57: Confirmado | F57: Electromiografía miembros INFERIORES con NCS (Nerve Conduction Studies) | G57: IPS | H57: $240,000 | I57: 1 | J57: =H57*I57 -> 240000 | K57: No | M57: =J57/0.8 -> 300000 | N57: No | O57: =M57/$I$80 -> 78.947368 | P57: No | R57: 270000 | T57: 0 | U57: =R57+S57 -> 270000 | W57: =J57 -> 240000 | X57: =W57-R57 -> -30000 | Z57: IPS ELECTRODIAGNOSTICO | AB57: 45947 | AC57: =260000+270000 -> 530000 | AD57: JURIDICA BANCOLOMBIA | AE57: TRANSFERENCIA
F58: ESPECIALISTAS | Z58: Juan Fernando Velazquez | AB58: 45951 | AC58: 320000 | AD58: JURIDICA BANCOLOMBIA | AE58: TRANSFERENCIA
B59: Archivado | D59: Pagado | E59: Confirmado | F59: Consulta con CARDIOLOGÍA | G59: HPTU | K59: No | P59: No | T59: 0 | U59: =R59+S59 -> 0 | Z59: NILSON LOPEZ | AB59: 45951 | AC59: 350000 | AD59: JURIDICA BANCOLOMBIA | AE59: TRANSFERENCIA
D60: Pagado | E60: Confirmado | F60: Consulta con INTERNISTA | G60: HPTU | J60: No | O60: No | T60: 0 | U60: =R60+S60 -> 0 | Z60: NILSON LOPEZ | AB60: 45951 | AC60: 350000 | AD60: JURIDICA BANCOLOMBIA | AE60: TRANSFERENCIA
B61: Archivado | D61: FACTURADO | E61: Confirmado | F61: Consulta con FISIATRÍA | G61: IPS | H61: 280000 | I61: 1 | J61: =H61*I61 -> 280000 | K61: No | M61: =J61/0.9 -> 311111.11 | N61: No | O61: =M61/$I$80 -> 81.871345 | P61: No | R61: 260000 | T61: 0 | U61: =R61+S61 -> 260000 | W61: =J61 -> 280000 | X61: =W61-R61 -> 20000
B62: Archivado | D62: FACTURADO | E62: Confirmado | F62: Consulta con ORTOPEDIA | G62: ORVÉ | H62: 280000 | I62: 1 | J62: =H62*I62 -> 280000 | K62: No | M62: =J62/0.9 -> 311111.11 | N62: No | O62: =M62/$I$80 -> 81.871345 | P62: No | R62: 290000 | T62: 0 | U62: =R62+S62 -> 290000 | W62: =J62 -> 280000 | X62: =W62-R62 -> -10000 | Z62: ORVÉ | AB62: 45947 | AC62: 290000 | AD62: JURIDICA BANCOLOMBIA | AE62: TRANSFERENCIA
B63: Archivado | D63: FACTURADO | E63: Confirmado | F63: Consulta con PODOLOGÍA | G63: Scholl | H63: 280000 | I63: 1 | J63: =H63*I63 -> 280000 | K63: No | M63: =J63/0.9 -> 311111.11 | N63: No | O63: =M63/$I$80 -> 81.871345 | P63: No | R63: 280000 | T63: =R63*2% -> 5600 | U63: =R63-T63 -> 274400 | W63: =J63 -> 280000 | X63: =W63-R63 -> 0 | Z63: SCHOLL PODOLOGO | AB63: 45951 | AC63: 274400 | AD63: JURIDICA BANCOLOMBIA | AE63: TRANSFERENCIA
B64: Archivado | D64: Pagado | E64: Confirmado | F64: Consulta con UROLOGÍA | G64: HPTU | H64: 300000 | I64: 1 | J64: =H64*I64 -> 300000 | K64: No | M64: =J64/0.95 -> 315789.47 | N64: No | O64: =M64/$I$80 -> 83.102493 | P64: No | R64: 300000 | T64: 0 | U64: =R64-T64 -> 300000 | W64: =J64 -> 300000 | X64: =W64-R64 -> 0 | Z64: FEDERICO GAVIRIA | AB64: 45951 | AC64: 300000 | AD64: JURIDICA BANCOLOMBIA | AE64: TRANSFERENCIA
B65: Archivado | D65: FACTURADO | E65: Confirmado | F65: Consulta con VIRTUAL DE PRIMERA VEZ Dr. Marcos Yepes | G65: Dr Marcos Yépes | H65: 150000 | I65: 1 | J65: =H65*I65 -> 150000 | K65: No | M65: =J65/0.95 -> 157894.74 | N65: No | O65: =M65/$I$80 -> 41.551247 | P65: No | R65: 150000 | T65: =R65*4% -> 6000 | U65: =R65-T65 -> 144000 | W65: =J65 -> 150000 | X65: =W65-R65 -> 0 | Z65: DR MARCOS YEPES
D66: FACTURADO | E66: Confirmado | F66: Consulta con VIRTUAL DE CONTROL Dr. Marcos Yepes - revisión de resultados | G66: Dr Marcos Yépes | H66: 150000 | I66: 1 | J66: =H66*I66 -> 150000 | K66: No | M66: =J66/0.95 -> 157894.74 | N66: No | O66: =M66/$I$80 -> 41.551247 | P66: No | R66: 150000 | T66: =R66*4% -> 6000 | U66: =R66-T66 -> 144000 | W66: =J66 -> 150000 | X66: =W66-R66 -> 0 | Z66: DR MARCOS YEPES | AB66: 45953 | AC66: 144000 | AD66: JURIDICA BANCOLOMBIA | AE66: TRANSFERENCIA
D67: Pagado | E67: Confirmado | F67: Consulta con VIRTUAL DE NUTRICIÓN Y PSICO NUTRICIÓN | G67: Dr Marlen Villalba | H67: 270000 | I67: 2 | J67: =H67*I67 -> 540000 | K67: No | M67: =J67/0.95 -> 568421.05 | N67: No | O67: =M67/$I$80 -> 149.58449 | P67: No | R67: =270000*2 -> 540000 | T67: =R67*4% -> 21600 | U67: =R67-T67 -> 518400 | W67: =J67 -> 540000 | X67: =W67-R67 -> 0 | Z67: DRA MARLEN VILLALBA | AB67: 45956 | AC67: 518400 | AD67: YENNY EFECTIVO CAMBIO USD RVA215 | AE67: DEPÓSITO CORRESPONSAL
D68: FACTURADO | E68: Confirmado | F68: Consulta con VIRTUAL VASCULAR PERIFÉRICO | G68: Cardiovida | H68: 350000 | I68: 1 | J68: =H68*I68 -> 350000 | K68: No | M68: =J68/0.95 -> 368421.05 | N68: No | O68: =M68/$I$80 -> 96.952909 | P68: No | R68: =350000-35000 -> 315000 | T68: =R68*2% -> 6300 | U68: =R68-T68 -> 308700 | W68: =J68 -> 350000 | X68: =W68-R68 -> 35000 | Z68: CARDIOVIDA | AB68: 45955 | AC68: 308700 | AD68: JENNY - BANCOLOMBIA AHORROS | AE68: TRANSFERENCIA
D69: FACTURADO | E69: Confirmado | F69: Masaje de drenaje linfático | G69: Gilma | H69: 150000 | I69: 1 | J69: =H69*I69 -> 150000 | K69: No | M69: =J69/0.8 -> 187500 | N69: No | O69: =M69/$I$80 -> 49.342105 | P69: No | R69: 150000 | T69: =R69*6% -> 9000 | U69: =R69-T69 -> 141000 | Z69: GILMA | AB69: 45953 | AC69: 140000 | AD69: JURIDICA BANCOLOMBIA | AE69: TRANSFERENCIA
D70: Caja menor | E70: Confirmado | F70: Tarros para proteina 24 horas orina + orina uroanalisis y fecal | G70: Johanns | H70: 15000 | I70: 1 | J70: =H70*I70 -> 15000 | K70: 8000 | M70: =J70/0.95 -> 15789.474 | N70: =K70/0.95 -> 8421.0526 | O70: =M70/$I$80 -> 4.1551247 | P70: =N70/$I$80 -> 2.2160665 | T70: 0 | U70: =R70+S70 -> 0
E71: Confirmado | F71: 02 Traslados hotel - clínica por trayecto lejos | G71: Johanns | H71: 60000 | I71: 4 | J71: =H71*I71 -> 240000 | K71: No | M71: =J71/0.95 -> 252631.58 | N71: No | O71: =M71/$I$80 -> 66.481994 | P71: No | T71: 0 | U71: =R71+S71 -> 0
E72: Confirmado | F72: 04 Traslados hotel - clínica por trayecto Cortos - cerca | G72: Johanns | H72: 40000 | I72: 2 | J72: =H72*I72 -> 80000 | K72: No | M72: =J72/0.95 -> 84210.526 | N72: No | O72: =M72/$I$80 -> 22.160665 | P72: No | T72: 0 | U72: =R72+S72 -> 0
E73: Confirmado | F73: Servicios Medical Trip Colombia: Acompañamiento Virtual | G73: Dayana | H73: 180000 | I73: 0.75 | J73: =H73*I73 -> 135000 | M73: =J73/0.95 -> 142105.26 | O73: =M73/$I$80 -> 37.396122 | T73: 0 | U73: =R73+S73 -> 0
E74: Confirmado | F74: Servicios Medical Trip Colombia: Acompañamiento presencial | G74: Johanns | H74: 180000 | I74: 2 | J74: =H74*I74 -> 360000 | M74: =J74/0.95 -> 378947.37 | O74: =M74/$I$80 -> 99.722992 | T74: 0 | U74: =R74+S74 -> 0
D75: FACTURADO | E75: Confirmado | F75: Servicios Medical Trip Colombia: Enfermera por horas | G75: Salud en casa | H75: 220000 | I75: 1 | J75: =H75*I75 -> 220000 | M75: =J75/0.9 -> 244444.44 | O75: =M75/$I$80 -> 64.327485 | T75: 0 | U75: =R75+S75 -> 0 | Z75: Enfermero salud en casa | AB75: 45947 | AC75: 100000 | AD75: JURIDICA BANCOLOMBIA | AE75: TRANSFENCIA
E76: Confirmado | F76: Caja menor | H76: 20000 | I76: 1 | J76: =+H76*I76 -> 20000 | K76: =H76*I76 -> 20000 | T76: 0 | U76: =R76+S76 -> 0 | Z76: Enfermero salud en casa | AB76: 45948 | AC76: 110000 | AD76: JURIDICA BANCOLOMBIA | AE76: TRANSFENCIA
I77: Total neto | J77: =SUM(J5:J76) -> 6793500 | K77: =SUM(K5:K76) -> 1352500
I78: 0.15 | J78: =J77/0.84 -> 8087500 | K78: =K77/0.74 -> 1827702.7 | O78: =SUM(O5:O77) -> 2128.3026 | P78: =SUM(P5:P77) -> 481.42659
H79: Gastos bancarios | I79: 4 * 1000 | J79: =J78*4/1000 -> 32350 | K79: =K78*4/1000 -> 7310.8108 | O79: =J79/$I$80 -> 8.5131579 | P79: =K79/$I$80 -> 1.9238976
H80: Tasa del dólar | I80: 3800 | J80: =SUM(J78:J79) -> 8119850 | K80: =SUM(K78:K79) -> 1835013.5 | O80: =SUM(O78:O79) -> 2136.8157 | P80: =SUM(P78:P79) -> 483.35049
J81: =J80/I80 -> 2136.8026 | K81: =K80/I80 -> 482.89829

Sheet PAGOS
B4: IVS TAC | D4: FISIATRIA Y ELECTROMIOGRAFIA | G4: ORTOPEDIA | I4: ENFERMERO | L4: enfermero | O4: CITA DE CONTROL MARCOSS
B24: DR MARCOS
B38: UROLOGO FEDERICO GAVIRIA | F38: CARDIOLOGO NILSON LOPEZ

Sheet ITINERARIO
D3: ITINERARIO: | F3: 17 - 23 OCTUBRE
C4: Dia | D4: Fecha | E4: Hora | F4: Actividad | G4: ACP horas | H4: Traslado cerca | I4: Traslado lejos
D5: 1 | E5: 45947 | F5: VIERNES
C6: OK | E6: 05:00 pm | F6: Vuelo Curazao - Medellín
C7: El pasajero lo hace por su cuenta | F7: Traslado a aeropuerto - hotel
F8: Alojamiento
D9: 2 | E9: 45948 | F9: SÁBADO | K9: ORVIN
F10: No desayunar - tomar agua - Tennis - ropa cómoda | K10: Laboratorios clínicos | L10: 10/18/2025 | M10: 06:45 AM
A11: CIMA | B11: Johanns | C11: Confirmado | D11: Stephen -Urvin | E11: 6:30 am | F11: Traslado Hotel - Centro médico | G11: 0.5 | H11: 1 | K11: Ecografía de abdomen total | L11: 10/18/2025 | M11: 07:00 AM
C12: Confirmado | D12: Stephen -Urvin | E12: 06:45 am | F12: Toma de muestras de sangre laboratorio clínico | K12: Doppler venoso miembros inferiores | L12: 10/18/2025 | M12: 07:00 AM
C13: Confirmado | D13: Stephen -Urvin | E13: 07:00 am | F13: Ecografía de abdomen total | K13: Doppler Arterial miembros inferiores | L13: 10/18/2025 | M13: 07:00 AM
C14: Confirmado | D14: Urvin | F14: Ecocardiografía | K14: Ecocardiografía | L14: 10/18/2025 | M14: 07:15 AM
C15: Confirmado | D15: Stephen -Urvin | F15: Radiografía de tórax | K15: Prueba de esfuerzo | L15: 10/18/2025 | M15: 07:15 AM
C16: Confirmado | D16: Stephen -Urvin | F16: Electrocardiograma | K16: Radiografía comparativa de caderas | L16: 10/18/2025 | M16: 08:00 AM
E17: 08:00 am | F17: Tiempo para comer | K17: Radiografía de tórax | L17: 10/18/2025 | M17: 08:00 AM
C18: No se realizó | D18: Urvin | F18: Prueba de esfuerzo | K18: Electrocardiograma | L18: 10/18/2025 | M18: 08:20AM
C19: Confirmado | D19: Urvin | F19: Doppler venoso miembros inferiores
C20: Confirmado | D20: Urvin | F20: Doppler Arterial miembros inferiores
C21: Confirmado | D21: Urvin | F21: Radiografía comparativa de caderas | K21: STEPHEN
B22: Johanns | C22: Confirmado | E22: 10:00 am | F22: Traslado Centro médico - Hotel | H22: 1 | K22: Laboratorios clínicos | L22: 10/18/2025 | M22: 06:45 AM
F23: TARDE LIBRE | K23: Radiografía de tórax | L23: 10/18/2025 | M23: 07:00 AM
D24: 3 | E24: 45949 | F24: DOMINGO | K24: Ecografía de abdomen total | L24: 10/18/2025 | M24: 07:20 AM
E25: 07:00 am | F25: Desayuno en el hotel | K25: Electrocardiograma | L25: 10/18/2025 | M25: 08:20AM
B26: Johanns | C26: Confirmado | E26: 08:00 am | F26: Traslado Hotel - Centro médico | G26: 0.25 | H26: 1
A27: CALLE 80 | B27: IVS | C27: Confirmado | D27: Urvin | E27: 09:00 am | F27: Tomografía de columna lumbar
B28: Johanns | C28: Confirmado | E28: 10:00 am | F28: Traslado Centro médico - Hotel | H28: 1
F29: TARDE LIBRE
D30: 4 | E30: 45950 | F30: LUNES
F31: Desayuno en el hotel
B32: Johanns | C32: Confirmado | E32: 10:15 am | F32: Traslado Hotel - Centro médico | G32: 0.5 | H32: 1
A33: Poblado - Clínica Las Vegas | B33: ORVÉ | C33: Confirmado | D33: Urvin | E33: 11:00 am | F33: Consulta con especialista en ORTOPEDIA
A34: Poblado - Torre Médica Salud Las Vegas | B34: IPS electrodiagnóstico | C34: Confirmado | D34: Urvin | E34: 12:00 pm | F34: Electromiografía miembros INFERIORES con NCS (Nerve Conduction Studies)
A35: Poblado - Torre Médica Salud Las Vegas | B35: IPS electrodiagnóstico | C35: Confirmado | D35: Urvin | E35: 01:00 pm | F35: Consulta con especialista en FISIATRÍA
B36: Johanns | C36: Confirmado | E36: 02:00 pm | F36: Traslado Hotel - Centro médico | H36: 1
F37: Tiempo para almorzar
D38: 5 | E38: 45951 | F38: MARTES
F39: Desayuno en el hotel
A40: Domicilio | B40: Scholl | C40: Confirmado | D40: Urvin | E40: 10:00 am | F40: Consulta a domicilio en su hotel con especialista en PODOLOGÍA | G40: 1
F41: Tiempo para almorzar
B42: Johanns | C42: Confirmado | E42: 12:45 pm | F42: Traslado Hotel - Centro médico | I42: 1
A43: Robledo | B43: HPTU | C43: Confirmado | D43: Urvin | E43: 01:30 pm | F43: Consulta con especialista en UROLOGÍA
A44: Robledo | B44: HPTU | C44: Confirmado | D44: Urvin | E44: 03:30 pm | F44: Consulta con especialista en CARDIOLOGÍA
A45: Robledo | B45: HPTU | C45: Confirmado | D45: Stephen | E45: 04:00 pm | F45: Consulta con especialista en INTERNISTA
B46: Johanns | C46: Confirmado | F46: Traslado Centro médico - Hotel | I46: 1
D47: 6 | E47: 45952 | F47: MIÉRCOLES
F48: Tiempo para desayunar
E49: 10:00 am | F49: Traslado Hotel - Centro médico | G49: 0.5 | H49: 1
A50: El POBLADO | B50: Scholl | F50: Consulta con Podología
F51: Traslado Centro médico - Hotel | H51: 1
E52: 12:00 pm | F52: Masaje
F53: TARDE LIBRE
D54: 7 | E54: 45953 | F54: JUEVES
F55: Desayuno en el hotel
C56: Pasajero directamente | F56: Traslado hotel - aeropuerto
F57: Vuelo internacional Curazao - Medellín
G58: =SUM(G5:G57) -> 2.75 | H58: =SUM(H5:H57) -> 8 | I58: =SUM(I5:I57) -> 2
F59: Chequeo incluido | G59: 0.75 | H59: 4 | I59: 0
G60: =G58-G59 -> 2 | H60: =H58-H59 -> 4 | I60: =I58-I59 -> 2
E62: 45955 | F62: SÁBADO
E63: 09:00 am | F63: Consulta virtual Vascular Periférico
F64: Consulta virtual con Nutrición
F65: Consulta virtual con Dr Marcos Yépes de control

Sheet DETALLE SERVICIOS
B2: CONCEPTO | C2: URVIN | D2: STEPHEN
B3: =COSTEO!F5 -> Póliza de asistencia médica al viajero - producto visitor por 07 días | C3: =COSTEO!O5 -> 9.2105263 | D3: =COSTEO!P5 -> 9.2105263
B4: =COSTEO!F6 -> PAQUETE DE CHEQUEO MÉDICO | C4: =COSTEO!O6 -> 470 | D4: =COSTEO!P6 -> 470
B5: =COSTEO!F7 -> LABORATORIOS CLÍNICOS | C5: =COSTEO!O7 | D5: =COSTEO!P7
B6: =COSTEO!F8 -> Antígeno de próstata | C6: =COSTEO!O8 | D6: =COSTEO!P8
B7: =COSTEO!F9 -> Coprológico | C7: =COSTEO!O9 | D7: =COSTEO!P9
B8: =COSTEO!F10 -> Vitamina D25 | C8: =COSTEO!O10 | D8: =COSTEO!P10
B9: =COSTEO!F11 -> Vitamina B12 | C9: =COSTEO!O11 | D9: =COSTEO!P11
B10: =COSTEO!F12 -> Perfil lipídico | C10: =COSTEO!O12 | D10: =COSTEO!P12
B11: =COSTEO!F13 -> Colesterol HDL | C11: =COSTEO!O13 | D11: =COSTEO!P13
B12: =COSTEO!F14 -> Colesterol LDL | C12: =COSTEO!O14 | D12: =COSTEO!P14
B13: =COSTEO!F15 -> Colesterol total | C13: =COSTEO!O15 | D13: =COSTEO!P15
B14: =COSTEO!F16 -> Triglicéridos | C14: =COSTEO!O16 | D14: =COSTEO!P16
... B50: =COSTEO!F52 -> Ecocardiografía | C50: =COSTEO!O52 -> 105.26316 | D50: =COSTEO!P52 -> No
B51: =COSTEO!F56 -> Tomografía de columna lumbar | C51: =COSTEO!O56 -> 92.105263 | D51: =COSTEO!P56 -> No
B52: =COSTEO!F53 -> Doppler venoso miembros inferiores | C52: =COSTEO!O53 -> 82.236842 | D52: =COSTEO!P53 -> No
B53: =COSTEO!F54 -> Doppler Arterial miembros inferiores | C53: =COSTEO!O54 -> 88.815789 | D53: =COSTEO!P54 -> No
B54: =COSTEO!F55 -> Radiografía comparativa de caderas | C54: =COSTEO!O55 -> 32.894737 | D54: =COSTEO!P55 -> No
B55: =COSTEO!F57 -> Electromiografía miembros INFERIORES con NCS (Nerve Conduction Studies) | C55: =COSTEO!O57 -> 78.947368 | D55: =COSTEO!P57 -> No
B56: =COSTEO!F58 -> ESPECIALISTAS | C56: =COSTEO!O58 | D56: =COSTEO!P58
B57: =COSTEO!F59 -> Consulta con CARDIOLOGÍA | C57: =COSTEO!O59 | D57: =COSTEO!P59 -> No
B58: =COSTEO!F60 -> Consulta con INTERNISTA | C58: =COSTEO!O60 -> No | D58: =COSTEO!P60
B59: =COSTEO!F61 -> Consulta con FISIATRÍA | C59: =COSTEO!O61 -> 81.871345 | D59: =COSTEO!P61 -> No
B60: =COSTEO!F62 -> Consulta con ORTOPEDIA | C60: =COSTEO!O62 -> 81.871345 | D60: =COSTEO!P62 -> No
B61: =COSTEO!F63 -> Consulta con PODOLOGÍA | C61: =COSTEO!O63 -> 81.871345 | D61: =COSTEO!P63 -> No
B62: =COSTEO!F64 -> Consulta con UROLOGÍA | C62: =COSTEO!O64 -> 83.102493 | D62: =COSTEO!P64 -> No
B63: =COSTEO!F65 -> Consulta con VIRTUAL DE PRIMERA VEZ Dr. Marcos Yepes | C63: =COSTEO!O65 -> 41.551247 | D63: =COSTEO!P66 -> No
B64: =COSTEO!F66 -> Consulta con VIRTUAL DE CONTROL Dr. Marcos Yepes - revisión de resultados | C64: =COSTEO!O66 -> 41.551247 | D64: =COSTEO!P67 -> No
B65: =COSTEO!F67 -> Consulta con VIRTUAL DE NUTRICIÓN Y PSICO NUTRICIÓN | C65: =COSTEO!O67 -> 149.58449 | D65: =COSTEO!P68 -> No
B66: =COSTEO!F68 -> Consulta con VIRTUAL VASCULAR PERIFÉRICO | C66: =COSTEO!O68 -> 96.952909 | D66: =COSTEO!P69 -> No
B67: =COSTEO!F69 -> Masaje de drenaje linfático | C67: =COSTEO!O69 -> 49.342105
B68: =COSTEO!F70 -> Tarros para proteina 24 horas orina + orina uroanalisis y fecal | C68: =COSTEO!O70 -> 4.1551247 | D68: =COSTEO!P70 -> 2.2160665
B69: =COSTEO!F71 -> 02 Traslados hotel - clínica por trayecto lejos | C69: =COSTEO!O71 -> 66.481994
B70: =COSTEO!F72 -> 04 Traslados hotel - clínica por trayecto Cortos - cerca | C70: =COSTEO!O72 -> 22.160665
B71: =COSTEO!F73 -> Servicios Medical Trip Colombia: Acompañamiento Virtual | C71: =COSTEO!O73 -> 37.396122 | D71: =COSTEO!P73
B72: =COSTEO!F74 -> Servicios Medical Trip Colombia: Acompañamiento presencial | C72: =COSTEO!O74 -> 99.722992 | D72: =COSTEO!P74
B73: =COSTEO!F75 -> Servicios Medical Trip Colombia: Enfermera por horas | C73: =COSTEO!O75 -> 64.327485
B74: 4 * 1000 impuesto bancario en Colombia | C74: =COSTEO!O79 -> 8.5131579 | D74: =COSTEO!P79 -> 1.9238976
B75: TOTAL A PAGAR EN DÓLARES | C75: =SUM(C3:C74) -> 2136.8157 | D75: =SUM(D3:D74) -> 483.35049
B76: =COSTEO!F78
B77: TOTAL A PAGAR EN DÓLARES | C77: =C75+D75 -> 2620.1662
B78: Pago con tarjeta 6% | C78: =C77*6% -> 157.20997
B79: TOTAL A PAGAR | C79: =C77+C78 -> 2777.3762
B80: =COSTEO!F82 | C80: 2400
B81: =COSTEO!F83 | C81: =C79-C80 -> 377.37618
B82: =COSTEO!F82
B83: =COSTEO!F83
B84: =COSTEO!F84
B85: =COSTEO!F85
B86: =COSTEO!F86
B87: =COSTEO!F87
B88: =COSTEO!F88
B89: =COSTEO!F89
B90: =COSTEO!F90
B91: =COSTEO!F91
B92: =COSTEO!F92
B93: =COSTEO!F93
... B97: =COSTEO!F97

Sheet CONFIRMACIÓN PAX 1
D2: 3148717994
D3: 3126246627
H20: 📌 PREPARACIÓN
H21: * Estar 30 min antes.
H23: 📌 Requisitos para la admisión: Importante traer todos los documentos físicos para agilizar el proceso de admisión.
H24: * Historia Clínica Y Orden Médica
H25: * Exámenes anteriores del área a evaluar
H26: * Documento de identidad
H28: NOTA ‼️: Favor tener en cuenta que si el paciente no llega con el tiempo anterior citado y/o acude a la hora exacta de la cita, no se garantiza la atención, dado que este requisito es indispensable en el proceso
H30: Gracias por elegirnos.
H31: Bienvenido a imagenes de vida y salud
D36: PRUEBA DE ESFUERZO INCARE

Sheet VUELO

Sheet CARPETA - ARCHIVO
A3: ARCHIVO DIGITAL | B3: LABORATORIOS CLÍNICOS | C3: ARCHIVO DIGITAL | D3: IMÁGENES DIAGNÓSTICAS | E3: ARCHIVO DIGITAL | F3: ESPECIALISTAS
